Workbook

Sheet Dashboard
C2: AUSTIN ENERGY COMBINED CONTACT CENTER CUSTOMER SATISFACTION
C6: REPORTING PERIOD | E6: Q2_2025
C8: UTILITY CALLING ABOUT | F8: IVR RATINGS | H8: PERCEPTIONS OF CSR | M8: OVERALL SATISFACTION RATING
C20: % Placed on Hold | E20: Time on Hold | J20: Comments from dissatisfied customer callbacks
C21: {=IFERROR(_xlfn._xlws.FILTER('[1]Customers Data'!C4:C1000,TEXT('[1]Customers Data'!B4:B1000,"MMMM")=E6),"")} | D21: {=IFERROR(_xlfn._xlws.FILTER('[1]Customers Data'!H4:H1000,TEXT('[1]Customers Data'!B4:B1000,"MMMM")=E6),"")} | E21: Less than 2 minutes | F21: Between 2 and 5 minutes

Sheet Customers Data
B3: Date | C3: Customer Name | D3: Email | E3: Purchase ID | F3: Product Satisfaction | G3: Delivery Satisfaction | H3: Overall Experience | I3: Avg Time to Solve An Issue | J3: Customer Satisfaction | K3: Customer Comments:
B4: 44927 | C4: John Smith | D4: john.smith@email.com | E4: WIAS123 | F4: 4.5 | G4: 4.7 | H4: 4.6 | I4: Less than 1 hour | J4: Neutral | K4: John Smith: "Great product quality! Fast delivery."
B5: 44928 | C5: Sarah Johnson | D5: sarah@email.com | E5: WIAS124 | F5: 4.8 | G5: 4.5 | H5: 4.65 | I5: 1-2 hours | J5: Neutral | K5: Sarah Johnson: "Love the variety. Could improve delivery tracking."
B6: 44929 | C6: Michael Davis | D6: michael@email.com | E6: WIAS125 | F6: 4.2 | G6: 4.6 | H6: 4.4 | I6: More than 2 hours | J6: Very Unsatisfied | K6: Michael Davis: "Satisfied overall, but sizing was a bit off."
B7: 44930 | C7: Emily White | D7: emily@email.com | E7: WIAS126 | F7: 4.9 | G7: 4.8 | H7: 4.85 | I7: 1-2 hours | J7: Unsatisfied | K7: Emily White: "Excellent service! Will shop again."
B8: 44959 | C8: Brian Thompson | D8: brian@email.com | E8: WIAS127 | F8: 4.7 | G8: 4.4 | H8: 4.55 | I8: Less than 1 hour | J8: Very Satisfied | K8: Brian Thompson: "Good prices, but product descriptions could be clearer."
B9: 44960 | C9: Jessica Turner | D9: jessica@email.com | E9: WIAS128 | F9: 4.6 | G9: 4.5 | H9: 4.55 | I9: Less than 1 hour | J9: Very Satisfied | K9: Jessica Turner: "Comfortable clothing. Delivery was on time."
B10: 44961 | C10: Kevin Miller | D10: kevin@email.com | E10: WIAS129 | F10: 4.3 | G10: 4.2 | H10: 4.25 | I10: Less than 1 hour | J10: Very Satisfied | K10: Kevin Miller: "Decent experience, but packaging could be more eco-friendly."
B11: 44962 | C11: Lauren Adams | D11: lauren@email.com | E11: WIAS130 | F11: 4.8 | G11: 4.7 | H11: 4.75 | I11: Less than 1 hour | J11: Satisfied | K11: Lauren Adams: "Highly satisfied. Good job on the new collection."
B12: 44963 | C12: Ryan Cooper | D12: ryan@email.com | E12: WIAS131 | F12: 4.5 | G12: 4.6 | H12: 4.55 | I12: Less than 1 hour | J12: Satisfied | K12: Ryan Cooper: "Quality products, but website navigation needs improvement."
B13: 44964 | C13: Ashley Parker | D13: ashley@email.com | E13: WIAS132 | F13: 4.7 | G13: 4.9 | H13: 4.8 | I13: 1-2 hours | J13: Neutral | K13: Ashley Parker: "Amazing experience. Will recommend to friends."

Sheet Chart Data
H1: {=INDEX('Chart Data'!$H$5:$L$10, ROWS('Chart Data'!$H$5:H5), MATCH($E$6, 'Chart Data'!I4:L4, 0))} -> #N/A
A3: Utility Calling About | H3: IVR Ratings | Q3: Perception of CSR
B4: Series 1 | C4: 5 | I4: Q4_2024 | J4: Q1_2025 | K4: Q2_2025 | L4: Q3_2025 | N4: Metric | O4: Selected_Period | R4: Q3_2024 | S4: Q4_2024 | T4: Q1_2025 | U4: Q2_2025 | V4: Q3_2025
A5: Electricity | B5: 0.57281553 | C5: 4 | H5: Reasonableness of hold time* | I5: 0.70238095 | J5: 0.62068966 | K5: 0.63636364 | L5: 0.48275862 | N5: =H5 -> Reasonableness of hold time* | O5: {=--INDEX($I$5:$L$10, ROWS($H$5:H5), MATCH(Dashboard!$E$6, $I$4:$L$4, 0))} -> 0.63636364 | Q5: Spoke Clearly/Easy to Understand | R5: 0.93532338 | S5: 0.9009901 | T5: 0.92380952 | U5: 0.94059406 | V5: 0.81372549
A6: Water | B6: 0.13592233 | C6: 3 | H6: Overall communication | I6: 0.59512195 | J6: 0.58095238 | K6: 0.69607843 | L6: 0.53398058 | N6: =H6 -> Overall communication | O6: {=--INDEX($I$5:$L$10, ROWS($H$5:H6), MATCH(Dashboard!$E$6, $I$4:$L$4, 0))} -> 0.69607843 | Q6: Courteous | R6: 0.93532338 | S6: 0.9009901 | T6: 0.9047619 | U6: 0.93069307 | V6: 0.78431373
A7: Solid Waste | B7: 0.087378641 | C7: 2 | H7: Easy to use | I7: 0.66829268 | J7: 0.64761905 | K7: 0.75490196 | L7: 0.54368932 | N7: =H7 -> Easy to use | O7: {=--INDEX($I$5:$L$10, ROWS($H$5:H7), MATCH(Dashboard!$E$6, $I$4:$L$4, 0))} -> 0.75490196 | Q7: Eagerness to Help You | R7: 0.91044776 | S7: 0.89108911 | T7: 0.81904762 | U7: 0.87128713 | V7: 0.69607843
A8: Don't know/no answer | B8: 0.0097087379 | C8: 1 | H8: Provided necessary information | I8: 0.62439024 | J8: 0.59047619 | K8: 0.69607843 | L8: 0.57281553 | N8: =H8 -> Provided necessary information | O8: {=--INDEX($I$5:$L$10, ROWS($H$5:H8), MATCH(Dashboard!$E$6, $I$4:$L$4, 0))} -> 0.69607843 | Q8: Acknowledged Issue or Concern | R8: 0.92537313 | S8: 0.88613861 | T8: 0.86666667 | U8: 0.87128713 | V8: 0.68627451
A9: Other | B9: 0.19417476 | H9: Appropriateness of wait time* | I9: 0.65365854 | J9: 0.6 | K9: 0.75490196 | L9: 0.58252427 | N9: =H9 -> Appropriateness of wait time* | O9: {=--INDEX($I$5:$L$10, ROWS($H$5:H9), MATCH(Dashboard!$E$6, $I$4:$L$4, 0))} -> 0.75490196 | Q9: Ensured Understanding of Issue or Process | R9: 0.87562189 | S9: 0.86633663 | T9: 0.83809524 | U9: 0.87128713 | V9: 0.68627451
H10: Usefulness of wait time message | I10: 0.76068376 | J10: 0.69491525 | K10: 0.875 | L10: 0.5915493 | N10: =H10 -> Usefulness of wait time message | O10: {=--INDEX($I$5:$L$10, ROWS($H$5:H10), MATCH(Dashboard!$E$6, $I$4:$L$4, 0))} -> 0.875 | Q10: Valued as a Customer | R10: 0.87064677 | S10: 0.86138614 | T10: 0.84761905 | U10: 0.88118812 | V10: 0.64705882
Q11: Satisfied with Call Outcome | R11: 0.86 | S11: 0.85 | T11: 0.82 | U11: 0.86 | V11: 0.59
Q12: Offered Appropriate Program and Plans | R12: 0.64 | S12: 0.68 | T12: 0.65 | U12: 0.72 | V12: 0.57
H14: =Dashboard!$E$6 -> Q2_2025
H15: =MATCH(Dashboard!$E$6, $I$4:$L$4, 0) -> 3
A21: Overall Satisfaction
B22: Satisfied with Call Outcome | I22: Q3_2024 | J22: Q4_2024 | K22: Q1_2025 | L22: Q2_2025 | M22: Q3_2025
A23: Q3_2024 | B23: 0.8592233 | H23: Satisfied with Call Outcome | I23: 0.8592233 | J23: 0.84878049 | K23: 0.81904762 | L23: 0.8627451 | M23: 0.59223301
A24: Q4_2024 | B24: 0.84878049
A25: Q1_2025 | B25: 0.81904762
A26: Q2_2025 | B26: 0.8627451
A27: Q3_2025 | B27: 0.59223301

Sheet Sheet1
A1: sys_RespNum | B1: S1 | C1: SR2 | D1: SR3 | E1: SC4 | F1: S5 | G1: Type | H1: Q1 | I1: Q1_4_other | J1: Q2 | K1: Q3 | L1: Q3_12_other | M1: Q3_15_other | N1: Q3_24_other | O1: Q4 | P1: Q4#_1 | Q1: Q4#_2 | R1: Q4#_3 | S1: Q5 | T1: Q6_r1 | U1: Q6_r2 | V1: Q6_r3 | W1: Q6_r4 | X1: Q7Low_r1_c1 | Y1: Q7r1_Low#1 | Z1: Q7r1_Low#2 | AA1: Q7r1_Low#3 | AB1: Q7r1_Low#4 | AC1: Q7High_r1_c1 | AD1: Q7r1_High#1 | AE1: Q7r1_High#2 | AF1: Q7r1_High#3 | AG1: Q7r1_High#4 | AH1: Q7Low_r2_c1 | AI1: Q7r2_Low#1 | AJ1: Q7r2_Low#2 | AK1: Q7r2_Low#3 | AL1: Q7r2_Low#4 | AM1: Q7High_r2_c1 | AN1: Q7r2_High#1 | AO1: Q7r2_High#2 | AP1: Q7r2_High#3 | AQ1: Q7r2_High#4 | AR1: Q7Low_r3_c1 | AS1: Q7r3_Low#1 | AT1: Q7r3_Low#2 | AU1: Q7r3_Low#3 | AV1: Q7r3_Low#4 | AW1: Q7High_r3_c1 | AX1: Q7r3_High#1 | AY1: Q7r3_High#2 | AZ1: Q7r3_High#3 | BA1: Q7r3_High#4 | BB1: Q7Low_r4_c1 | BC1: Q7r4_Low#1 | BD1: Q7r4_Low#2 | BE1: Q7r4_Low#3 | BF1: Q7r4_Low#4 | BG1: Q7High_r4_c1 | BH1: Q7r4_High#1 | BI1: Q7r4_High#2 | BJ1: Q7r4_High#3 | BK1: Q7r4_High#4 | BL1: Q8 | BM1: Q9 | BN1: Q10 | BO1: Q10_1 | BP1: Q10_2 | BQ1: Q10_3 | BR1: Q10_4 | BS1: Q11 | BT1: Q12 | BU1: Q12_1 | BV1: Q12_2 | BW1: Q12_3 | BX1: Q12A | BY1: Q12B | BZ1: Q12B_1 | CA1: Q12B_2 | CB1: Q12B_3 | CC1: Q13 | CD1: Q14 | CE1: Q15 | CF1: Q16 | CG1: Q17 | CH1: Q18 | CI1: Q18_1 | CJ1: Q18_2 | CK1: Q18_3 | CL1: Q19 | CM1: Q20 | CN1: Q20_1 | CO1: Q20_2 | CP1: Q20_3 | CQ1: Q21 | CR1: Q22 | CS1: Q23_r1 | CT1: Q23_r2 | CU1: Q23_r3 | CV1: Q23_r4 | CW1: Q23_r5 | CX1: Q23_r6 | CY1: Q23_r7 | CZ1: Q24 | DA1: Q24_1 | DB1: Q24_2 | DC1: Q25 | DD1: Q26_1 | DE1: Q26_2 | DF1: Q26_3 | DG1: Q26_4 | DH1: Q26_5 | DI1: Q26_6 | DJ1: Q26_7 | DK1: Q26_8 | DL1: Q26_9 | DM1: Q26_9_other | DN1: Q27 | DO1: Q28 | DP1: Q28_1 | DQ1: Q28_2 | DR1: Q29 | DS1: Q30 | DT1: Q30_1 | DU1: Q30_2 | DV1: Q30_3 | DW1: Q31 | DX1: Q32 | DY1: Q33 | DZ1: Q33_1 | EA1: DC1 | EB1: DC1_3_other | EC1: DC1_5_other | ED1: DC1_9_other | EE1: DC1_19_other | EF1: DC1_20_other | EG1: DC1_21_other | EH1: DC1_22_other | EI1: DC2 | EJ1: DC3 | EK1: DC4 | EL1: DC5 | EM1: DR1 | EN1: DR2 | EO1: DR2_6_other | EP1: DR3 | EQ1: DR4 | ER1: DR5 | ES1: DR6 | ET1: DR7 | EU1: DR8 | EV1: DR9 | EW1: DR10 | EX1: DR11 | EY1: ContactInfo_first | EZ1: ContactInfo_last | FA1: ContactInfo_Company | FB1: ContactInfo_email | FC1: ContactInfo_Phone | FD1: InterID | FE1: Month | FF1: QtaMonth | FG1: Date | FH1: sys_EndTime | FI1: ID
A2: 17 | B2: 1 | C2: 2 | D2: 1 | E2: #NULL! | F2: 2 | G2: 2 | H2: 4 | I2: Payment | J2: 1 | K2: 11 | P2: #NULL! | Q2: #NULL! | R2: #NULL! | S2: #NULL! | T2: 5 | U2: 5 | V2: 7 | W2: 8 | Y2: #NULL! | Z2: #NULL! | AA2: #NULL! | AB2: #NULL! | AD2: #NULL! | AE2: #NULL! | AF2: #NULL! | AG2: #NULL! | AI2: #NULL! | AJ2: #NULL! | AK2: #NULL! | AL2: #NULL! | AN2: #NULL! | AO2: #NULL! | AP2: #NULL! | AQ2: #NULL! | AS2: #NULL! | AT2: #NULL! | AU2: #NULL! | AV2: #NULL! | AX2: #NULL! | AY2: #NULL! | AZ2: #NULL! | BA2: #NULL! | BC2: #NULL! | BD2: #NULL! | BE2: #NULL! | BF2: #NULL! | BG2: It was short enough | BH2: 21 | BI2: #NULL! | BJ2: #NULL! | BK2: #NULL! | BL2: 2 | BM2: 4 | BN2: I don't remember. Probably something about being able to do the things I wanted to do online; which I couldn't, because I would have been doing them online if I could. | BO2: 1 | BP2: #NULL! | BQ2: #NULL! | BR2: #NULL! | BS2: 7 | BT2: Letting people who have trouble paying know that there are options and that they should ask about those options. | BU2: 1 | BV2: #NULL! | BW2: #NULL! | BX2: #NULL! | BZ2: #NULL! | CA2: #NULL! | CB2: #NULL! | CC2: 3 | CD2: #NULL! | CE2: 1 | CF2: 1 | CG2: 1 | CH2: Different section of the center. | CI2: 1 | CJ2: #NULL! | CK2: #NULL! | CL2: 8 | CN2: #NULL! | CO2: #NULL! | CP2: #NULL! | CQ2: 1 | CR2: 8 | CS2: 10 | CT2: 10 | CU2: 10 | CV2: 10 | CW2: 10 | CX2: 10 | CY2: 10 | DA2: #NULL! | DB2: #NULL! | DC2: 9 | DD2: #NULL! | DE2: #NULL! | DF2: #NULL! | DG2: #NULL! | DH2: #NULL! | DI2: #NULL! | DJ2: #NULL! | DK2: #NULL! | DL2: #NULL! | DN2: 1 | DP2: #NULL! | DQ2: #NULL! | DR2: #NULL! | DT2: #NULL! | DU2: #NULL! | DV2: #NULL! | DW2: 2 | DX2: 2 | DZ2: #NULL! | EA2: #NULL! | EI2: #NULL! | EJ2: #NULL! | EK2: #NULL! | EL2: #NULL! | EM2: 9 | EN2: 6 | EO2: Mutt | EP2: 5 | EQ2: 1 | ER2: 2 | ES2: 78723 | ET2: 4 | EU2: 3 | EV2: 2 | EW2: 5 | EX2: 3 | EY2: RAnthony | EZ2: Steele | FB2: ranthonysteele@gmail.com | FC2: 5129260317 | FD2: 0 | FE2: #NULL! | FF2: 2 | FH2: 22 Jul 2025 - 14:42:03 CDT | FI2: 1109
A3: 18 | B3: 1 | C3: 2 | D3: 1 | E3: #NULL! | F3: 2 | G3: 2 | H3: 2 | J3: 1 | K3: 9 | P3: #NULL! | Q3: #NULL! | R3: #NULL! | S3: #NULL! | T3: 11 | U3: 11 | V3: 8 | W3: 11 | Y3: #NULL! | Z3: #NULL! | AA3: #NULL! | AB3: #NULL! | AD3: #NULL! | AE3: #NULL! | AF3: #NULL! | AG3: #NULL! | AI3: #NULL! | AJ3: #NULL! | AK3: #NULL! | AL3: #NULL! | AN3: #NULL! | AO3: #NULL! | AP3: #NULL! | AQ3: #NULL! | AS3: #NULL! | AT3: #NULL! | AU3: #NULL! | AV3: #NULL! | AW3: 10 | AX3: #NULL! | AY3: #NULL! | AZ3: #NULL! | BA3: #NULL! | BC3: #NULL! | BD3: #NULL! | BE3: #NULL! | BF3: #NULL! | BH3: #NULL! | BI3: #NULL! | BJ3: #NULL! | BK3: #NULL! | BL3: 2 | BM3: 5 | BN3: No remember | BO3: 98 | BP3: #NULL! | BQ3: #NULL! | BR3: #NULL! | BS3: 11 | BT3: No remember | BU3: 98 | BV3: #NULL! | BW3: #NULL! | BX3: #NULL! | BZ3: #NULL! | CA3: #NULL! | CB3: #NULL! | CC3: 1 | CD3: 9 | CE3: 2 | CF3: #NULL! | CG3: #NULL! | CI3: #NULL! | CJ3: #NULL! | CK3: #NULL! | CL3: #NULL! | CN3: #NULL! | CO3: #NULL! | CP3: #NULL! | CQ3: 2 | CR3: #NULL! | CS3: 10 | CT3: 10 | CU3: 10 | CV3: 10 | CW3: 10 | CX3: 10 | CY3: 10 | DA3: #NULL! | DB3: #NULL! | DC3: 10 | DD3: #NULL! | DE3: #NULL! | DF3: #NULL! | DG3: #NULL! | DH3: #NULL! | DI3: #NULL! | DJ3: #NULL! | DK3: #NULL! | DL3: #NULL! | DN3: 3 | DO3: Service was great he helps me 100% | DP3: 97 | DQ3: #NULL! | DR3: #NULL! | DT3: #NULL! | DU3: #NULL! | DV3: #NULL! | DW3: 3 | DX3: 2 | DZ3: #NULL! | EA3: #NULL! | EI3: #NULL! | EJ3: #NULL! | EK3: #NULL! | EL3: #NULL! | EM3: 6 | EN3: 6 | EO3: Puertorican | EP3: 6 | EQ3: 2 | ER3: 1 | ES3: 78704 | ET3: 5 | EU3: 6 | EV3: 1 | EW3: 5 | EX3: 2 | EY3: Vivian | EZ3: Hernandez | FB3: Hvivian88@gmail.com | FC3: 5126196064 | FD3: 0 | FE3: #NULL! | FF3: 2 | FH3: 22 Jul 2025 - 14:50:06 CDT | FI3: 860
A4: 25 | B4: 1 | C4: 2 | D4: 1 | E4: #NULL! | F4: 2 | G4: 2 | H4: 3 | J4: 1 | K4: 2 | P4: #NULL! | Q4: #NULL! | R4: #NULL! | S4: #NULL! | T4: 8 | U4: 8 | V4: 9 | W4: 9 | Y4: #NULL! | Z4: #NULL! | AA4: #NULL! | AB4: #NULL! | AC4: N/a | AD4: 97 | AE4: #NULL! | AF4: #NULL! | AG4: #NULL! | AI4: #NULL! | AJ4: #NULL! | AK4: #NULL! | AL4: #NULL! | AM4: N/a | AN4: 97 | AO4: #NULL! | AP4: #NULL! | AQ4: #NULL! | AS4: #NULL! | AT4: #NULL! | AU4: #NULL! | AV4: #NULL! | AW4: Blind, use phone | AX4: 99 | AY4: #NULL! | AZ4: #NULL! | BA4: #NULL! | BC4: #NULL! | BD4: #NULL! | BE4: #NULL! | BF4: #NULL! | BG4: N/a | BH4: 97 | BI4: #NULL! | BJ4: #NULL! | BK4: #NULL! | BL4: 2 | BM4: 4 | BN4: ??????????? | BO4: 99 | BP4: #NULL! | BQ4: #NULL! | BR4: #NULL! | BS4: 8 | BT4: Time to reach rep | BU4: 6 | BV4: #NULL! | BW4: #NULL! | BX4: #NULL! | BZ4: #NULL! | CA4: #NULL! | CB4: #NULL! | CC4: 2 | CD4: #NULL! | CE4: 1 | CF4: 1 | CG4: 2 | CH4: Have a modest in ground pool for medical/ physical therapy. During the wastewater measuring period, the pool water used for each filling is about 600 gallons/ it needs filling about every 6 weeks this water use adds to my monthly water bill for the year. A small amount of water is used every other month to backwash the filter. It is drained for repairs every 1o years. It is not fair | CI4: 2 | CJ4: #NULL! | CK4: #NULL! | CL4: 5 | CM4: Do not include pool filling in my annual/monthly water bill. | CN4: 99 | CO4: #NULL! | CP4: #NULL! | CQ4: 3 | CR4: #NULL! | CS4: 10 | CT4: 6 | CU4: 5 | CV4: 5 | CW4: 6 | CX4: 8 | CY4: 9 | CZ4: Help instead of just saying no | DA4: 5 | DB4: #NULL! | DC4: 3 | DD4: 0 | DE4: 0 | DF4: 0 | DG4: 0 | DH4: 0 | DI4: 1 | DJ4: 0 | DK4: 0 | DL4: 0 | DN4: 2 | DO4: ????? | DP4: 99 | DQ4: #NULL! | DR4: #NULL! | DT4: #NULL! | DU4: #NULL! | DV4: #NULL! | DW4: 1 | DX4: 2 | DZ4: #NULL! | EA4: #NULL! | EI4: #NULL! | EJ4: #NULL! | EK4: #NULL! | EL4: #NULL! | EM4: 10 | EN4: 1 | EP4: 5 | EQ4: 1 | ER4: 2 | ES4: 78759 | ET4: 2 | EU4: 4 | EV4: 8 | EW4: 5 | EX4: 1 | EY4: GERALD | EZ4: OROURKE | FB4: GOROURKE@AUSTIN.RR.COM | FC4: 5129920125 | FD4: 10098 | FE4: #NULL! | FF4: 2 | FH4: 29 Jul 2025 - 11:06:51 CDT | FI4: 836
A5: 28 | B5: 1 | C5: 2 | D5: 1 | E5: #NULL! | F5: 2 | G5: 2 | H5: 2 | J5: 1 | K5: 2 | P5: #NULL! | Q5: #NULL! | R5: #NULL! | S5: #NULL! | T5: 8 | U5: 8 | V5: 8 | W5: 7 | Y5: #NULL! | Z5: #NULL! | AA5: #NULL! | AB5: #NULL! | AC5: 8 | AD5: #NULL! | AE5: #NULL! | AF5: #NULL! | AG5: #NULL! | AI5: #NULL! | AJ5: #NULL! | AK5: #NULL! | AL5: #NULL! | AM5: 8 | AN5: #NULL! | AO5: #NULL! | AP5: #NULL! | AQ5: #NULL! | AS5: #NULL! | AT5: #NULL! | AU5: #NULL! | AV5: #NULL! | AW5: 8 | AX5: #NULL! | AY5: #NULL! | AZ5: #NULL! | BA5: #NULL! | BC5: #NULL! | BD5: #NULL! | BE5: #NULL! | BF5: #NULL! | BH5: #NULL! | BI5: #NULL! | BJ5: #NULL! | BK5: #NULL! | BL5: 1 | BM5: #NULL! | BO5: #NULL! | BP5: #NULL! | BQ5: #NULL! | BR5: #NULL! | BS5: #NULL! | BU5: #NULL! | BV5: #NULL! | BW5: #NULL! | BX5: #NULL! | BZ5: #NULL! | CA5: #NULL! | CB5: #NULL! | CC5: 2 | CD5: #NULL! | CE5: 2 | CF5: #NULL! | CG5: #NULL! | CI5: #NULL! | CJ5: #NULL! | CK5: #NULL! | CL5: #NULL! | CN5: #NULL! | CO5: #NULL! | CP5: #NULL! | CQ5: 2 | CR5: #NULL! | CS5: 9 | CT5: 9 | CU5: 9 | CV5: 9 | CW5: 9 | CX5: 9 | CY5: 9 | DA5: #NULL! | DB5: #NULL! | DC5: 9 | DD5: #NULL! | DE5: #NULL! | DF5: #NULL! | DG5: #NULL! | DH5: #NULL! | DI5: #NULL! | DJ5: #NULL! | DK5: #NULL! | DL5: #NULL! | DN5: 1 | DP5: #NULL! | DQ5: #NULL! | DR5: #NULL! | DT5: #NULL! | DU5: #NULL! | DV5: #NULL! | DW5: 3 | DX5: 2 | DZ5: #NULL! | EA5: #NULL! | EI5: #NULL! | EJ5: #NULL! | EK5: #NULL! | EL5: #NULL! | EM5: 10 | EN5: 1 | EP5: 5 | EQ5: 1 | ER5: 2 | ES5: 78746 | ET5: 2 | EU5: 4 | EV5: 5 | EW5: 5 | EX5: 1 | EY5: Ron | EZ5: Pauley | FB5: Rapauley47@austin.rr.com | FC5: 513-423-6030 | FD5: #NULL! | FE5: #NULL! | FF5: 3 | FH5: 11 Aug 2025 - 15:38:32 CDT | FI5: 12536
A6: 29 | B6: 1 | C6: 2 | D6: 1 | E6: #NULL! | F6: 2 | G6: 2 | H6: 2 | J6: 1 | K6: 15 | M6: Balance | P6: #NULL! | Q6: #NULL! | R6: #NULL! | S6: #NULL! | T6: 10 | U6: 10 | V6: 10 | W6: 10 | Y6: #NULL! | Z6: #NULL! | AA6: #NULL! | AB6: #NULL! | AC6: 10 | AD6: #NULL! | AE6: #NULL! | AF6: #NULL! | AG6: #NULL! | AI6: #NULL! | AJ6: #NULL! | AK6: #NULL! | AL6: #NULL! | AM6: 10 | AN6: #NULL! | AO6: #NULL! | AP6: #NULL! | AQ6: #NULL! | AS6: #NULL! | AT6: #NULL! | AU6: #NULL! | AV6: #NULL! | AW6: 10 | AX6: #NULL! | AY6: #NULL! | AZ6: #NULL! | BA6: #NULL! | BC6: #NULL! | BD6: #NULL! | BE6: #NULL! | BF6: #NULL! | BG6: 10 | BH6: #NULL! | BI6: #NULL! | BJ6: #NULL! | BK6: #NULL! | BL6: 1 | BM6: #NULL! | BO6: #NULL! | BP6: #NULL! | BQ6: #NULL! | BR6: #NULL! | BS6: #NULL! | BU6: #NULL! | BV6: #NULL! | BW6: #NULL! | BX6: #NULL! | BZ6: #NULL! | CA6: #NULL! | CB6: #NULL! | CC6: 2 | CD6: #NULL! | CE6: 2 | CF6: #NULL! | CG6: #NULL! | CI6: #NULL! | CJ6: #NULL! | CK6: #NULL! | CL6: #NULL! | CN6: #NULL! | CO6: #NULL! | CP6: #NULL! | CQ6: 2 | CR6: #NULL! | CS6: 10 | CT6: 10 | CU6: 10 | CV6: 10 | CW6: 10 | CX6: 10 | CY6: 10 | DA6: #NULL! | DB6: #NULL! | DC6: 10 | DD6: #NULL! | DE6: #NULL! | DF6: #NULL! | DG6: #NULL! | DH6: #NULL! | DI6: #NULL! | DJ6: #NULL! | DK6: #NULL! | DL6: #NULL! | DN6: 1 | DP6: #NULL! | DQ6: #NULL! | DR6: #NULL! | DT6: #NULL! | DU6: #NULL! | DV6: #NULL! | DW6: 2 | DX6: 1 | DY6: Weatherzarion | DZ6: 99 | EA6: #NULL! | EI6: #NULL! | EJ6: #NULL! | EK6: #NULL! | EL6: #NULL! | EM6: 10 | EN6: 6 | EO6: White | EP6: 5 | EQ6: 1 | ER6: 2 | ES6: 78744 | ET6: 3 | EU6: 4 | EV6: 6 | EW6: 5 | EX6: 1 | EY6: Allan | EZ6: Mexas | FB6: Ahmexas@gmail.coñm | FC6: 5134175794 | FD6: #NULL! | FE6: #NULL! | FF6: 2 | FH6: 11 Aug 2025 - 16:03:53 CDT | FI6: 3122
A7: 31 | B7: 1 | C7: 2 | D7: 1 | E7: #NULL! | F7: 2 | G7: 2 | H7: 2 | J7: 1 | K7: 3 | P7: #NULL! | Q7: #NULL! | R7: #NULL! | S7: #NULL! | T7: 10 | U7: 10 | V7: 10 | W7: 10 | Y7: #NULL! | Z7: #NULL! | AA7: #NULL! | AB7: #NULL! | AC7: 10 | AD7: #NULL! | AE7: #NULL! | AF7: #NULL! | AG7: #NULL! | AI7: #NULL! | AJ7: #NULL! | AK7: #NULL! | AL7: #NULL! | AM7: 10 | AN7: #NULL! | AO7: #NULL! | AP7: #NULL! | AQ7: #NULL! | AS7: #NULL! | AT7: #NULL! | AU7: #NULL! | AV7: #NULL! | AW7: 10 | AX7: #NULL! | AY7: #NULL! | AZ7: #NULL! | BA7: #NULL! | BC7: #NULL! | BD7: #NULL! | BE7: #NULL! | BF7: #NULL! | BG7: 9 | BH7: #NULL! | BI7: #NULL! | BJ7: #NULL! | BK7: #NULL! | BL7: 2 | BM7: 7 | BN7: Don’t recall something about I don’t remember | BO7: 98 | BP7: #NULL! | BQ7: #NULL! | BR7: #NULL! | BS7: 5 | BT7: Nice music no message | BU7: 20 | BV7: #NULL! | BW7: #NULL! | BX7: #NULL! | BZ7: #NULL! | CA7: #NULL! | CB7: #NULL! | CC7: 2 | CD7: #NULL! | CE7: 1 | CF7: 1 | CG7: 1 | CH7: I need to pay both bills, the light and water and waste water. I had been unable to log into my online account. Car said I don’t remember her name. She was patient and she walked me through what the issue was and was able to fix it. I was a very satisfied. | CI7: 1 | CJ7: #NULL! | CK7: #NULL! | CL7: 9 | CN7: #NULL! | CO7: #NULL! | CP7: #NULL! | CQ7: 2 | CR7: #NULL! | CS7: 10 | CT7: 10 | CU7: 10 | CV7: 10 | CW7: 10 | CX7: 10 | CY7: 10 | DA7: #NULL! | DB7: #NULL! | DC7: 10 | DD7: #NULL! | DE7: #NULL! | DF7: #NULL! | DG7: #NULL! | DH7: #NULL! | DI7: #NULL! | DJ7: #NULL! | DK7: #NULL! | DL7: #NULL! | DN7: 1 | DP7: #NULL! | DQ7: #NULL! | DR7: #NULL! | DT7: #NULL! | DU7: #NULL! | DV7: #NULL! | DW7: 5 | DX7: 2 | DZ7: #NULL! | EA7: #NULL! | EI7: #NULL! | EJ7: #NULL! | EK7: #NULL! | EL7: #NULL! | EM7: 9 | EN7: 3 | EP7: 1 | EQ7: 3 | ER7: 2 | ES7: 78745 | ET7: 2 | EU7: 4 | EV7: 4 | EW7: 5 | EX7: 2 | EY7: Yolanda | EZ7: Arriaga | FB7: yoarriaga07@Yahoo.com | FC7: 5124131966 | FD7: #NULL! | FE7: #NULL! | FF7: 3 | FH7: 12 Aug 2025 - 12:05:53 CDT | FI7: 12573
A8: 37 | B8: 1 | C8: 2 | D8: 1 | E8: #NULL! | F8: 2 | G8: 2 | H8: 2 | J8: 1 | K8: 14 | N8: Nest thermostat program | P8: #NULL! | Q8: #NULL! | R8: #NULL! | S8: #NULL! | T8: 10 | U8: 10 | V8: 10 | W8: 9 | Y8: #NULL! | Z8: #NULL! | AA8: #NULL! | AB8: #NULL! | AC8: Clear instructions | AD8: 30 | AE8: #NULL! | AF8: #NULL! | AG8: #NULL! | AI8: #NULL! | AJ8: #NULL! | AK8: #NULL! | AL8: #NULL! | AM8: Got me to appropriate person | AN8: 22 | AO8: #NULL! | AP8: #NULL! | AQ8: #NULL! | AS8: #NULL! | AT8: #NULL! | AU8: #NULL! | AV8: #NULL! | AW8: Easy to use | AX8: 27 | AY8: #NULL! | AZ8: #NULL! | BA8: #NULL! | BC8: #NULL! | BD8: #NULL! | BE8: #NULL! | BF8: #NULL! | BG8: Did not take long | BH8: 21 | BI8: #NULL! | BJ8: #NULL! | BK8: #NULL! | BL8: 5 | BM8: 10 | BN8: Don’t remember | BO8: 98 | BP8: #NULL! | BQ8: #NULL! | BR8: #NULL! | BS8: 10 | BT8: No other messages | BU8: 97 | BV8: #NULL! | BW8: #NULL! | BX8: #NULL! | BZ8: #NULL! | CA8: #NULL! | CB8: #NULL! | CC8: 2 | CD8: #NULL! | CE8: 1 | CF8: 1 | CG8: 2 | CH8: They had someone call me back | CI8: 2 | CJ8: #NULL! | CK8: #NULL! | CL8: 10 | CN8: #NULL! | CO8: #NULL! | CP8: #NULL! | CQ8: 2 | CR8: #NULL! | CS8: 10 | CT8: 10 | CU8: 10 | CV8: 11 | CW8: 10 | CX8: 10 | CY8: 9 | DA8: #NULL! | DB8: #NULL! | DC8: 10 | DD8: #NULL! | DE8: #NULL! | DF8: #NULL! | DG8: #NULL! | DH8: #NULL! | DI8: #NULL! | DJ8: #NULL! | DK8: #NULL! | DL8: #NULL! | DN8: 1 | DP8: #NULL! | DQ8: #NULL! | DR8: #NULL! | DT8: #NULL! | DU8: #NULL! | DV8: #NULL! | DW8: 2 | DX8: 2 | DZ8: #NULL! | EA8: #NULL! | EI8: #NULL! | EJ8: #NULL! | EK8: #NULL! | EL8: #NULL! | EM8: 10 | EN8: 1 | EP8: 5 | EQ8: 3 | ER8: 1 | ES8: 78701 | ET8: 1 | EU8: 4 | EV8: 5 | EW8: 5 | EX8: 1 | EY8: Gary | EZ8: Watkins | FB8: garywatkins@protonmail.com | FC8: 5126729678 | FD8: #NULL! | FE8: #NULL! | FF8: 3 | FH8: 17 Aug 2025 - 16:43:05 CDT | FI8: 12617
A9: 58 | B9: 1 | C9: 2 | D9: 1 | E9: #NULL! | F9: 2 | G9: 2 | H9: 1 | J9: 2 | K9: 2 | O9: Our trash can has been missed on numerous occasions. I’ve had to call for a pick up about 4-5 times in this year alone. I requested some sort of credit for our inconvenience but never received a response to that. They did send someone to clear out our trash with the next day though. | P9: 12 | Q9: #NULL! | R9: #NULL! | S9: #NULL! | T9: 9 | U9: 8 | V9: 8 | W9: 9 | Y9: #NULL! | Z9: #NULL! | AA9: #NULL! | AB9: #NULL! | AC9: 8 | AD9: #NULL! | AE9: #NULL! | AF9: #NULL! | AG9: #NULL! | AI9: #NULL! | AJ9: #NULL! | AK9: #NULL! | AL9: #NULL! | AM9: 8 | AN9: #NULL! | AO9: #NULL! | AP9: #NULL! | AQ9: #NULL! | AS9: #NULL! | AT9: #NULL! | AU9: #NULL! | AV9: #NULL! | AW9: 8 | AX9: #NULL! | AY9: #NULL! | AZ9: #NULL! | BA9: #NULL! | BC9: #NULL! | BD9: #NULL! | BE9: #NULL! | BF9: #NULL! | BG9: 8 | BH9: #NULL! | BI9: #NULL! | BJ9: #NULL! | BK9: #NULL! | BL9: 2 | BM9: 5 | BN9: A constant loop asking if I or someone in my household was on life support. | BO9: 99 | BP9: #NULL! | BQ9: #NULL! | BR9: #NULL! | BS9: 3 | BT9: Rates are stable for the next quarter or on the opposite side, rates are expected to increase in the next quarter due to xyzzy… | BU9: 1 | BV9: #NULL! | BW9: #NULL! | BX9: #NULL! | BZ9: #NULL! | CA9: #NULL! | CB9: #NULL! | CC9: 1 | CD9: 8 | CE9: 2 | CF9: #NULL! | CG9: #NULL! | CI9: #NULL! | CJ9: #NULL! | CK9: #NULL! | CL9: #NULL! | CN9: #NULL! | CO9: #NULL! | CP9: #NULL! | CQ9: 2 | CR9: #NULL! | CS9: 10 | CT9: 10 | CU9: 9 | CV9: 8 | CW9: 9 | CX9: 9 | CY9: 10 | DA9: #NULL! | DB9: #NULL! | DC9: 9 | DD9: #NULL! | DE9: #NULL! | DF9: #NULL! | DG9: #NULL! | DH9: #NULL! | DI9: #NULL! | DJ9: #NULL! | DK9: #NULL! | DL9: #NULL! | DN9: 1 | DP9: #NULL! | DQ9: #NULL! | DR9: #NULL! | DT9: #NULL! | DU9: #NULL! | DV9: #NULL! | DW9: 2 | DX9: 2 | DZ9: #NULL! | EA9: #NULL! | EI9: #NULL! | EJ9: #NULL! | EK9: #NULL! | EL9: #NULL! | EM9: 8 | EN9: 3 | EP9: 1 | EQ9: 1 | ER9: 2 | ES9: 78660 | ET9: 4 | EU9: 3 | EV9: 6 | EW9: 5 | EX9: 2 | EY9: Amelia | EZ9: De La Rosa-Rodriguez | FB9: arodriguez2052@yahoo.com | FC9: 5129252012 | FD9: #NULL! | FE9: #NULL! | FF9: 2 | FH9: 08 Sep 2025 - 15:13:44 CDT | FI9: 10637
A10: 61 | B10: 1 | C10: 2 | D10: 1 | E10: #NULL! | F10: 2 | G10: 2 | H10: 4 | I10: Moving questions | J10: 1 | K10: 6 | P10: #NULL! | Q10: #NULL! | R10: #NULL! | S10: #NULL! | T10: 10 | U10: 10 | V10: 10 | W10: 10 | Y10: #NULL! | Z10: #NULL! | AA10: #NULL! | AB10: #NULL! | AC10: 10 | AD10: #NULL! | AE10: #NULL! | AF10: #NULL! | AG10: #NULL! | AI10: #NULL! | AJ10: #NULL! | AK10: #NULL! | AL10: #NULL! | AM10: 10 | AN10: #NULL! | AO10: #NULL! | AP10: #NULL! | AQ10: #NULL! | AS10: #NULL! | AT10: #NULL! | AU10: #NULL! | AV10: #NULL! | AW10: 10 | AX10: #NULL! | AY10: #NULL! | AZ10: #NULL! | BA10: #NULL! | BC10: #NULL! | BD10: #NULL! | BE10: #NULL! | BF10: #NULL! | BG10: 10 | BH10: #NULL! | BI10: #NULL! | BJ10: #NULL! | BK10: #NULL! | BL10: 1 | BM10: #NULL! | BO10: #NULL! | BP10: #NULL! | BQ10: #NULL! | BR10: #NULL! | BS10: #NULL! | BU10: #NULL! | BV10: #NULL! | BW10: #NULL! | BX10: #NULL! | BZ10: #NULL! | CA10: #NULL! | CB10: #NULL! | CC10: 2 | CD10: #NULL! | CE10: 2 | CF10: #NULL! | CG10: #NULL! | CI10: #NULL! | CJ10: #NULL! | CK10: #NULL! | CL10: #NULL! | CN10: #NULL! | CO10: #NULL! | CP10: #NULL! | CQ10: 2 | CR10: #NULL! | CS10: 10 | CT10: 10 | CU10: 10 | CV10: 10 | CW10: 10 | CX10: 10 | CY10: 10 | DA10: #NULL! | DB10: #NULL! | DC10: 10 | DD10: #NULL! | DE10: #NULL! | DF10: #NULL! | DG10: #NULL! | DH10: #NULL! | DI10: #NULL! | DJ10: #NULL! | DK10: #NULL! | DL10: #NULL! | DN10: 1 | DP10: #NULL! | DQ10: #NULL! | DR10: #NULL! | DT10: #NULL! | DU10: #NULL! | DV10: #NULL! | DW10: 3 | DX10: 1 | DY10: Just get notice though email of saving energy | DZ10: 99 | EA10: #NULL! | EI10: #NULL! | EJ10: #NULL! | EK10: #NULL! | EL10: #NULL! | EM10: 4 | EN10: 3 | EP10: 1 | EQ10: 1 | ER10: 1 | ES10: 78729 | ET10: 5 | EU10: 1 | EV10: 4 | EW10: 4 | EX10: 2 | EY10: Areli | EZ10: Dauphin | FB10: Arelimguerrero@gmail.com | FC10: 5125847314 | FD10: #NULL! | FE10: #NULL! | FF10: 1 | FH10: 08 Sep 2025 - 15:13:34 CDT | FI10: 1286
A11: 64 | B11: 1 | C11: 2 | D11: 1 | E11: #NULL! | F11: 2 | G11: 2 | H11: 2 | J11: 2 | K11: 23 | O11: Meter on my house seems way out of line with actual electricity used. | P11: 1 | Q11: #NULL! | R11: #NULL! | S11: #NULL! | T11: 2 | U11: 1 | V11: 5 | W11: 2 | X11: Not helpful | Y11: 6 | Z11: #NULL! | AA11: #NULL! | AB11: #NULL! | AD11: #NULL! | AE11: #NULL! | AF11: #NULL! | AG11: #NULL! | AH11: Not helpful | AI11: 6 | AJ11: #NULL! | AK11: #NULL! | AL11: #NULL! | AN11: #NULL! | AO11: #NULL! | AP11: #NULL! | AQ11: #NULL! | AS11: #NULL! | AT11: #NULL! | AU11: #NULL! | AV11: #NULL! | AX11: #NULL! | AY11: #NULL! | AZ11: #NULL! | BA11: #NULL! | BB11: Long wait time | BC11: 2 | BD11: #NULL! | BE11: #NULL! | BF11: #NULL! | BH11: #NULL! | BI11: #NULL! | BJ11: #NULL! | BK11: #NULL! | BL11: 2 | BM11: 9 | BN11: No idea | BO11: 98 | BP11: #NULL! | BQ11: #NULL! | BR11: #NULL! | BS11: 10 | BT11: That would be it | BU11: 97 | BV11: #NULL! | BW11: #NULL! | BX11: #NULL! | BZ11: #NULL! | CA11: #NULL! | CB11: #NULL! | CC11: 1 | CD11: 4 | CE11: 1 | CF11: 1 | CG11: 2 | CH11: Meter reading seems crazy off, but never got any help | CI11: 1 | CJ11: #NULL! | CK11: #NULL! | CL11: 4 | CM11: Find someone who understands my kind of meter and why it is showing such high usage | CN11: 3 | CO11: #NULL! | CP11: #NULL! | CQ11: 2 | CR11: #NULL! | CS11: 9 | CT11: 9 | CU11: 1 | CV11: 3 | CW11: 5 | CX11: 9 | CY11: 9 | CZ11: Fix the meter issue | DA11: 2 | DB11: #NULL! | DC11: 3 | DD11: 1 | DE11: 1 | DF11: 0 | DG11: 0 | DH11: 0 | DI11: 1 | DJ11: 0 | DK11: 1 | DL11: 0 | DN11: 2 | DO11: Someone with knowledge of the meter and why readings are so high | DP11: 5 | DQ11: #NULL! | DR11: #NULL! | DT11: #NULL! | DU11: #NULL! | DV11: #NULL! | DW11: 1 | DX11: 2 | DZ11: #NULL! | EA11: #NULL! | EI11: #NULL! | EJ11: #NULL! | EK11: #NULL! | EL11: #NULL! | EM11: 6 | EN11: 1 | EP11: 1 | EQ11: 1 | ER11: 2 | ES11: 78735 | ET11: 4 | EU11: 4 | EV11: 6 | EW11: 5 | EX11: 1 | EY11: Brian | EZ11: Cobb | FB11: brian@cobbmechanical.com | FC11: 5129172998 | FD11: #NULL! | FE11: #NULL! | FF11: 2 | FH11: 08 Sep 2025 - 15:35:26 CDT | FI11: 3192
A12: 76 | B12: 1 | C12: 2 | D12: 1 | E12: #NULL! | F12: 2 | G12: 2 | H12: 3 | J12: 1 | K12: 12 | L12: Water leak caused by work on main line that blew my meter to house line | P12: #NULL! | Q12: #NULL! | R12: #NULL! | S12: #NULL! | T12: 6 | U12: 8 | V12: 5 | W12: 9 | Y12: #NULL! | Z12: #NULL! | AA12: #NULL! | AB12: #NULL! | AD12: #NULL! | AE12: #NULL! | AF12: #NULL! | AG12: #NULL! | AI12: #NULL! | AJ12: #NULL! | AK12: #NULL! | AL12: #NULL! | AM12: Although it took several hours, we were able to determine how I could receive a partial credit | AN12: 25 | AO12: #NULL! | AP12: #NULL! | AQ12: #NULL! | AS12: #NULL! | AT12: #NULL! | AU12: #NULL! | AV12: #NULL! | AX12: #NULL! | AY12: #NULL! | AZ12: #NULL! | BA12: #NULL! | BC12: #NULL! | BD12: #NULL! | BE12: #NULL! | BF12: #NULL! | BG12: I was served and supported by a great customer service team, as I spoke to more than one person | BH12: 24 | BI12: 25 | BJ12: #NULL! | BK12: #NULL! | BL12: 1 | BM12: #NULL! | BO12: #NULL! | BP12: #NULL! | BQ12: #NULL! | BR12: #NULL! | BS12: #NULL! | BU12: #NULL! | BV12: #NULL! | BW12: #NULL! | BX12: #NULL! | BZ12: #NULL! | CA12: #NULL! | CB12: #NULL! | CC12: 1 | CD12: 7 | CE12: 1 | CF12: 1 | CG12: 1 | CH12: I cannot remember the specific reason | CI12: 98 | CJ12: #NULL! | CK12: #NULL! | CL12: 10 | CN12: #NULL! | CO12: #NULL! | CP12: #NULL! | CQ12: 1 | CR12: 9 | CS12: 10 | CT12: 8 | CU12: 8 | CV12: 9 | CW12: 6 | CX12: 9 | CY12: 10 | DA12: #NULL! | DB12: #NULL! | DC12: 10 | DD12: #NULL! | DE12: #NULL! | DF12: #NULL! | DG12: #NULL! | DH12: #NULL! | DI12: #NULL! | DJ12: #NULL! | DK12: #NULL! | DL12: #NULL! | DN12: 1 | DP12: #NULL! | DQ12: #NULL! | DR12: #NULL! | DT12: #NULL! | DU12: #NULL! | DV12: #NULL! | DW12: 1 | DX12: 2 | DZ12: #NULL! | EA12: #NULL! | EI12: #NULL! | EJ12: #NULL! | EK12: #NULL! | EL12: #NULL! | EM12: 6 | EN12: 1 | EP12: 1 | EQ12: 1 | ER12: 2 | ES12: 78750 | ET12: 2 | EU12: 5 | EV12: 6 | EW12: 5 | EX12: 1 | EY12: Christian | EZ12: Patrik | FB12: Christianjpatrik@gmail.com | FC12: 512-560-1894 | FD12: #NULL! | FE12: #NULL! | FF12: 1 | FH12: 08 Sep 2025 - 16:39:12 CDT | FI12: 8864
A13: 78 | B13: 1 | C13: 2 | D13: 1 | E13: #NULL! | F13: 2 | G13: 2 | H13: 2 | J13: 1 | K13: 33 | N13: Auto payment options on bill | P13: #NULL! | Q13: #NULL! | R13: #NULL! | S13: #NULL! | T13: 10 | U13: 10 | V13: 10 | W13: 7 | Y13: #NULL! | Z13: #NULL! | AA13: #NULL! | AB13: #NULL! | AC13: Seamless | AD13: 21 | AE13: #NULL! | AF13: #NULL! | AG13: #NULL! | AI13: #NULL! | AJ13: #NULL! | AK13: #NULL! | AL13: #NULL! | AM13: Agent knew exactly what was required to solve my issue | AN13: 25 | AO13: #NULL! | AP13: #NULL! | AQ13: #NULL! | AS13: #NULL! | AT13: #NULL! | AU13: #NULL! | AV13: #NULL! | AW13: She was excellent | AX13: 24 | AY13: #NULL! | AZ13: #NULL! | BA13: #NULL! | BC13: #NULL! | BD13: #NULL! | BE13: #NULL! | BF13: #NULL! | BH13: #NULL! | BI13: #NULL! | BJ13: #NULL! | BK13: #NULL! | BL13: 2 | BM13: 7 | BN13: Don’t | BO13: 98 | BP13: #NULL! | BQ13: #NULL! | BR13: #NULL! | BS13: 10 | BT13: None | BU13: 97 | BV13: #NULL! | BW13: #NULL! | BX13: #NULL! | BZ13: #NULL! | CA13: #NULL! | CB13: #NULL! | CC13: 1 | CD13: 8 | CE13: 2 | CF13: #NULL! | CG13: #NULL! | CI13: #NULL! | CJ13: #NULL! | CK13: #NULL! | CL13: #NULL! | CN13: #NULL! | CO13: #NULL! | CP13: #NULL! | CQ13: 2 | CR13: #NULL! | CS13: 10 | CT13: 10 | CU13: 10 | CV13: 10 | CW13: 10 | CX13: 10 | CY13: 10 | DA13: #NULL! | DB13: #NULL! | DC13: 10 | DD13: #NULL! | DE13: #NULL! | DF13: #NULL! | DG13: #NULL! | DH13: #NULL! | DI13: #NULL! | DJ13: #NULL! | DK13: #NULL! | DL13: #NULL! | DN13: 1 | DP13: #NULL! | DQ13: #NULL! | DR13: #NULL! | DT13: #NULL! | DU13: #NULL! | DV13: #NULL! | DW13: 3 | DX13: 2 | DZ13: #NULL! | EA13: #NULL! | EI13: #NULL! | EJ13: #NULL! | EK13: #NULL! | EL13: #NULL! | EM13: 6 | EN13: 1 | EP13: 5 | EQ13: 1 | ER13: 2 | ES13: 78731 | ET13: 2 | EU13: 5 | EV13: 6 | EW13: 5 | EX13: 1 | EY13: Andrew | EZ13: Rhodes | FB13: arhodes0@gmail.com | FC13: 6504419499 | FD13: #NULL! | FE13: #NULL! | FF13: 2 | FH13: 08 Sep 2025 - 16:46:40 CDT | FI13: 4384
A14: 79 | B14: 1 | C14: 2 | D14: 1 | E14: #NULL! | F14: 2 | G14: 2 | H14: 1 | J14: 1 | K14: 14 | N14: Recycling | P14: #NULL! | Q14: #NULL! | R14: #NULL! | S14: #NULL! | T14: 10 | U14: 10 | V14: 10 | W14: 10 | Y14: #NULL! | Z14: #NULL! | AA14: #NULL! | AB14: #NULL! | AC14: 10 | AD14: #NULL! | AE14: #NULL! | AF14: #NULL! | AG14: #NULL! | AI14: #NULL! | AJ14: #NULL! | AK14: #NULL! | AL14: #NULL! | AM14: 10 | AN14: #NULL! | AO14: #NULL! | AP14: #NULL! | AQ14: #NULL! | AS14: #NULL! | AT14: #NULL! | AU14: #NULL! | AV14: #NULL! | AW14: 10 | AX14: #NULL! | AY14: #NULL! | AZ14: #NULL! | BA14: #NULL! | BC14: #NULL! | BD14: #NULL! | BE14: #NULL! | BF14: #NULL! | BG14: 10 | BH14: #NULL! | BI14: #NULL! | BJ14: #NULL! | BK14: #NULL! | BL14: 1 | BM14: #NULL! | BO14: #NULL! | BP14: #NULL! | BQ14: #NULL! | BR14: #NULL! | BS14: #NULL! | BU14: #NULL! | BV14: #NULL! | BW14: #NULL! | BX14: #NULL! | BZ14: #NULL! | CA14: #NULL! | CB14: #NULL! | CC14: 2 | CD14: #NULL! | CE14: 2 | CF14: #NULL! | CG14: #NULL! | CI14: #NULL! | CJ14: #NULL! | CK14: #NULL! | CL14: #NULL! | CN14: #NULL! | CO14: #NULL! | CP14: #NULL! | CQ14: 2 | CR14: #NULL! | CS14: 10 | CT14: 10 | CU14: 10 | CV14: 10 | CW14: 10 | CX14: 10 | CY14: 10 | DA14: #NULL! | DB14: #NULL! | DC14: 10 | DD14: #NULL! | DE14: #NULL! | DF14: #NULL! | DG14: #NULL! | DH14: #NULL! | DI14: #NULL! | DJ14: #NULL! | DK14: #NULL! | DL14: #NULL! | DN14: 1 | DP14: #NULL! | DQ14: #NULL! | DR14: #NULL! | DT14: #NULL! | DU14: #NULL! | DV14: #NULL! | DW14: 2 | DX14: 2 | DZ14: #NULL! | EA14: #NULL! | EI14: #NULL! | EJ14: #NULL! | EK14: #NULL! | EL14: #NULL! | EM14: 10 | EN14: 1 | EP14: 5 | EQ14: 5 | ER14: 1 | ES14: 78759 | ET14: 3 | EU14: 4 | EV14: 2 | EW14: 5 | EX14: 2 | EY14: Audrey | EZ14: Johnson | FB14: audrey.johson71@gmail.com | FC14: 512-810-8065 | FD14: #NULL! | FE14: #NULL! | FF14: 1 | FH14: 08 Sep 2025 - 16:52:33 CDT | FI14: 2547
A15: 83 | B15: 1 | C15: 2 | D15: 1 | E15: #NULL! | F15: 2 | G15: 2 | H15: 4 | I15: Clean community fee and what city services it applies to, maintenance on street lighting | J15: 1 | K15: 20 | P15: #NULL! | Q15: #NULL! | R15: #NULL! | S15: #NULL! | T15: 3 | U15: 10 | V15: 6 | W15: 10 | X15: This is more an issue with Austin 311. Austin energy was able to look up the info for the clean community fee and clarify that it does cover bulk pickup and dead animal removal for condominiums, but city employees did not believe me until I got a 3-way call with Austin energy and a 311 representative on the line at the same time. | Y15: 5 | Z15: #NULL! | AA15: #NULL! | AB15: #NULL! | AD15: #NULL! | AE15: #NULL! | AF15: #NULL! | AG15: #NULL! | AI15: #NULL! | AJ15: #NULL! | AK15: #NULL! | AL15: #NULL! | AM15: Austin energy employees were able to locate the correct information for my inquiry. I consider this a high level of service as other companies often have representatives not empowered to make changes to accounts or gather necessary information. | AN15: 30 | AO15: #NULL! | AP15: #NULL! | AQ15: #NULL! | AS15: #NULL! | AT15: #NULL! | AU15: #NULL! | AV15: #NULL! | AX15: #NULL! | AY15: #NULL! | AZ15: #NULL! | BA15: #NULL! | BC15: #NULL! | BD15: #NULL! | BE15: #NULL! | BF15: #NULL! | BG15: Austin energy was able to answer my call and respond in a reasonable amount of time on the phone. I consider this a very good level of service, especially as other companies or services become difficult to reach | BH15: 22 | BI15: #NULL! | BJ15: #NULL! | BK15: #NULL! | BL15: 2 | BM15: 4 | BN15: I’m sorry, I don’t remember the exact path through the phone tree. This was a complex call to multiple city agencies including call forwarding and a 3-way conversation and was resolved in about 30 minutes total. Difficult but achievable for the average customer. | BO15: 98 | BP15: #NULL! | BQ15: #NULL! | BR15: #NULL! | BS15: 7 | BT15: A phone tree option to leave a brief message with description of the issue and receive a callback if hold time were to exceed a few minutes. | BU15: 13 | BV15: #NULL! | BW15: #NULL! | BX15: #NULL! | BZ15: #NULL! | CA15: #NULL! | CB15: #NULL! | CC15: 1 | CD15: 10 | CE15: 1 | CF15: 1 | CG15: 1 | CH15: Yes. The representative need to look up information and contact another agency to inform them of their findings. | CI15: 1 | CJ15: #NULL! | CK15: #NULL! | CL15: 10 | CN15: #NULL! | CO15: #NULL! | CP15: #NULL! | CQ15: 2 | CR15: #NULL! | CS15: 10 | CT15: 10 | CU15: 10 | CV15: 10 | CW15: 10 | CX15: 10 | CY15: 10 | DA15: #NULL! | DB15: #NULL! | DC15: 10 | DD15: #NULL! | DE15: #NULL! | DF15: #NULL! | DG15: #NULL! | DH15: #NULL! | DI15: #NULL! | DJ15: #NULL! | DK15: #NULL! | DL15: #NULL! | DN15: 1 | DP15: #NULL! | DQ15: #NULL! | DR15: #NULL! | DT15: #NULL! | DU15: #NULL! | DV15: #NULL! | DW15: 4 | DX15: 1 | DY15: I receive paper bills from Austin energy. The included information advised me of billing changes. These were used to update the budget for a condo association to good effect. | DZ15: 3 | EA15: #NULL! | EI15: #NULL! | EJ15: #NULL! | EK15: #NULL! | EL15: #NULL! | EM15: 4 | EN15: 1 | EP15: 1 | EQ15: 2 | ER15: 2 | ES15: 78704 | ET15: 1 | EU15: 5 | EV15: 6 | EW15: 5 | EX15: 1 | EY15: David | EZ15: Craven | FB15: cascraven@gmail.com | FC15: 5408186726 | FD15: #NULL! | FE15: #NULL! | FF15: 2 | FH15: 08 Sep 2025 - 17:41:00 CDT | FI15: 3209
A16: 86 | B16: 1 | C16: 2 | D16: 1 | E16: #NULL! | F16: 2 | G16: 2 | H16: 2 | J16: 1 | K16: 3 | P16: #NULL! | Q16: #NULL! | R16: #NULL! | S16: #NULL! | T16: 10 | U16: 10 | V16: 10 | W16: 10 | Y16: #NULL! | Z16: #NULL! | AA16: #NULL! | AB16: #NULL! | AC16: 10 | AD16: #NULL! | AE16: #NULL! | AF16: #NULL! | AG16: #NULL! | AI16: #NULL! | AJ16: #NULL! | AK16: #NULL! | AL16: #NULL! | AM16: 10 | AN16: #NULL! | AO16: #NULL! | AP16: #NULL! | AQ16: #NULL! | AS16: #NULL! | AT16: #NULL! | AU16: #NULL! | AV16: #NULL! | AW16: 10 | AX16: #NULL! | AY16: #NULL! | AZ16: #NULL! | BA16: #NULL! | BC16: #NULL! | BD16: #NULL! | BE16: #NULL! | BF16: #NULL! | BG16: 10 | BH16: #NULL! | BI16: #NULL! | BJ16: #NULL! | BK16: #NULL! | BL16: 1 | BM16: #NULL! | BO16: #NULL! | BP16: #NULL! | BQ16: #NULL! | BR16: #NULL! | BS16: #NULL! | BU16: #NULL! | BV16: #NULL! | BW16: #NULL! | BX16: #NULL! | BZ16: #NULL! | CA16: #NULL! | CB16: #NULL! | CC16: 1 | CD16: 10 | CE16: 2 | CF16: #NULL! | CG16: #NULL! | CI16: #NULL! | CJ16: #NULL! | CK16: #NULL! | CL16: #NULL! | CN16: #NULL! | CO16: #NULL! | CP16: #NULL! | CQ16: 2 | CR16: #NULL! | CS16: 10 | CT16: 10 | CU16: 10 | CV16: 10 | CW16: 10 | CX16: 10 | CY16: 10 | DA16: #NULL! | DB16: #NULL! | DC16: 10 | DD16: #NULL! | DE16: #NULL! | DF16: #NULL! | DG16: #NULL! | DH16: #NULL! | DI16: #NULL! | DJ16: #NULL! | DK16: #NULL! | DL16: #NULL! | DN16: 1 | DP16: #NULL! | DQ16: #NULL! | DR16: #NULL! | DT16: #NULL! | DU16: #NULL! | DV16: #NULL! | DW16: 3 | DX16: 2 | DZ16: #NULL! | EA16: #NULL! | EI16: #NULL! | EJ16: #NULL! | EK16: #NULL! | EL16: #NULL! | EM16: 9 | EN16: 3 | EP16: 5 | EQ16: 3 | ER16: 2 | ES16: 78724 | ET16: 1 | EU16: 3 | EV16: 2 | EW16: 5 | EX16: 1 | EY16: Joe | EZ16: Altamirano Jr | FB16: cjimtheboss@gmail.com | FC16: 737-888-4223 | FD16: #NULL! | FE16: #NULL! | FF16: 1 | FH16: 08 Sep 2025 - 18:49:22 CDT | FI16: 8868
A17: 91 | B17: 1 | C17: 2 | D17: 1 | E17: #NULL! | F17: 3 | G17: 2 | H17: 3 | J17: 1 | K17: 21 | P17: #NULL! | Q17: #NULL! | R17: #NULL! | S17: #NULL! | T17: 10 | U17: 10 | V17: 10 | W17: 10 | Y17: #NULL! | Z17: #NULL! | AA17: #NULL! | AB17: #NULL! | AC17: Easy to follow | AD17: 20 | AE17: #NULL! | AF17: #NULL! | AG17: #NULL! | AI17: #NULL! | AJ17: #NULL! | AK17: #NULL! | AL17: #NULL! | AM17: Easy to follow | AN17: 27 | AO17: #NULL! | AP17: #NULL! | AQ17: #NULL! | AS17: #NULL! | AT17: #NULL! | AU17: #NULL! | AV17: #NULL! | AW17: Easy to follow | AX17: 22 | AY17: #NULL! | AZ17: #NULL! | BA17: #NULL! | BC17: #NULL! | BD17: #NULL! | BE17: #NULL! | BF17: #NULL! | BG17: Easy to follow | BH17: 27 | BI17: #NULL! | BJ17: #NULL! | BK17: #NULL! | BL17: 2 | BM17: 7 | BN17: Can’t remember | BO17: 98 | BP17: #NULL! | BQ17: #NULL! | BR17: #NULL! | BS17: 10 | BT17: How can save more energy tips | BU17: 8 | BV17: #NULL! | BW17: #NULL! | BX17: #NULL! | BZ17: #NULL! | CA17: #NULL! | CB17: #NULL! | CC17: 3 | CD17: #NULL! | CE17: 1 | CF17: 1 | CG17: 1 | CH17: Can’t remember | CI17: 98 | CJ17: #NULL! | CK17: #NULL! | CL17: 7 | CM17: Google to where I may get the answer | CN17: 99 | CO17: #NULL! | CP17: #NULL! | CQ17: 2 | CR17: #NULL! | CS17: 8 | CT17: 8 | CU17: 8 | CV17: 8 | CW17: 8 | CX17: 8 | CY17: 8 | DA17: #NULL! | DB17: #NULL! | DC17: 6 | DD17: 0 | DE17: 0 | DF17: 1 | DG17: 0 | DH17: 0 | DI17: 0 | DJ17: 0 | DK17: 0 | DL17: 0 | DN17: 1 | DP17: #NULL! | DQ17: #NULL! | DR17: #NULL! | DT17: #NULL! | DU17: #NULL! | DV17: #NULL! | DW17: 2 | DX17: 2 | DZ17: #NULL! | EA17: #NULL! | EI17: #NULL! | EJ17: #NULL! | EK17: #NULL! | EL17: #NULL! | EM17: 10 | EN17: 1 | EP17: 5 | EQ17: 5 | ER17: 2 | ES17: 78749 | ET17: 2 | EU17: 5 | EV17: 2 | EW17: 5 | EX17: 2 | EY17: Vonnie | EZ17: Basham | FB17: Bashamvonnie@gmail.com | FC17: 5128612079 | FD17: #NULL! | FE17: #NULL! | FF17: 2 | FH17: 08 Sep 2025 - 21:13:21 CDT | FI17: 3169
A18: 103 | B18: 1 | C18: 2 | D18: 1 | E18: #NULL! | F18: 2 | G18: 2 | H18: 3 | J18: 1 | K18: 1 | P18: #NULL! | Q18: #NULL! | R18: #NULL! | S18: 10 | T18: 10 | U18: 10 | V18: 10 | W18: 10 | Y18: #NULL! | Z18: #NULL! | AA18: #NULL! | AB18: #NULL! | AC18: 10 | AD18: #NULL! | AE18: #NULL! | AF18: #NULL! | AG18: #NULL! | AI18: #NULL! | AJ18: #NULL! | AK18: #NULL! | AL18: #NULL! | AM18: 10 | AN18: #NULL! | AO18: #NULL! | AP18: #NULL! | AQ18: #NULL! | AS18: #NULL! | AT18: #NULL! | AU18: #NULL! | AV18: #NULL! | AW18: 10 | AX18: #NULL! | AY18: #NULL! | AZ18: #NULL! | BA18: #NULL! | BC18: #NULL! | BD18: #NULL! | BE18: #NULL! | BF18: #NULL! | BG18: 10 | BH18: #NULL! | BI18: #NULL! | BJ18: #NULL! | BK18: #NULL! | BL18: 2 | BM18: 2 | BN18: Don’t remember | BO18: 98 | BP18: #NULL! | BQ18: #NULL! | BR18: #NULL! | BS18: 1 | BT18: Not sure | BU18: 98 | BV18: #NULL! | BW18: #NULL! | BX18: #NULL! | BZ18: #NULL! | CA18: #NULL! | CB18: #NULL! | CC18: 2 | CD18: #NULL! | CE18: 1 | CF18: 1 | CG18: 1 | CH18: Don’t remember | CI18: 98 | CJ18: #NULL! | CK18: #NULL! | CL18: 10 | CN18: #NULL! | CO18: #NULL! | CP18: #NULL! | CQ18: 2 | CR18: #NULL! | CS18: 10 | CT18: 10 | CU18: 10 | CV18: 10 | CW18: 10 | CX18: 10 | CY18: 10 | DA18: #NULL! | DB18: #NULL! | DC18: 10 | DD18: #NULL! | DE18: #NULL! | DF18: #NULL! | DG18: #NULL! | DH18: #NULL! | DI18: #NULL! | DJ18: #NULL! | DK18: #NULL! | DL18: #NULL! | DN18: 1 | DP18: #NULL! | DQ18: #NULL! | DR18: #NULL! | DT18: #NULL! | DU18: #NULL! | DV18: #NULL! | DW18: 3 | DX18: 2 | DZ18: #NULL! | EA18: #NULL! | EI18: #NULL! | EJ18: #NULL! | EK18: #NULL! | EL18: #NULL! | EM18: 8 | EN18: 1 | EP18: 1 | EQ18: 1 | ER18: 2 | ES18: 78759 | ET18: 4 | EU18: 4 | EV18: 6 | EW18: 5 | EX18: 1 | EY18: Salman | EZ18: Khan | FB18: denpesar@me.com | FC18: 6462635204 | FD18: #NULL! | FE18: #NULL! | FF18: 1 | FH18: 09 Sep 2025 - 07:27:52 CDT | FI18: 10156
A19: 106 | B19: 1 | C19: 2 | D19: 1 | E19: #NULL! | F19: 2 | G19: 2 | H19: 2 | J19: 1 | K19: 3 | P19: #NULL! | Q19: #NULL! | R19: #NULL! | S19: #NULL! | T19: 6 | U19: 7 | V19: 7 | W19: 6 | Y19: #NULL! | Z19: #NULL! | AA19: #NULL! | AB19: #NULL! | AD19: #NULL! | AE19: #NULL! | AF19: #NULL! | AG19: #NULL! | AI19: #NULL! | AJ19: #NULL! | AK19: #NULL! | AL19: #NULL! | AN19: #NULL! | AO19: #NULL! | AP19: #NULL! | AQ19: #NULL! | AS19: #NULL! | AT19: #NULL! | AU19: #NULL! | AV19: #NULL! | AX19: #NULL! | AY19: #NULL! | AZ19: #NULL! | BA19: #NULL! | BC19: #NULL! | BD19: #NULL! | BE19: #NULL! | BF19: #NULL! | BH19: #NULL! | BI19: #NULL! | BJ19: #NULL! | BK19: #NULL! | BL19: 2 | BM19: 6 | BN19: Please wait for the next representative. I honestly don’t remember. | BO19: 6 | BP19: #NULL! | BQ19: #NULL! | BR19: #NULL! | BS19: 8 | BT19: Options to pay bill electronically | BU19: 2 | BV19: #NULL! | BW19: #NULL! | BX19: #NULL! | BZ19: #NULL! | CA19: #NULL! | CB19: #NULL! | CC19: 2 | CD19: #NULL! | CE19: 2 | CF19: #NULL! | CG19: #NULL! | CI19: #NULL! | CJ19: #NULL! | CK19: #NULL! | CL19: #NULL! | CN19: #NULL! | CO19: #NULL! | CP19: #NULL! | CQ19: 2 | CR19: #NULL! | CS19: 7 | CT19: 7 | CU19: 6 | CV19: 6 | CW19: 6 | CX19: 7 | CY19: 7 | CZ19: I think ways to pay bill electronically | DA19: 4 | DB19: #NULL! | DC19: 10 | DD19: #NULL! | DE19: #NULL! | DF19: #NULL! | DG19: #NULL! | DH19: #NULL! | DI19: #NULL! | DJ19: #NULL! | DK19: #NULL! | DL19: #NULL! | DN19: 1 | DP19: #NULL! | DQ19: #NULL! | DR19: #NULL! | DT19: #NULL! | DU19: #NULL! | DV19: #NULL! | DW19: 1 | DX19: 2 | DZ19: #NULL! | EA19: #NULL! | EI19: #NULL! | EJ19: #NULL! | EK19: #NULL! | EL19: #NULL! | EM19: 6 | EN19: 3 | EP19: 1 | EQ19: 2 | ER19: 1 | ES19: 78758 | ET19: 2 | EU19: 5 | EV19: 5 | EW19: 5 | EX19: 1 | EY19: David Augustine | EZ19: Ysla | FB19: daysla@icloud.com | FC19: 5129389484 | FD19: #NULL! | FE19: #NULL! | FF19: 1 | FH19: 09 Sep 2025 - 07:44:49 CDT | FI19: 3885
A20: 119 | B20: 1 | C20: 2 | D20: 1 | E20: #NULL! | F20: 2 | G20: 2 | H20: 2 | J20: 1 | K20: 18 | P20: #NULL! | Q20: #NULL! | R20: #NULL! | S20: #NULL! | T20: 8 | U20: 10 | V20: 10 | W20: 10 | Y20: #NULL! | Z20: #NULL! | AA20: #NULL! | AB20: #NULL! | AC20: Sometime the option to get a live agent is hard | AD20: 3 | AE20: #NULL! | AF20: #NULL! | AG20: #NULL! | AI20: #NULL! | AJ20: #NULL! | AK20: #NULL! | AL20: #NULL! | AM20: They explain it to me very well | AN20: 25 | AO20: #NULL! | AP20: #NULL! | AQ20: #NULL! | AS20: #NULL! | AT20: #NULL! | AU20: #NULL! | AV20: #NULL! | AW20: They are so nice | AX20: 24 | AY20: #NULL! | AZ20: #NULL! | BA20: #NULL! | BC20: #NULL! | BD20: #NULL! | BE20: #NULL! | BF20: #NULL! | BG20: Perfect | BH20: 28 | BI20: #NULL! | BJ20: #NULL! | BK20: #NULL! | BL20: 2 | BM20: 8 | BN20: I don't remember | BO20: 98 | BP20: #NULL! | BQ20: #NULL! | BR20: #NULL! | BS20: 11 | BT20: I don't remember | BU20: 98 | BV20: #NULL! | BW20: #NULL! | BX20: #NULL! | BZ20: #NULL! | CA20: #NULL! | CB20: #NULL! | CC20: 1 | CD20: 10 | CE20: 2 | CF20: #NULL! | CG20: #NULL! | CI20: #NULL! | CJ20: #NULL! | CK20: #NULL! | CL20: #NULL! | CN20: #NULL! | CO20: #NULL! | CP20: #NULL! | CQ20: 2 | CR20: #NULL! | CS20: 10 | CT20: 10 | CU20: 10 | CV20: 10 | CW20: 10 | CX20: 10 | CY20: 10 | DA20: #NULL! | DB20: #NULL! | DC20: 10 | DD20: #NULL! | DE20: #NULL! | DF20: #NULL! | DG20: #NULL! | DH20: #NULL! | DI20: #NULL! | DJ20: #NULL! | DK20: #NULL! | DL20: #NULL! | DN20: 1 | DP20: #NULL! | DQ20: #NULL! | DR20: #NULL! | DT20: #NULL! | DU20: #NULL! | DV20: #NULL! | DW20: 2 | DX20: 2 | DZ20: #NULL! | EA20: #NULL! | EI20: #NULL! | EJ20: #NULL! | EK20: #NULL! | EL20: #NULL! | EM20: 4 | EN20: 3 | EP20: 1 | EQ20: 3 | ER20: 1 | ES20: 78741 | ET20: 2 | EU20: 4 | EV20: 3 | EW20: 4 | EX20: 2 | EY20: Betty | EZ20: Escalona | FB20: Elizabeth.escalona.26@gmail.com | FC20: 5125219258 | FD20: #NULL! | FE20: #NULL! | FF20: 2 | FH20: 09 Sep 2025 - 08:55:00 CDT | FI20: 10771
A21: 120 | B21: 1 | C21: 2 | D21: 1 | E21: #NULL! | F21: 2 | G21: 2 | H21: 2 | J21: 1 | K21: 3 | P21: #NULL! | Q21: #NULL! | R21: #NULL! | S21: #NULL! | T21: 4 | U21: 3 | V21: 5 | W21: 5 | Y21: #NULL! | Z21: #NULL! | AA21: #NULL! | AB21: #NULL! | AD21: #NULL! | AE21: #NULL! | AF21: #NULL! | AG21: #NULL! | AH21: That's how I feel call went | AI21: 7 | AJ21: #NULL! | AK21: #NULL! | AL21: #NULL! | AN21: #NULL! | AO21: #NULL! | AP21: #NULL! | AQ21: #NULL! | AS21: #NULL! | AT21: #NULL! | AU21: #NULL! | AV21: #NULL! | AX21: #NULL! | AY21: #NULL! | AZ21: #NULL! | BA21: #NULL! | BC21: #NULL! | BD21: #NULL! | BE21: #NULL! | BF21: #NULL! | BH21: #NULL! | BI21: #NULL! | BJ21: #NULL! | BK21: #NULL! | BL21: 2 | BM21: 9 | BN21: Different pay stations | BO21: 99 | BP21: #NULL! | BQ21: #NULL! | BR21: #NULL! | BS21: 10 | BT21: Ways to help pay bills | BU21: 2 | BV21: #NULL! | BW21: #NULL! | BX21: #NULL! | BZ21: #NULL! | CA21: #NULL! | CB21: #NULL! | CC21: 2 | CD21: #NULL! | CE21: 2 | CF21: #NULL! | CG21: #NULL! | CI21: #NULL! | CJ21: #NULL! | CK21: #NULL! | CL21: #NULL! | CN21: #NULL! | CO21: #NULL! | CP21: #NULL! | CQ21: 2 | CR21: #NULL! | CS21: 3 | CT21: 5 | CU21: 4 | CV21: 1 | CW21: 10 | CX21: 4 | CY21: 7 | CZ21: Not seem like you're rushed off the phone | DA21: 5 | DB21: #NULL! | DC21: 7 | DD21: 0 | DE21: 0 | DF21: 0 | DG21: 0 | DH21: 0 | DI21: 0 | DJ21: 1 | DK21: 0 | DL21: 0 | DN21: 1 | DP21: #NULL! | DQ21: #NULL! | DR21: #NULL! | DT21: #NULL! | DU21: #NULL! | DV21: #NULL! | DW21: 5 | DX21: 2 | DZ21: #NULL! | EA21: #NULL! | EI21: #NULL! | EJ21: #NULL! | EK21: #NULL! | EL21: #NULL! | EM21: 9 | EN21: 2 | EP21: 5 | EQ21: 2 | ER21: 1 | ES21: 78744 | ET21: 2 | EU21: 1 | EV21: 1 | EW21: 5 | EX21: 2 | EY21: Rosie | EZ21: Taylor | FB21: essietaylor2505@gmail.com | FC21: 5129457080 | FD21: #NULL! | FE21: #NULL! | FF21: 2 | FH21: 09 Sep 2025 - 08:57:03 CDT | FI21: 9517
A22: 129 | B22: 1 | C22: 2 | D22: 1 | E22: #NULL! | F22: 2 | G22: 2 | H22: 2 | J22: 1 | K22: 4 | P22: #NULL! | Q22: #NULL! | R22: #NULL! | S22: #NULL! | T22: 10 | U22: 10 | V22: 10 | W22: 10 | Y22: #NULL! | Z22: #NULL! | AA22: #NULL! | AB22: #NULL! | AC22: Prompt efficient service | AD22: 21 | AE22: #NULL! | AF22: #NULL! | AG22: #NULL! | AI22: #NULL! | AJ22: #NULL! | AK22: #NULL! | AL22: #NULL! | AM22: Rep was helpful and knowledgeable about putting the account back into the property owner’s name | AN22: 25 | AO22: #NULL! | AP22: #NULL! | AQ22: #NULL! | AS22: #NULL! | AT22: #NULL! | AU22: #NULL! | AV22: #NULL! | AW22: Easy | AX22: 27 | AY22: #NULL! | AZ22: #NULL! | BA22: #NULL! | BC22: #NULL! | BD22: #NULL! | BE22: #NULL! | BF22: #NULL! | BG22: Stated time was more than actual. Very quick | BH22: 21 | BI22: #NULL! | BJ22: #NULL! | BK22: #NULL! | BL22: 2 | BM22: 3 | BN22: Don't recall | BO22: 98 | BP22: #NULL! | BQ22: #NULL! | BR22: #NULL! | BS22: 9 | BT22: Hours of service, required materials so callers are prepared, interesting facts/upcoming activities for Austin energy, things you can accomplish online | BU22: 12 | BV22: 22 | BW22: 2 | BX22: #NULL! | BZ22: #NULL! | CA22: #NULL! | CB22: #NULL! | CC22: 2 | CD22: #NULL! | CE22: 2 | CF22: #NULL! | CG22: #NULL! | CI22: #NULL! | CJ22: #NULL! | CK22: #NULL! | CL22: #NULL! | CN22: #NULL! | CO22: #NULL! | CP22: #NULL! | CQ22: 2 | CR22: #NULL! | CS22: 10 | CT22: 10 | CU22: 10 | CV22: 10 | CW22: 10 | CX22: 10 | CY22: 10 | DA22: #NULL! | DB22: #NULL! | DC22: 10 | DD22: #NULL! | DE22: #NULL! | DF22: #NULL! | DG22: #NULL! | DH22: #NULL! | DI22: #NULL! | DJ22: #NULL! | DK22: #NULL! | DL22: #NULL! | DN22: 1 | DP22: #NULL! | DQ22: #NULL! | DR22: #NULL! | DT22: #NULL! | DU22: #NULL! | DV22: #NULL! | DW22: 2 | DX22: 2 | DZ22: #NULL! | EA22: #NULL! | EI22: #NULL! | EJ22: #NULL! | EK22: #NULL! | EL22: #NULL! | EM22: 8 | EN22: 1 | EP22: 2 | EQ22: 2 | ER22: 2 | ES22: 78757 | ET22: 1 | EU22: 4 | EV22: 5 | EW22: 5 | EX22: 2 | EY22: Evelyn | EZ22: Brandley | FB22: Evelyncamille@yahoo.com | FC22: 5123507281 | FD22: #NULL! | FE22: #NULL! | FF22: 2 | FH22: 09 Sep 2025 - 10:14:54 CDT | FI22: 4558
A23: 135 | B23: 1 | C23: 2 | D23: 1 | E23: #NULL! | F23: 2 | G23: 2 | H23: 3 | J23: 1 | K23: 2 | P23: #NULL! | Q23: #NULL! | R23: #NULL! | S23: #NULL! | T23: 8 | U23: 9 | V23: 9 | W23: 7 | Y23: #NULL! | Z23: #NULL! | AA23: #NULL! | AB23: #NULL! | AC23: I got information that was necessary to apply for adjustment to my wastewater billing. | AD23: 26 | AE23: #NULL! | AF23: #NULL! | AG23: #NULL! | AI23: #NULL! | AJ23: #NULL! | AK23: #NULL! | AL23: #NULL! | AM23: Same as above | AN23: 26 | AO23: #NULL! | AP23: #NULL! | AQ23: #NULL! | AS23: #NULL! | AT23: #NULL! | AU23: #NULL! | AV23: #NULL! | AW23: I like speaking with a person. | AX23: 3 | AY23: #NULL! | AZ23: #NULL! | BA23: #NULL! | BC23: #NULL! | BD23: #NULL! | BE23: #NULL! | BF23: #NULL! | BH23: #NULL! | BI23: #NULL! | BJ23: #NULL! | BK23: #NULL! | BL23: 4 | BM23: #NULL! | BO23: #NULL! | BP23: #NULL! | BQ23: #NULL! | BR23: #NULL! | BS23: #NULL! | BU23: #NULL! | BV23: #NULL! | BW23: #NULL! | BX23: 10 | BZ23: #NULL! | CA23: #NULL! | CB23: #NULL! | CC23: 3 | CD23: #NULL! | CE23: 3 | CF23: #NULL! | CG23: #NULL! | CI23: #NULL! | CJ23: #NULL! | CK23: #NULL! | CL23: #NULL! | CN23: #NULL! | CO23: #NULL! | CP23: #NULL! | CQ23: 2 | CR23: #NULL! | CS23: 9 | CT23: 10 | CU23: 9 | CV23: 9 | CW23: 10 | CX23: 10 | CY23: 10 | DA23: #NULL! | DB23: #NULL! | DC23: 9 | DD23: #NULL! | DE23: #NULL! | DF23: #NULL! | DG23: #NULL! | DH23: #NULL! | DI23: #NULL! | DJ23: #NULL! | DK23: #NULL! | DL23: #NULL! | DN23: 1 | DP23: #NULL! | DQ23: #NULL! | DR23: #NULL! | DT23: #NULL! | DU23: #NULL! | DV23: #NULL! | DW23: 2 | DX23: 2 | DZ23: #NULL! | EA23: #NULL! | EI23: #NULL! | EJ23: #NULL! | EK23: #NULL! | EL23: #NULL! | EM23: 10 | EN23: 1 | EP23: 5 | EQ23: 1 | ER23: 2 | ES23: 78730 | ET23: 2 | EU23: 4 | EV23: 6 | EW23: 4 | EX23: 2 | EY23: Holly | EZ23: Hargis | FB23: hollyhargis2@gmail.com | FC23: 7132482819 | FD23: #NULL! | FE23: #NULL! | FF23: 2 | FH23: 09 Sep 2025 - 10:59:02 CDT | FI23: 4604
A24: 136 | B24: 1 | C24: 2 | D24: 1 | E24: #NULL! | F24: 3 | G24: 2 | H24: 1 | J24: 2 | K24: 20 | N24: My trashcan wasn't completely emptied. | O24: There was a trash bag left at the bottom of my trash bin after trash pickup. They only emptied half of the bin. | P24: 12 | Q24: #NULL! | R24: #NULL! | S24: #NULL! | T24: 3 | U24: 3 | V24: 3 | W24: 10 | X24: It takes too long to speak to someone. | Y24: 2 | Z24: #NULL! | AA24: #NULL! | AB24: #NULL! | AD24: #NULL! | AE24: #NULL! | AF24: #NULL! | AG24: #NULL! | AH24: What I speak, it never understands me correctly, no matter how slow and clear I speak. | AI24: 9 | AJ24: #NULL! | AK24: #NULL! | AL24: #NULL! | AN24: #NULL! | AO24: #NULL! | AP24: #NULL! | AQ24: #NULL! | AR24: I would much rather speak to a human being. | AS24: 3 | AT24: #NULL! | AU24: #NULL! | AV24: #NULL! | AX24: #NULL! | AY24: #NULL! | AZ24: #NULL! | BA24: #NULL! | BC24: #NULL! | BD24: #NULL! | BE24: #NULL! | BF24: #NULL! | BG24: I rarely ever have to wait very long. | BH24: 21 | BI24: #NULL! | BJ24: #NULL! | BK24: #NULL! | BL24: 2 | BM24: 4 | BN24: I don't know | BO24: 98 | BP24: #NULL! | BQ24: #NULL! | BR24: #NULL! | BS24: 10 | BT24: It would be nice to know what benefits the city offers for free and what rebates are available. | BU24: 1 | BV24: #NULL! | BW24: #NULL! | BX24: #NULL! | BZ24: #NULL! | CA24: #NULL! | CB24: #NULL! | CC24: 1 | CD24: 9 | CE24: 2 | CF24: #NULL! | CG24: #NULL! | CI24: #NULL! | CJ24: #NULL! | CK24: #NULL! | CL24: #NULL! | CN24: #NULL! | CO24: #NULL! | CP24: #NULL! | CQ24: 2 | CR24: #NULL! | CS24: 10 | CT24: 9 | CU24: 10 | CV24: 11 | CW24: 10 | CX24: 10 | CY24: 10 | DA24: #NULL! | DB24: #NULL! | DC24: 10 | DD24: #NULL! | DE24: #NULL! | DF24: #NULL! | DG24: #NULL! | DH24: #NULL! | DI24: #NULL! | DJ24: #NULL! | DK24: #NULL! | DL24: #NULL! | DN24: 1 | DP24: #NULL! | DQ24: #NULL! | DR24: #NULL! | DT24: #NULL! | DU24: #NULL! | DV24: #NULL! | DW24: 4 | DX24: 3 | DZ24: #NULL! | EA24: #NULL! | EI24: #NULL! | EJ24: #NULL! | EK24: #NULL! | EL24: #NULL! | EM24: 8 | EN24: 3 | EP24: 1 | EQ24: 2 | ER24: 2 | ES24: 78747 | ET24: 1 | EU24: 4 | EV24: 4 | EW24: 5 | EX24: 2 | EY24: Angelina | EZ24: Gonzalez | FB24: Gonzalezangela31@gmail.com | FC24: 5128675309 | FD24: #NULL! | FE24: #NULL! | FF24: 2 | FH24: 09 Sep 2025 - 11:08:18 CDT | FI24: 2087
A25: 142 | B25: 1 | C25: 2 | D25: 1 | E25: #NULL! | F25: 2 | G25: 2 | H25: 2 | J25: 1 | K25: 11 | P25: #NULL! | Q25: #NULL! | R25: #NULL! | S25: #NULL! | T25: 10 | U25: 10 | V25: 10 | W25: 10 | Y25: #NULL! | Z25: #NULL! | AA25: #NULL! | AB25: #NULL! | AC25: Short waiting time | AD25: 21 | AE25: #NULL! | AF25: #NULL! | AG25: #NULL! | AI25: #NULL! | AJ25: #NULL! | AK25: #NULL! | AL25: #NULL! | AM25: All necessary info provided | AN25: 30 | AO25: #NULL! | AP25: #NULL! | AQ25: #NULL! | AS25: #NULL! | AT25: #NULL! | AU25: #NULL! | AV25: #NULL! | AW25: Excellent | AX25: 28 | AY25: #NULL! | AZ25: #NULL! | BA25: #NULL! | BC25: #NULL! | BD25: #NULL! | BE25: #NULL! | BF25: #NULL! | BG25: Excellent | BH25: 28 | BI25: #NULL! | BJ25: #NULL! | BK25: #NULL! | BL25: 2 | BM25: 5 | BN25: Recording about how long for wait time. What department to call for making payments? | BO25: 8 | BP25: #NULL! | BQ25: #NULL! | BR25: #NULL! | BS25: 10 | BT25: None | BU25: 97 | BV25: #NULL! | BW25: #NULL! | BX25: #NULL! | BZ25: #NULL! | CA25: #NULL! | CB25: #NULL! | CC25: 2 | CD25: #NULL! | CE25: 2 | CF25: #NULL! | CG25: #NULL! | CI25: #NULL! | CJ25: #NULL! | CK25: #NULL! | CL25: #NULL! | CN25: #NULL! | CO25: #NULL! | CP25: #NULL! | CQ25: 2 | CR25: #NULL! | CS25: 10 | CT25: 10 | CU25: 10 | CV25: 10 | CW25: 10 | CX25: 10 | CY25: 10 | DA25: #NULL! | DB25: #NULL! | DC25: 10 | DD25: #NULL! | DE25: #NULL! | DF25: #NULL! | DG25: #NULL! | DH25: #NULL! | DI25: #NULL! | DJ25: #NULL! | DK25: #NULL! | DL25: #NULL! | DN25: 1 | DP25: #NULL! | DQ25: #NULL! | DR25: #NULL! | DT25: #NULL! | DU25: #NULL! | DV25: #NULL! | DW25: 3 | DX25: 2 | DZ25: #NULL! | EA25: #NULL! | EI25: #NULL! | EJ25: #NULL! | EK25: #NULL! | EL25: #NULL! | EM25: 10 | EN25: 2 | EP25: 5 | EQ25: 1 | ER25: 2 | ES25: 78752 | ET25: 2 | EU25: 3 | EV25: 3 | EW25: 5 | EX25: 2 | EY25: Darleen | EZ25: Gilmore | FB25: darleen1947@gmail.com | FC25: 5129255896 | FD25: #NULL! | FE25: #NULL! | FF25: 2 | FH25: 09 Sep 2025 - 11:56:29 CDT | FI25: 3261
A26: 147 | B26: 1 | C26: 2 | D26: 1 | E26: #NULL! | F26: 2 | G26: 2 | H26: 2 | J26: 1 | K26: 38 | N26: Inquiry about bill assistance program | P26: #NULL! | Q26: #NULL! | R26: #NULL! | S26: #NULL! | T26: 10 | U26: 10 | V26: 10 | W26: 10 | Y26: #NULL! | Z26: #NULL! | AA26: #NULL! | AB26: #NULL! | AC26: I got all the information I needed in a timely fashion. | AD26: 21 | AE26: #NULL! | AF26: #NULL! | AG26: #NULL! | AI26: #NULL! | AJ26: #NULL! | AK26: #NULL! | AL26: #NULL! | AM26: I got all the information I needed in a timely fashion. | AN26: 21 | AO26: #NULL! | AP26: #NULL! | AQ26: #NULL! | AS26: #NULL! | AT26: #NULL! | AU26: #NULL! | AV26: #NULL! | AW26: I got all the information I needed in a timely fashion from a polite associate. | AX26: 21 | AY26: #NULL! | AZ26: #NULL! | BA26: #NULL! | BC26: #NULL! | BD26: #NULL! | BE26: #NULL! | BF26: #NULL! | BG26: I got all the information I needed in a timely fashion. | BH26: 21 | BI26: #NULL! | BJ26: #NULL! | BK26: #NULL! | BL26: 2 | BM26: 10 | BN26: I don't remember the info I heard while on hold. | BO26: 98 | BP26: #NULL! | BQ26: #NULL! | BR26: #NULL! | BS26: 8 | BT26: N/a | BU26: 97 | BV26: #NULL! | BW26: #NULL! | BX26: #NULL! | BZ26: #NULL! | CA26: #NULL! | CB26: #NULL! | CC26: 2 | CD26: #NULL! | CE26: 2 | CF26: #NULL! | CG26: #NULL! | CI26: #NULL! | CJ26: #NULL! | CK26: #NULL! | CL26: #NULL! | CN26: #NULL! | CO26: #NULL! | CP26: #NULL! | CQ26: 2 | CR26: #NULL! | CS26: 10 | CT26: 10 | CU26: 10 | CV26: 10 | CW26: 10 | CX26: 10 | CY26: 10 | DA26: #NULL! | DB26: #NULL! | DC26: 10 | DD26: #NULL! | DE26: #NULL! | DF26: #NULL! | DG26: #NULL! | DH26: #NULL! | DI26: #NULL! | DJ26: #NULL! | DK26: #NULL! | DL26: #NULL! | DN26: 1 | DP26: #NULL! | DQ26: #NULL! | DR26: #NULL! | DT26: #NULL! | DU26: #NULL! | DV26: #NULL! | DW26: 2 | DX26: 2 | DZ26: #NULL! | EA26: #NULL! | EI26: #NULL! | EJ26: #NULL! | EK26: #NULL! | EL26: #NULL! | EM26: 4 | EN26: 7 | EP26: 3 | EQ26: 2 | ER26: 2 | ES26: 78753 | ET26: 2 | EU26: 3 | EV26: 3 | EW26: 5 | EX26: 1 | EY26: Douglas | EZ26: Bass | FB26: Dj_182@YAHOO.COM | FC26: 9094479283 | FD26: #NULL! | FE26: #NULL! | FF26: 1 | FH26: 09 Sep 2025 - 12:05:13 CDT | FI26: 6372
A27: 150 | B27: 1 | C27: 2 | D27: 1 | E27: #NULL! | F27: 3 | G27: 2 | H27: 2 | J27: 1 | K27: 1 | P27: #NULL! | Q27: #NULL! | R27: #NULL! | S27: 6 | T27: 7 | U27: 8 | V27: 8 | W27: 7 | Y27: #NULL! | Z27: #NULL! | AA27: #NULL! | AB27: #NULL! | AD27: #NULL! | AE27: #NULL! | AF27: #NULL! | AG27: #NULL! | AI27: #NULL! | AJ27: #NULL! | AK27: #NULL! | AL27: #NULL! | AM27: Sometimes we have to repeat the request. It is causing delays. | AN27: 9 | AO27: #NULL! | AP27: #NULL! | AQ27: #NULL! | AS27: #NULL! | AT27: #NULL! | AU27: #NULL! | AV27: #NULL! | AW27: It is what it is expected from an automatized service. | AX27: 28 | AY27: #NULL! | AZ27: #NULL! | BA27: #NULL! | BC27: #NULL! | BD27: #NULL! | BE27: #NULL! | BF27: #NULL! | BH27: #NULL! | BI27: #NULL! | BJ27: #NULL! | BK27: #NULL! | BL27: 2 | BM27: 7 | BN27: I was waiting to speak with an agent, I heard noise, a woman voice and them silence. I waited around 2 minutes while the person at the other side of the line was silenced or muted. It was discouraged to call to get an answer to be disconnected. Poor customer service and wasted time. | BO27: 99 | BP27: #NULL! | BQ27: #NULL! | BR27: #NULL! | BS27: 1 | BT27: None at this call and time. | BU27: 97 | BV27: #NULL! | BW27: #NULL! | BX27: #NULL! | BZ27: #NULL! | CA27: #NULL! | CB27: #NULL! | CC27: 2 | CD27: #NULL! | CE27: 2 | CF27: #NULL! | CG27: #NULL! | CI27: #NULL! | CJ27: #NULL! | CK27: #NULL! | CL27: #NULL! | CN27: #NULL! | CO27: #NULL! | CP27: #NULL! | CQ27: 2 | CR27: #NULL! | CS27: 1 | CT27: 1 | CU27: 1 | CV27: 1 | CW27: 1 | CX27: 1 | CY27: 1 | CZ27: The call was unsuccessful. The agent disconnected the call. | DA27: 97 | DB27: #NULL! | DC27: 1 | DD27: 1 | DE27: 1 | DF27: 0 | DG27: 0 | DH27: 0 | DI27: 1 | DJ27: 0 | DK27: 0 | DL27: 1 | DM27: the agent disconnected the call. | DN27: 2 | DO27: Answering calls and resolve issues. | DP27: 4 | DQ27: #NULL! | DR27: #NULL! | DT27: #NULL! | DU27: #NULL! | DV27: #NULL! | DW27: 5 | DX27: 2 | DZ27: #NULL! | EA27: #NULL! | EI27: #NULL! | EJ27: #NULL! | EK27: #NULL! | EL27: #NULL! | EM27: 11 | EN27: 7 | EP27: 7 | EQ27: 3 | ER27: 3 | ES27: 78744 | ET27: 7 | EU27: 6 | EV27: 8 | EW27: 5 | EX27: 4 | EY27: A | EZ27: Duenas | FB27: gabycamps@hotmail.com | FC27: 5127971216 | FD27: #NULL! | FE27: #NULL! | FF27: 2 | FH27: 09 Sep 2025 - 12:24:35 CDT | FI27: 5809
A28: 164 | B28: 1 | C28: 2 | D28: 1 | E28: #NULL! | F28: 2 | G28: 2 | H28: 2 | J28: 1 | K28: 3 | P28: #NULL! | Q28: #NULL! | R28: #NULL! | S28: #NULL! | T28: 10 | U28: 10 | V28: 10 | W28: 10 | Y28: #NULL! | Z28: #NULL! | AA28: #NULL! | AB28: #NULL! | AC28: Easy to use is correct | AD28: 20 | AE28: #NULL! | AF28: #NULL! | AG28: #NULL! | AI28: #NULL! | AJ28: #NULL! | AK28: #NULL! | AL28: #NULL! | AM28: They do the job right | AN28: 25 | AO28: #NULL! | AP28: #NULL! | AQ28: #NULL! | AS28: #NULL! | AT28: #NULL! | AU28: #NULL! | AV28: #NULL! | AW28: Great way to communicate | AX28: 20 | AY28: #NULL! | AZ28: #NULL! | BA28: #NULL! | BC28: #NULL! | BD28: #NULL! | BE28: #NULL! | BF28: #NULL! | BG28: No wait time | BH28: 21 | BI28: #NULL! | BJ28: #NULL! | BK28: #NULL! | BL28: 1 | BM28: #NULL! | BO28: #NULL! | BP28: #NULL! | BQ28: #NULL! | BR28: #NULL! | BS28: #NULL! | BU28: #NULL! | BV28: #NULL! | BW28: #NULL! | BX28: #NULL! | BZ28: #NULL! | CA28: #NULL! | CB28: #NULL! | CC28: 2 | CD28: #NULL! | CE28: 2 | CF28: #NULL! | CG28: #NULL! | CI28: #NULL! | CJ28: #NULL! | CK28: #NULL! | CL28: #NULL! | CN28: #NULL! | CO28: #NULL! | CP28: #NULL! | CQ28: 2 | CR28: #NULL! | CS28: 10 | CT28: 10 | CU28: 10 | CV28: 10 | CW28: 10 | CX28: 10 | CY28: 10 | DA28: #NULL! | DB28: #NULL! | DC28: 10 | DD28: #NULL! | DE28: #NULL! | DF28: #NULL! | DG28: #NULL! | DH28: #NULL! | DI28: #NULL! | DJ28: #NULL! | DK28: #NULL! | DL28: #NULL! | DN28: 1 | DP28: #NULL! | DQ28: #NULL! | DR28: #NULL! | DT28: #NULL! | DU28: #NULL! | DV28: #NULL! | DW28: 3 | DX28: 2 | DZ28: #NULL! | EA28: #NULL! | EI28: #NULL! | EJ28: #NULL! | EK28: #NULL! | EL28: #NULL! | EM28: 4 | EN28: 2 | EP28: 6 | EQ28: 2 | ER28: 1 | ES28: 78759 | ET28: 2 | EU28: 4 | EV28: 1 | EW28: 5 | EX28: 2 | EY28: DAYTA | EZ28: JONES | FB28: daytajackson28@gmail.com | FC28: 5127482550 | FD28: #NULL! | FE28: #NULL! | FF28: 2 | FH28: 09 Sep 2025 - 14:09:15 CDT | FI28: 5748
A29: 173 | B29: 1 | C29: 2 | D29: 1 | E29: #NULL! | F29: 2 | G29: 2 | H29: 2 | J29: 1 | K29: 10 | P29: #NULL! | Q29: #NULL! | R29: #NULL! | S29: #NULL! | T29: 5 | U29: 11 | V29: 11 | W29: 5 | Y29: #NULL! | Z29: #NULL! | AA29: #NULL! | AB29: #NULL! | AD29: #NULL! | AE29: #NULL! | AF29: #NULL! | AG29: #NULL! | AI29: #NULL! | AJ29: #NULL! | AK29: #NULL! | AL29: #NULL! | AN29: #NULL! | AO29: #NULL! | AP29: #NULL! | AQ29: #NULL! | AS29: #NULL! | AT29: #NULL! | AU29: #NULL! | AV29: #NULL! | AX29: #NULL! | AY29: #NULL! | AZ29: #NULL! | BA29: #NULL! | BC29: #NULL! | BD29: #NULL! | BE29: #NULL! | BF29: #NULL! | BH29: #NULL! | BI29: #NULL! | BJ29: #NULL! | BK29: #NULL! | BL29: 1 | BM29: #NULL! | BO29: #NULL! | BP29: #NULL! | BQ29: #NULL! | BR29: #NULL! | BS29: #NULL! | BU29: #NULL! | BV29: #NULL! | BW29: #NULL! | BX29: #NULL! | BZ29: #NULL! | CA29: #NULL! | CB29: #NULL! | CC29: 2 | CD29: #NULL! | CE29: 2 | CF29: #NULL! | CG29: #NULL! | CI29: #NULL! | CJ29: #NULL! | CK29: #NULL! | CL29: #NULL! | CN29: #NULL! | CO29: #NULL! | CP29: #NULL! | CQ29: 2 | CR29: #NULL! | CS29: 10 | CT29: 8 | CU29: 10 | CV29: 8 | CW29: 10 | CX29: 10 | CY29: 9 | DA29: #NULL! | DB29: #NULL! | DC29: 4 | DD29: 0 | DE29: 1 | DF29: 0 | DG29: 0 | DH29: 0 | DI29: 1 | DJ29: 0 | DK29: 0 | DL29: 0 | DN29: 3 | DO29: The fee for moving could have been dropped to help make my bill more affordable, so I wouldn’t be drowning in it and facing disconnection as a single mother on one income. | DP29: 3 | DQ29: #NULL! | DR29: #NULL! | DT29: #NULL! | DU29: #NULL! | DV29: #NULL! | DW29: 1 | DX29: 2 | DZ29: #NULL! | EA29: #NULL! | EI29: #NULL! | EJ29: #NULL! | EK29: #NULL! | EL29: #NULL! | EM29: 3 | EN29: 1 | EP29: 1 | EQ29: 3 | ER29: 1 | ES29: 78745 | ET29: 3 | EU29: 3 | EV29: 3 | EW29: 5 | EX29: 2 | EY29: Kathryn | EZ29: Wickham | FB29: Katewickham89@gmail.com | FC29: (512)671-0851 | FD29: #NULL! | FE29: #NULL! | FF29: 1 | FH29: 09 Sep 2025 - 16:20:11 CDT | FI29: 4043
A30: 176 | B30: 1 | C30: 2 | D30: 1 | E30: #NULL! | F30: 2 | G30: 2 | H30: 2 | J30: 1 | K30: 23 | P30: #NULL! | Q30: #NULL! | R30: #NULL! | S30: #NULL! | T30: 1 | U30: 1 | V30: 1 | W30: 1 | X30: I pay a majority of bill for “service center” - awful service. | Y30: 5 | Z30: #NULL! | AA30: #NULL! | AB30: #NULL! | AD30: #NULL! | AE30: #NULL! | AF30: #NULL! | AG30: #NULL! | AH30: I pay a majority of bill for “service center” - awful service. | AI30: 5 | AJ30: #NULL! | AK30: #NULL! | AL30: #NULL! | AN30: #NULL! | AO30: #NULL! | AP30: #NULL! | AQ30: #NULL! | AR30: I pay a majority of bill for “service center” - awful service. | AS30: 5 | AT30: #NULL! | AU30: #NULL! | AV30: #NULL! | AX30: #NULL! | AY30: #NULL! | AZ30: #NULL! | BA30: #NULL! | BB30: I pay a majority of bill for “service center” - awful service. | BC30: 5 | BD30: #NULL! | BE30: #NULL! | BF30: #NULL! | BH30: #NULL! | BI30: #NULL! | BJ30: #NULL! | BK30: #NULL! | BL30: 3 | BM30: 8 | BN30: Excuses | BO30: 99 | BP30: #NULL! | BQ30: #NULL! | BR30: #NULL! | BS30: 1 | BT30: Just get me a live ‘helpful’ person | BU30: 99 | BV30: #NULL! | BW30: #NULL! | BX30: #NULL! | BZ30: #NULL! | CA30: #NULL! | CB30: #NULL! | CC30: 1 | CD30: 1 | CE30: 1 | CF30: 1 | CG30: 2 | CH30: Talk to someone else | CI30: 2 | CJ30: #NULL! | CK30: #NULL! | CL30: 1 | CM30: I pay a majority of bill for “service center” - awful service. | CN30: 7 | CO30: #NULL! | CP30: #NULL! | CQ30: 1 | CR30: 1 | CS30: 1 | CT30: 1 | CU30: 1 | CV30: 1 | CW30: 1 | CX30: 1 | CY30: 1 | CZ30: I pay a majority of bill for “service center” - awful service. | DA30: 5 | DB30: #NULL! | DC30: 1 | DD30: 1 | DE30: 1 | DF30: 0 | DG30: 0 | DH30: 0 | DI30: 1 | DJ30: 0 | DK30: 1 | DL30: 0 | DN30: 2 | DO30: I pay a majority of bill for “service center” - aweful service. | DP30: 3 | DQ30: #NULL! | DR30: #NULL! | DT30: #NULL! | DU30: #NULL! | DV30: #NULL! | DW30: 1 | DX30: 2 | DZ30: #NULL! | EA30: #NULL! | EI30: #NULL! | EJ30: #NULL! | EK30: #NULL! | EL30: #NULL! | EM30: 11 | EN30: 7 | EP30: 7 | EQ30: 5 | ER30: 3 | ES30: 78750 | ET30: 7 | EU30: 6 | EV30: 8 | EW30: 6 | EX30: 4 | EY30: j | EZ30: f | FB30: jfelger@hotmail.com | FC30: 5125551212 | FD30: #NULL! | FE30: #NULL! | FF30: 1 | FH30: 09 Sep 2025 - 16:27:52 CDT | FI30: 7737
A31: 190 | B31: 1 | C31: 2 | D31: 1 | E31: #NULL! | F31: 2 | G31: 2 | H31: 2 | J31: 1 | K31: 11 | P31: #NULL! | Q31: #NULL! | R31: #NULL! | S31: #NULL! | T31: 11 | U31: 4 | V31: 2 | W31: 8 | Y31: #NULL! | Z31: #NULL! | AA31: #NULL! | AB31: #NULL! | AD31: #NULL! | AE31: #NULL! | AF31: #NULL! | AG31: #NULL! | AI31: #NULL! | AJ31: #NULL! | AK31: #NULL! | AL31: #NULL! | AN31: #NULL! | AO31: #NULL! | AP31: #NULL! | AQ31: #NULL! | AR31: I prefer to communicate with another human | AS31: 3 | AT31: #NULL! | AU31: #NULL! | AV31: #NULL! | AX31: #NULL! | AY31: #NULL! | AZ31: #NULL! | BA31: #NULL! | BC31: #NULL! | BD31: #NULL! | BE31: #NULL! | BF31: #NULL! | BG31: Because the wait time was not long | BH31: 21 | BI31: #NULL! | BJ31: #NULL! | BK31: #NULL! | BL31: 2 | BM31: 6 | BN31: I don’t remember honestly, I think it was an automated message with a reminder that I could visit the website as well or I can choose to be called back if I wanted | BO31: 1 | BP31: 13 | BQ31: #NULL! | BR31: #NULL! | BS31: 10 | BT31: No elevator or opera music is all I ask | BU31: 21 | BV31: #NULL! | BW31: #NULL! | BX31: #NULL! | BZ31: #NULL! | CA31: #NULL! | CB31: #NULL! | CC31: 2 | CD31: #NULL! | CE31: 2 | CF31: #NULL! | CG31: #NULL! | CI31: #NULL! | CJ31: #NULL! | CK31: #NULL! | CL31: #NULL! | CN31: #NULL! | CO31: #NULL! | CP31: #NULL! | CQ31: 2 | CR31: #NULL! | CS31: 10 | CT31: 10 | CU31: 10 | CV31: 10 | CW31: 10 | CX31: 10 | CY31: 10 | DA31: #NULL! | DB31: #NULL! | DC31: 9 | DD31: #NULL! | DE31: #NULL! | DF31: #NULL! | DG31: #NULL! | DH31: #NULL! | DI31: #NULL! | DJ31: #NULL! | DK31: #NULL! | DL31: #NULL! | DN31: 1 | DP31: #NULL! | DQ31: #NULL! | DR31: #NULL! | DT31: #NULL! | DU31: #NULL! | DV31: #NULL! | DW31: 3 | DX31: 2 | DZ31: #NULL! | EA31: #NULL! | EI31: #NULL! | EJ31: #NULL! | EK31: #NULL! | EL31: #NULL! | EM31: 2 | EN31: 3 | EP31: 7 | EQ31: 2 | ER31: 1 | ES31: 78744 | ET31: 3 | EU31: 1 | EV31: 1 | EW31: 5 | EX31: 2 | EY31: Jessica | EZ31: Castillo | FB31: Jessdontfwu45@gmail.com | FC31: 7372680575 | FD31: #NULL! | FE31: #NULL! | FF31: 2 | FH31: 09 Sep 2025 - 18:05:12 CDT | FI31: 8368
A32: 206 | B32: 1 | C32: 2 | D32: 1 | E32: #NULL! | F32: 3 | G32: 2 | H32: 2 | J32: 2 | K32: 5 | O32: I discontinued service and I am still being charged for electricity | P32: 1 | Q32: #NULL! | R32: #NULL! | S32: #NULL! | T32: 1 | U32: 1 | V32: 1 | W32: 3 | X32: My request to discontinue service has resulted in my still being charged | Y32: 99 | Z32: #NULL! | AA32: #NULL! | AB32: #NULL! | AD32: #NULL! | AE32: #NULL! | AF32: #NULL! | AG32: #NULL! | AH32: No response about why I am still being charged for service | AI32: 7 | AJ32: #NULL! | AK32: #NULL! | AL32: #NULL! | AN32: #NULL! | AO32: #NULL! | AP32: #NULL! | AQ32: #NULL! | AR32: Bad | AS32: 7 | AT32: #NULL! | AU32: #NULL! | AV32: #NULL! | AX32: #NULL! | AY32: #NULL! | AZ32: #NULL! | BA32: #NULL! | BB32: Irrelevant | BC32: 99 | BD32: #NULL! | BE32: #NULL! | BF32: #NULL! | BH32: #NULL! | BI32: #NULL! | BJ32: #NULL! | BK32: #NULL! | BL32: 2 | BM32: 10 | BN32: That's is a stupid question | BO32: 99 | BP32: #NULL! | BQ32: #NULL! | BR32: #NULL! | BS32: 1 | BT32: This is wasting my time. Stop charging me for service when I requested disconnection for august 19 | BU32: 99 | BV32: #NULL! | BW32: #NULL! | BX32: #NULL! | BZ32: #NULL! | CA32: #NULL! | CB32: #NULL! | CC32: 2 | CD32: #NULL! | CE32: 2 | CF32: #NULL! | CG32: #NULL! | CI32: #NULL! | CJ32: #NULL! | CK32: #NULL! | CL32: #NULL! | CN32: #NULL! | CO32: #NULL! | CP32: #NULL! | CQ32: 2 | CR32: #NULL! | CS32: 7 | CT32: 5 | CU32: 6 | CV32: 1 | CW32: 3 | CX32: 5 | CY32: 11 | CZ32: Stop my service per my request!!!! | DA32: 2 | DB32: #NULL! | DC32: 1 | DD32: 0 | DE32: 1 | DF32: 0 | DG32: 0 | DH32: 0 | DI32: 0 | DJ32: 0 | DK32: 0 | DL32: 0 | DN32: 2 | DO32: Stop charging me for my service | DP32: 99 | DQ32: #NULL! | DR32: #NULL! | DT32: #NULL! | DU32: #NULL! | DV32: #NULL! | DW32: 1 | DX32: 2 | DZ32: #NULL! | EA32: #NULL! | EI32: #NULL! | EJ32: #NULL! | EK32: #NULL! | EL32: #NULL! | EM32: 10 | EN32: 1 | EP32: 1 | EQ32: 1 | ER32: 1 | ES32: 99999 | ET32: 7 | EU32: 4 | EV32: 6 | EW32: 4 | EX32: 1 | EY32: Kestutis | EZ32: Stanciauskas | FB32: kstanciauskas@gmail.com | FC32: 7373410064 | FD32: #NULL! | FE32: #NULL! | FF32: 2 | FH32: 10 Sep 2025 - 07:26:46 CDT | FI32: 10950
A33: 213 | B33: 1 | C33: 2 | D33: 1 | E33: #NULL! | F33: 2 | G33: 2 | H33: 2 | J33: 1 | K33: 11 | P33: #NULL! | Q33: #NULL! | R33: #NULL! | S33: #NULL! | T33: 10 | U33: 10 | V33: 10 | W33: 10 | Y33: #NULL! | Z33: #NULL! | AA33: #NULL! | AB33: #NULL! | AC33: Quick responses to get you to the right agent. They answer really quick | AD33: 21 | AE33: #NULL! | AF33: #NULL! | AG33: #NULL! | AI33: #NULL! | AJ33: #NULL! | AK33: #NULL! | AL33: #NULL! | AM33: Very knowledgeable and if not will get you to the right department | AN33: 25 | AO33: #NULL! | AP33: #NULL! | AQ33: #NULL! | AS33: #NULL! | AT33: #NULL! | AU33: #NULL! | AV33: #NULL! | AW33: Very easy service to use | AX33: 27 | AY33: #NULL! | AZ33: #NULL! | BA33: #NULL! | BC33: #NULL! | BD33: #NULL! | BE33: #NULL! | BF33: #NULL! | BG33: Very short | BH33: 21 | BI33: #NULL! | BJ33: #NULL! | BK33: #NULL! | BL33: 2 | BM33: 3 | BN33: I heard piano music | BO33: 20 | BP33: #NULL! | BQ33: #NULL! | BR33: #NULL! | BS33: 10 | BT33: Someone will be with you shortly | BU33: 6 | BV33: #NULL! | BW33: #NULL! | BX33: #NULL! | BZ33: #NULL! | CA33: #NULL! | CB33: #NULL! | CC33: 2 | CD33: #NULL! | CE33: 1 | CF33: 1 | CG33: 1 | CH33: Different department needed for my situation | CI33: 1 | CJ33: #NULL! | CK33: #NULL! | CL33: 10 | CN33: #NULL! | CO33: #NULL! | CP33: #NULL! | CQ33: 2 | CR33: #NULL! | CS33: 10 | CT33: 10 | CU33: 10 | CV33: 10 | CW33: 10 | CX33: 10 | CY33: 10 | DA33: #NULL! | DB33: #NULL! | DC33: 10 | DD33: #NULL! | DE33: #NULL! | DF33: #NULL! | DG33: #NULL! | DH33: #NULL! | DI33: #NULL! | DJ33: #NULL! | DK33: #NULL! | DL33: #NULL! | DN33: 1 | DP33: #NULL! | DQ33: #NULL! | DR33: #NULL! | DT33: #NULL! | DU33: #NULL! | DV33: #NULL! | DW33: 2 | DX33: 2 | DZ33: #NULL! | EA33: #NULL! | EI33: #NULL! | EJ33: #NULL! | EK33: #NULL! | EL33: #NULL! | EM33: 7 | EN33: 7 | EP33: 1 | EQ33: 5 | ER33: 3 | ES33: 99999 | ET33: 1 | EU33: 4 | EV33: 8 | EW33: 5 | EX33: 2 | EY33: Kimbelry | EZ33: Richardson-Diji | FB33: kimberlysrichardson@gmail.com | FC33: 7779311 | FD33: #NULL! | FE33: #NULL! | FF33: 1 | FH33: 10 Sep 2025 - 08:37:26 CDT | FI33: 333
A34: 228 | B34: 1 | C34: 2 | D34: 1 | E34: #NULL! | F34: 2 | G34: 2 | H34: 3 | J34: 1 | K34: 21 | P34: #NULL! | Q34: #NULL! | R34: #NULL! | S34: #NULL! | T34: 10 | U34: 10 | V34: 10 | W34: 10 | Y34: #NULL! | Z34: #NULL! | AA34: #NULL! | AB34: #NULL! | AC34: They were helpful | AD34: 25 | AE34: #NULL! | AF34: #NULL! | AG34: #NULL! | AI34: #NULL! | AJ34: #NULL! | AK34: #NULL! | AL34: #NULL! | AM34: Helpful | AN34: 25 | AO34: #NULL! | AP34: #NULL! | AQ34: #NULL! | AS34: #NULL! | AT34: #NULL! | AU34: #NULL! | AV34: #NULL! | AW34: Helpful | AX34: 25 | AY34: #NULL! | AZ34: #NULL! | BA34: #NULL! | BC34: #NULL! | BD34: #NULL! | BE34: #NULL! | BF34: #NULL! | BG34: They were very kind | BH34: 24 | BI34: #NULL! | BJ34: #NULL! | BK34: #NULL! | BL34: 2 | BM34: 7 | BN34: Music | BO34: 20 | BP34: #NULL! | BQ34: #NULL! | BR34: #NULL! | BS34: 10 | BT34: Nothing | BU34: 97 | BV34: #NULL! | BW34: #NULL! | BX34: #NULL! | BZ34: #NULL! | CA34: #NULL! | CB34: #NULL! | CC34: 1 | CD34: 8 | CE34: 2 | CF34: #NULL! | CG34: #NULL! | CI34: #NULL! | CJ34: #NULL! | CK34: #NULL! | CL34: #NULL! | CN34: #NULL! | CO34: #NULL! | CP34: #NULL! | CQ34: 2 | CR34: #NULL! | CS34: 10 | CT34: 10 | CU34: 10 | CV34: 10 | CW34: 10 | CX34: 10 | CY34: 10 | DA34: #NULL! | DB34: #NULL! | DC34: 10 | DD34: #NULL! | DE34: #NULL! | DF34: #NULL! | DG34: #NULL! | DH34: #NULL! | DI34: #NULL! | DJ34: #NULL! | DK34: #NULL! | DL34: #NULL! | DN34: 1 | DP34: #NULL! | DQ34: #NULL! | DR34: #NULL! | DT34: #NULL! | DU34: #NULL! | DV34: #NULL! | DW34: 2 | DX34: 1 | DY34: Online and texted | DZ34: 5 | EA34: #NULL! | EI34: #NULL! | EJ34: #NULL! | EK34: #NULL! | EL34: #NULL! | EM34: 9 | EN34: 1 | EP34: 1 | EQ34: 3 | ER34: 2 | ES34: 78702 | ET34: 2 | EU34: 3 | EV34: 6 | EW34: 5 | EX34: 2 | EY34: Laura | EZ34: Cox | FB34: lauraycox@gmail.com | FC34: 512-587-8046 | FD34: #NULL! | FE34: #NULL! | FF34: 2 | FH34: 10 Sep 2025 - 10:26:05 CDT | FI34: 12220
A35: 253 | B35: 1 | C35: 2 | D35: 1 | E35: #NULL! | F35: 2 | G35: 2 | H35: 3 | J35: 1 | K35: 21 | P35: #NULL! | Q35: #NULL! | R35: #NULL! | S35: #NULL! | T35: 8 | U35: 7 | V35: 7 | W35: 9 | Y35: #NULL! | Z35: #NULL! | AA35: #NULL! | AB35: #NULL! | AC35: A live person would be best | AD35: 3 | AE35: #NULL! | AF35: #NULL! | AG35: #NULL! | AI35: #NULL! | AJ35: #NULL! | AK35: #NULL! | AL35: #NULL! | AN35: #NULL! | AO35: #NULL! | AP35: #NULL! | AQ35: #NULL! | AS35: #NULL! | AT35: #NULL! | AU35: #NULL! | AV35: #NULL! | AX35: #NULL! | AY35: #NULL! | AZ35: #NULL! | BA35: #NULL! | BC35: #NULL! | BD35: #NULL! | BE35: #NULL! | BF35: #NULL! | BG35: No wait time is preferable | BH35: 21 | BI35: #NULL! | BJ35: #NULL! | BK35: #NULL! | BL35: 2 | BM35: 7 | BN35: Do not recall | BO35: 98 | BP35: #NULL! | BQ35: #NULL! | BR35: #NULL! | BS35: 10 | BT35: Wait time, option to leave message with return call, phone number of representatives to call back later if have to hang up | BU35: 6 | BV35: 13 | BW35: #NULL! | BX35: #NULL! | BZ35: #NULL! | CA35: #NULL! | CB35: #NULL! | CC35: 1 | CD35: 10 | CE35: 1 | CF35: 1 | CG35: 2 | CH35: Wrong person with wrong answer on the reply - I was told. | CI35: 1 | CJ35: #NULL! | CK35: #NULL! | CL35: 7 | CM35: I was never given a response on how my waste water was measured. We had a high no period (5200 gallons) so wanted to confirm the start date of no 16. | CN35: 7 | CO35: #NULL! | CP35: #NULL! | CQ35: 2 | CR35: #NULL! | CS35: 10 | CT35: 10 | CU35: 10 | CV35: 10 | CW35: 10 | CX35: 10 | CY35: 10 | DA35: #NULL! | DB35: #NULL! | DC35: 6 | DD35: 0 | DE35: 1 | DF35: 0 | DG35: 0 | DH35: 0 | DI35: 0 | DJ35: 0 | DK35: 0 | DL35: 0 | DN35: 2 | DO35: Answer my question - on was the start date for the 3 months averaging of waste water no 16. | DP35: 4 | DQ35: #NULL! | DR35: #NULL! | DT35: #NULL! | DU35: #NULL! | DV35: #NULL! | DW35: 2 | DX35: 2 | DZ35: #NULL! | EA35: #NULL! | EI35: #NULL! | EJ35: #NULL! | EK35: #NULL! | EL35: #NULL! | EM35: 9 | EN35: 1 | EP35: 1 | EQ35: 1 | ER35: 2 | ES35: 78731 | ET35: 2 | EU35: 5 | EV35: 6 | EW35: 5 | EX35: 2 | EY35: Louri | EZ35: OLeary | FB35: loleary2@gmail.com | FC35: 5124771615 | FD35: #NULL! | FE35: #NULL! | FF35: 2 | FH35: 10 Sep 2025 - 14:36:14 CDT | FI35: 10981
A36: 254 | B36: 1 | C36: 2 | D36: 1 | E36: #NULL! | F36: 2 | G36: 2 | H36: 2 | J36: 1 | K36: 19 | P36: #NULL! | Q36: #NULL! | R36: #NULL! | S36: #NULL! | T36: 4 | U36: 7 | V36: 7 | W36: 7 | Y36: #NULL! | Z36: #NULL! | AA36: #NULL! | AB36: #NULL! | AD36: #NULL! | AE36: #NULL! | AF36: #NULL! | AG36: #NULL! | AI36: #NULL! | AJ36: #NULL! | AK36: #NULL! | AL36: #NULL! | AN36: #NULL! | AO36: #NULL! | AP36: #NULL! | AQ36: #NULL! | AS36: #NULL! | AT36: #NULL! | AU36: #NULL! | AV36: #NULL! | AX36: #NULL! | AY36: #NULL! | AZ36: #NULL! | BA36: #NULL! | BC36: #NULL! | BD36: #NULL! | BE36: #NULL! | BF36: #NULL! | BH36: #NULL! | BI36: #NULL! | BJ36: #NULL! | BK36: #NULL! | BL36: 2 | BM36: 5 | BN36: Something like" your message is important to us. Please wait for a customer service representative". I initially called Austin 311 to report a power outage but was told to call Austin energy directly. | BO36: 2 | BP36: #NULL! | BQ36: #NULL! | BR36: #NULL! | BS36: 8 | BT36: What information they will be asking from me. How long will wait be. Another number to call if the response time is delayed. | BU36: 22 | BV36: #NULL! | BW36: #NULL! | BX36: #NULL! | BZ36: #NULL! | CA36: #NULL! | CB36: #NULL! | CC36: 2 | CD36: #NULL! | CE36: 1 | CF36: 2 | CG36: #NULL! | CI36: #NULL! | CJ36: #NULL! | CK36: #NULL! | CL36: #NULL! | CN36: #NULL! | CO36: #NULL! | CP36: #NULL! | CQ36: 2 | CR36: #NULL! | CS36: 9 | CT36: 7 | CU36: 9 | CV36: 11 | CW36: 8 | CX36: 10 | CY36: 7 | DA36: #NULL! | DB36: #NULL! | DC36: 8 | DD36: #NULL! | DE36: #NULL! | DF36: #NULL! | DG36: #NULL! | DH36: #NULL! | DI36: #NULL! | DJ36: #NULL! | DK36: #NULL! | DL36: #NULL! | DN36: 1 | DP36: #NULL! | DQ36: #NULL! | DR36: #NULL! | DT36: #NULL! | DU36: #NULL! | DV36: #NULL! | DW36: 3 | DX36: 2 | DZ36: #NULL! | EA36: #NULL! | EI36: #NULL! | EJ36: #NULL! | EK36: #NULL! | EL36: #NULL! | EM36: 10 | EN36: 1 | EP36: 5 | EQ36: 1 | ER36: 2 | ES36: 78749 | ET36: 2 | EU36: 4 | EV36: 5 | EW36: 5 | EX36: 2 | EY36: Marcia | EZ36: Desy | FB36: marciadesy@sbcglobal.net | FC36: 5126193537 | FD36: #NULL! | FE36: #NULL! | FF36: 1 | FH36: 10 Sep 2025 - 14:37:23 CDT | FI36: 1624
A37: 259 | B37: 1 | C37: 2 | D37: 1 | E37: #NULL! | F37: 2 | G37: 2 | H37: 4 | I37: All | J37: 1 | K37: 33 | N37: Requesting help in paying my bill. | P37: #NULL! | Q37: #NULL! | R37: #NULL! | S37: #NULL! | T37: 5 | U37: 5 | V37: 5 | W37: 10 | Y37: #NULL! | Z37: #NULL! | AA37: #NULL! | AB37: #NULL! | AD37: #NULL! | AE37: #NULL! | AF37: #NULL! | AG37: #NULL! | AI37: #NULL! | AJ37: #NULL! | AK37: #NULL! | AL37: #NULL! | AN37: #NULL! | AO37: #NULL! | AP37: #NULL! | AQ37: #NULL! | AS37: #NULL! | AT37: #NULL! | AU37: #NULL! | AV37: #NULL! | AX37: #NULL! | AY37: #NULL! | AZ37: #NULL! | BA37: #NULL! | BC37: #NULL! | BD37: #NULL! | BE37: #NULL! | BF37: #NULL! | BG37: 8 | BH37: #NULL! | BI37: #NULL! | BJ37: #NULL! | BK37: #NULL! | BL37: 2 | BM37: 7 | BN37: Don’t remember | BO37: 98 | BP37: #NULL! | BQ37: #NULL! | BR37: #NULL! | BS37: 10 | BT37: N/a | BU37: 97 | BV37: #NULL! | BW37: #NULL! | BX37: #NULL! | BZ37: #NULL! | CA37: #NULL! | CB37: #NULL! | CC37: 2 | CD37: #NULL! | CE37: 2 | CF37: #NULL! | CG37: #NULL! | CI37: #NULL! | CJ37: #NULL! | CK37: #NULL! | CL37: #NULL! | CN37: #NULL! | CO37: #NULL! | CP37: #NULL! | CQ37: 2 | CR37: #NULL! | CS37: 10 | CT37: 5 | CU37: 5 | CV37: 1 | CW37: 1 | CX37: 10 | CY37: 5 | CZ37: The car gave me incorrect information. She stated clearly that my electric service needed to be disconnected before they could offer assistance in paying my bill. | DA37: 4 | DB37: #NULL! | DC37: 1 | DD37: 0 | DE37: 1 | DF37: 0 | DG37: 0 | DH37: 0 | DI37: 0 | DJ37: 0 | DK37: 0 | DL37: 0 | DN37: 2 | DO37: Provide correct information. | DP37: 4 | DQ37: #NULL! | DR37: #NULL! | DT37: #NULL! | DU37: #NULL! | DV37: #NULL! | DW37: 1 | DX37: 2 | DZ37: #NULL! | EA37: #NULL! | EI37: #NULL! | EJ37: #NULL! | EK37: #NULL! | EL37: #NULL! | EM37: 10 | EN37: 1 | EP37: 5 | EQ37: 2 | ER37: 2 | ES37: 78741 | ET37: 2 | EU37: 5 | EV37: 1 | EW37: 5 | EX37: 1 | EY37: Michael | EZ37: Roach | FB37: mgroach2@gmail.com | FC37: 5127053125 | FD37: #NULL! | FE37: #NULL! | FF37: 2 | FH37: 10 Sep 2025 - 15:05:58 CDT | FI37: 3539
A38: 262 | B38: 1 | C38: 2 | D38: 1 | E38: #NULL! | F38: 3 | G38: 2 | H38: 2 | J38: 1 | K38: 5 | P38: #NULL! | Q38: #NULL! | R38: #NULL! | S38: #NULL! | T38: 10 | U38: 10 | V38: 10 | W38: 10 | Y38: #NULL! | Z38: #NULL! | AA38: #NULL! | AB38: #NULL! | AC38: I've been with COA for many years. Never had any problem with y'all | AD38: 28 | AE38: #NULL! | AF38: #NULL! | AG38: #NULL! | AI38: #NULL! | AJ38: #NULL! | AK38: #NULL! | AL38: #NULL! | AM38: Ditto | AN38: 28 | AO38: #NULL! | AP38: #NULL! | AQ38: #NULL! | AS38: #NULL! | AT38: #NULL! | AU38: #NULL! | AV38: #NULL! | AW38: Ditto | AX38: 28 | AY38: #NULL! | AZ38: #NULL! | BA38: #NULL! | BC38: #NULL! | BD38: #NULL! | BE38: #NULL! | BF38: #NULL! | BG38: Ditto | BH38: 28 | BI38: #NULL! | BJ38: #NULL! | BK38: #NULL! | BL38: 2 | BM38: 4 | BN38: Not sure | BO38: 98 | BP38: #NULL! | BQ38: #NULL! | BR38: #NULL! | BS38: 7 | BT38: I don't know | BU38: 98 | BV38: #NULL! | BW38: #NULL! | BX38: #NULL! | BZ38: #NULL! | CA38: #NULL! | CB38: #NULL! | CC38: 2 | CD38: #NULL! | CE38: 2 | CF38: #NULL! | CG38: #NULL! | CI38: #NULL! | CJ38: #NULL! | CK38: #NULL! | CL38: #NULL! | CN38: #NULL! | CO38: #NULL! | CP38: #NULL! | CQ38: 2 | CR38: #NULL! | CS38: 10 | CT38: 10 | CU38: 10 | CV38: 10 | CW38: 10 | CX38: 10 | CY38: 10 | DA38: #NULL! | DB38: #NULL! | DC38: 10 | DD38: #NULL! | DE38: #NULL! | DF38: #NULL! | DG38: #NULL! | DH38: #NULL! | DI38: #NULL! | DJ38: #NULL! | DK38: #NULL! | DL38: #NULL! | DN38: 1 | DP38: #NULL! | DQ38: #NULL! | DR38: #NULL! | DT38: #NULL! | DU38: #NULL! | DV38: #NULL! | DW38: 3 | DX38: 3 | DZ38: #NULL! | EA38: #NULL! | EI38: #NULL! | EJ38: #NULL! | EK38: #NULL! | EL38: #NULL! | EM38: 10 | EN38: 6 | EO38: Irish, Cherokee | EP38: 5 | EQ38: 3 | ER38: 1 | ES38: 78753 | ET38: 1 | EU38: 4 | EV38: 3 | EW38: 5 | EX38: 2 | EY38: Brenda | EZ38: Miller | FB38: Brendatubbs2002@yahoo.com | FC38: 512-497-2289 | FD38: #NULL! | FE38: #NULL! | FF38: 3 | FH38: 10 Sep 2025 - 15:41:20 CDT | FI38: 27559
A39: 264 | B39: 1 | C39: 2 | D39: 1 | E39: #NULL! | F39: 2 | G39: 2 | H39: 2 | J39: 2 | K39: 2 | O39: For over 6 months, I’ve been trying to resolve overbilling on my account. Lately, my point of contact is supervisor joseph Hernandez. His favorite line is "I’ve resolved the issue and everything has been straightened out and you should see the corrected results on next month's bill. But next month’s bill is the same or worse. | P39: 1 | Q39: #NULL! | R39: #NULL! | S39: #NULL! | T39: 1 | U39: 1 | V39: 1 | W39: 1 | X39: 1 | Y39: #NULL! | Z39: #NULL! | AA39: #NULL! | AB39: #NULL! | AD39: #NULL! | AE39: #NULL! | AF39: #NULL! | AG39: #NULL! | AH39: 1 | AI39: #NULL! | AJ39: #NULL! | AK39: #NULL! | AL39: #NULL! | AN39: #NULL! | AO39: #NULL! | AP39: #NULL! | AQ39: #NULL! | AR39: 1 | AS39: #NULL! | AT39: #NULL! | AU39: #NULL! | AV39: #NULL! | AX39: #NULL! | AY39: #NULL! | AZ39: #NULL! | BA39: #NULL! | BB39: 1 | BC39: #NULL! | BD39: #NULL! | BE39: #NULL! | BF39: #NULL! | BH39: #NULL! | BI39: #NULL! | BJ39: #NULL! | BK39: #NULL! | BL39: 4 | BM39: #NULL! | BO39: #NULL! | BP39: #NULL! | BQ39: #NULL! | BR39: #NULL! | BS39: #NULL! | BU39: #NULL! | BV39: #NULL! | BW39: #NULL! | BX39: 1 | BY39: Mr. Joseph Hernandez has not returned the last 3 phone calls; I left for him. | BZ39: 1 | CA39: #NULL! | CB39: #NULL! | CC39: 1 | CD39: 1 | CE39: 1 | CF39: 3 | CG39: #NULL! | CI39: #NULL! | CJ39: #NULL! | CK39: #NULL! | CL39: #NULL! | CN39: #NULL! | CO39: #NULL! | CP39: #NULL! | CQ39: 1 | CR39: 1 | CS39: 1 | CT39: 1 | CU39: 1 | CV39: 1 | CW39: 1 | CX39: 1 | CY39: 1 | CZ39: After 6 months, I would have thought Mr. Joseph Hernandez could resolve the problem but in fact the problem just gets delayed another month. | DA39: 2 | DB39: #NULL! | DC39: 1 | DD39: 0 | DE39: 0 | DF39: 0 | DG39: 0 | DH39: 0 | DI39: 1 | DJ39: 0 | DK39: 0 | DL39: 0 | DN39: 2 | DO39: Resolve the billing issues, working from your own billing. Learn how to use a calculator??? Who knows-this is totally unbelievable!!! | DP39: 4 | DQ39: 9 | DR39: #NULL! | DT39: #NULL! | DU39: #NULL! | DV39: #NULL! | DW39: 1 | DX39: 2 | DZ39: #NULL! | EA39: #NULL! | EI39: #NULL! | EJ39: #NULL! | EK39: #NULL! | EL39: #NULL! | EM39: 10 | EN39: 7 | EP39: 5 | EQ39: 5 | ER39: 3 | ES39: 78758 | ET39: 7 | EU39: 5 | EV39: 1 | EW39: 5 | EX39: 1 | EY39: EDWARD | EZ39: GRUENDLER | FB39: ed_gruendler@yahoo.com | FC39: 5127928618 | FD39: #NULL! | FE39: #NULL! | FF39: 2 | FH39: 10 Sep 2025 - 15:53:11 CDT | FI39: 4534
A40: 271 | B40: 1 | C40: 2 | D40: 1 | E40: #NULL! | F40: 2 | G40: 2 | H40: 4 | I40: Tree branches interfering with power lines | J40: 1 | K40: 19 | P40: #NULL! | Q40: #NULL! | R40: #NULL! | S40: #NULL! | T40: 10 | U40: 10 | V40: 10 | W40: 10 | Y40: #NULL! | Z40: #NULL! | AA40: #NULL! | AB40: #NULL! | AC40: My call was handled quickly and efficiently. | AD40: 21 | AE40: #NULL! | AF40: #NULL! | AG40: #NULL! | AI40: #NULL! | AJ40: #NULL! | AK40: #NULL! | AL40: #NULL! | AM40: My call was handled quickly and efficiently. | AN40: 21 | AO40: #NULL! | AP40: #NULL! | AQ40: #NULL! | AS40: #NULL! | AT40: #NULL! | AU40: #NULL! | AV40: #NULL! | AW40: My call was handled quickly and efficiently. | AX40: 21 | AY40: #NULL! | AZ40: #NULL! | BA40: #NULL! | BC40: #NULL! | BD40: #NULL! | BE40: #NULL! | BF40: #NULL! | BG40: My call was handled quickly and efficiently. | BH40: 21 | BI40: #NULL! | BJ40: #NULL! | BK40: #NULL! | BL40: 2 | BM40: 4 | BN40: I don’t remember. | BO40: 98 | BP40: #NULL! | BQ40: #NULL! | BR40: #NULL! | BS40: 9 | BT40: Perhaps a message about little-known city services, such as the Austin recycling center, would be helpful. | BU40: 1 | BV40: #NULL! | BW40: #NULL! | BX40: #NULL! | BZ40: #NULL! | CA40: #NULL! | CB40: #NULL! | CC40: 2 | CD40: #NULL! | CE40: 2 | CF40: #NULL! | CG40: #NULL! | CI40: #NULL! | CJ40: #NULL! | CK40: #NULL! | CL40: #NULL! | CN40: #NULL! | CO40: #NULL! | CP40: #NULL! | CQ40: 2 | CR40: #NULL! | CS40: 10 | CT40: 10 | CU40: 10 | CV40: 11 | CW40: 10 | CX40: 10 | CY40: 10 | DA40: #NULL! | DB40: #NULL! | DC40: 8 | DD40: #NULL! | DE40: #NULL! | DF40: #NULL! | DG40: #NULL! | DH40: #NULL! | DI40: #NULL! | DJ40: #NULL! | DK40: #NULL! | DL40: #NULL! | DN40: 2 | DO40: The call was a success, but the city is not going to take care of the tree branch issue I called about because the lines are not their lines. So, the call was completely satisfactory, but the result is not what I wished. Not the city or Austin energy ‘s fault at all. | DP40: 99 | DQ40: #NULL! | DR40: #NULL! | DT40: #NULL! | DU40: #NULL! | DV40: #NULL! | DW40: 3 | DX40: 1 | DY40: I’m sorry to say I don’t remember. | DZ40: 98 | EA40: #NULL! | EI40: #NULL! | EJ40: #NULL! | EK40: #NULL! | EL40: #NULL! | EM40: 7 | EN40: 1 | EP40: 2 | EQ40: 2 | ER40: 2 | ES40: 78753 | ET40: 1 | EU40: 4 | EV40: 2 | EW40: 5 | EX40: 2 | EY40: Deborah | EZ40: Cobb | FB40: deborahcfreeman@yahoo.com | FC40: 5129635352 | FD40: #NULL! | FE40: #NULL! | FF40: 3 | FH40: 10 Sep 2025 - 16:11:50 CDT | FI40: 13785
A41: 277 | B41: 1 | C41: 2 | D41: 1 | E41: #NULL! | F41: 2 | G41: 2 | H41: 3 | J41: 1 | K41: 2 | P41: #NULL! | Q41: #NULL! | R41: #NULL! | S41: #NULL! | T41: 1 | U41: 1 | V41: 1 | W41: 2 | X41: Machine | Y41: 4 | Z41: #NULL! | AA41: #NULL! | AB41: #NULL! | AD41: #NULL! | AE41: #NULL! | AF41: #NULL! | AG41: #NULL! | AH41: No | AI41: 97 | AJ41: #NULL! | AK41: #NULL! | AL41: #NULL! | AN41: #NULL! | AO41: #NULL! | AP41: #NULL! | AQ41: #NULL! | AR41: No | AS41: 99 | AT41: #NULL! | AU41: #NULL! | AV41: #NULL! | AX41: #NULL! | AY41: #NULL! | AZ41: #NULL! | BA41: #NULL! | BB41: Duh | BC41: 99 | BD41: #NULL! | BE41: #NULL! | BF41: #NULL! | BH41: #NULL! | BI41: #NULL! | BJ41: #NULL! | BK41: #NULL! | BL41: 4 | BM41: #NULL! | BO41: #NULL! | BP41: #NULL! | BQ41: #NULL! | BR41: #NULL! | BS41: #NULL! | BU41: #NULL! | BV41: #NULL! | BW41: #NULL! | BX41: 1 | BY41: We’re not well informed. | BZ41: 4 | CA41: #NULL! | CB41: #NULL! | CC41: 3 | CD41: #NULL! | CE41: 1 | CF41: 3 | CG41: #NULL! | CI41: #NULL! | CJ41: #NULL! | CK41: #NULL! | CL41: #NULL! | CN41: #NULL! | CO41: #NULL! | CP41: #NULL! | CQ41: 1 | CR41: 4 | CS41: 7 | CT41: 7 | CU41: 7 | CV41: 5 | CW41: 8 | CX41: 5 | CY41: 7 | CZ41: Gigg | DA41: 99 | DB41: #NULL! | DC41: 1 | DD41: 0 | DE41: 0 | DF41: 0 | DG41: 0 | DH41: 0 | DI41: 1 | DJ41: 0 | DK41: 0 | DL41: 0 | DN41: 1 | DP41: #NULL! | DQ41: #NULL! | DR41: #NULL! | DT41: #NULL! | DU41: #NULL! | DV41: #NULL! | DW41: 1 | DX41: 2 | DZ41: #NULL! | EA41: #NULL! | EI41: #NULL! | EJ41: #NULL! | EK41: #NULL! | EL41: #NULL! | EM41: 10 | EN41: 7 | EP41: 7 | EQ41: 5 | ER41: 2 | ES41: 78731 | ET41: 1 | EU41: 5 | EV41: 8 | EW41: 5 | EX41: 4 | EY41: Mark | EZ41: Thomas | FB41: markothomas88@yahoo.com | FC41: 5126581006 | FD41: #NULL! | FE41: #NULL! | FF41: 1 | FH41: 10 Sep 2025 - 16:30:17 CDT | FI41: 9108
A42: 279 | B42: 1 | C42: 2 | D42: 1 | E42: #NULL! | F42: 3 | G42: 2 | H42: 2 | J42: 2 | K42: 11 | O42: The bill was very high whereas I spent 80% of my time out busy with work. | P42: 1 | Q42: #NULL! | R42: #NULL! | S42: #NULL! | T42: 5 | U42: 9 | V42: 3 | W42: 9 | Y42: #NULL! | Z42: #NULL! | AA42: #NULL! | AB42: #NULL! | AD42: #NULL! | AE42: #NULL! | AF42: #NULL! | AG42: #NULL! | AI42: #NULL! | AJ42: #NULL! | AK42: #NULL! | AL42: #NULL! | AM42: Na | AN42: 97 | AO42: #NULL! | AP42: #NULL! | AQ42: #NULL! | AR42: Na | AS42: 97 | AT42: #NULL! | AU42: #NULL! | AV42: #NULL! | AX42: #NULL! | AY42: #NULL! | AZ42: #NULL! | BA42: #NULL! | BC42: #NULL! | BD42: #NULL! | BE42: #NULL! | BF42: #NULL! | BG42: They're quite quick to respond though. | BH42: 21 | BI42: #NULL! | BJ42: #NULL! | BK42: #NULL! | BL42: 5 | BM42: 5 | BN42: Na | BO42: 97 | BP42: #NULL! | BQ42: #NULL! | BR42: #NULL! | BS42: 11 | BT42: How to manage electricity consumption in your house 🏠. | BU42: 1 | BV42: #NULL! | BW42: #NULL! | BX42: #NULL! | BZ42: #NULL! | CA42: #NULL! | CB42: #NULL! | CC42: 1 | CD42: 11 | CE42: 3 | CF42: #NULL! | CG42: #NULL! | CI42: #NULL! | CJ42: #NULL! | CK42: #NULL! | CL42: #NULL! | CN42: #NULL! | CO42: #NULL! | CP42: #NULL! | CQ42: 2 | CR42: #NULL! | CS42: 10 | CT42: 9 | CU42: 10 | CV42: 9 | CW42: 9 | CX42: 10 | CY42: 9 | DA42: #NULL! | DB42: #NULL! | DC42: 1 | DD42: 0 | DE42: 1 | DF42: 0 | DG42: 0 | DH42: 0 | DI42: 0 | DJ42: 0 | DK42: 0 | DL42: 0 | DN42: 2 | DO42: The representative was good and kind but my issue was not resolved because it was at her power to do that. | DP42: 99 | DQ42: #NULL! | DR42: #NULL! | DT42: #NULL! | DU42: #NULL! | DV42: #NULL! | DW42: 3 | DX42: 2 | DZ42: #NULL! | EA42: #NULL! | EI42: #NULL! | EJ42: #NULL! | EK42: #NULL! | EL42: #NULL! | EM42: 3 | EN42: 2 | EP42: 1 | EQ42: 2 | ER42: 1 | ES42: 78753 | ET42: 1 | EU42: 4 | EV42: 3 | EW42: 4 | EX42: 1 | EY42: Elvis | EZ42: Fuenganghare | FB42: elvisfueng@gmail.com | FC42: 5127059947 | FD42: #NULL! | FE42: #NULL! | FF42: 3 | FH42: 10 Sep 2025 - 16:49:36 CDT | FI42: 18076
A43: 280 | B43: 1 | C43: 2 | D43: 1 | E43: #NULL! | F43: 2 | G43: 2 | H43: 3 | J43: 1 | K43: 13 | P43: #NULL! | Q43: #NULL! | R43: #NULL! | S43: #NULL! | T43: 10 | U43: 10 | V43: 10 | W43: 10 | Y43: #NULL! | Z43: #NULL! | AA43: #NULL! | AB43: #NULL! | AC43: Responding via punching in a numerical code for whatever service needed was easy & clear to understand | AD43: 20 | AE43: #NULL! | AF43: #NULL! | AG43: #NULL! | AI43: #NULL! | AJ43: #NULL! | AK43: #NULL! | AL43: #NULL! | AM43: I was provided with the info I needed easily | AN43: 27 | AO43: #NULL! | AP43: #NULL! | AQ43: #NULL! | AS43: #NULL! | AT43: #NULL! | AU43: #NULL! | AV43: #NULL! | AW43: I think this is an easy way to communicate to obtain very basic acct info | AX43: 27 | AY43: #NULL! | AZ43: #NULL! | BA43: #NULL! | BC43: #NULL! | BD43: #NULL! | BE43: #NULL! | BF43: #NULL! | BG43: Didn’t hardly have to wait for an answer | BH43: 21 | BI43: #NULL! | BJ43: #NULL! | BK43: #NULL! | BL43: 2 | BM43: 2 | BN43: I apologize I do not recall hearing anything while on hold | BO43: 98 | BP43: #NULL! | BQ43: #NULL! | BR43: #NULL! | BS43: 10 | BT43: Hours of operation, alternate ways to contact support or any other self-serve options | BU43: 12 | BV43: 2 | BW43: #NULL! | BX43: #NULL! | BZ43: #NULL! | CA43: #NULL! | CB43: #NULL! | CC43: 1 | CD43: 10 | CE43: 2 | CF43: #NULL! | CG43: #NULL! | CI43: #NULL! | CJ43: #NULL! | CK43: #NULL! | CL43: #NULL! | CN43: #NULL! | CO43: #NULL! | CP43: #NULL! | CQ43: 2 | CR43: #NULL! | CS43: 9 | CT43: 10 | CU43: 9 | CV43: 6 | CW43: 2 | CX43: 10 | CY43: 5 | CZ43: I wasn’t allowed to do any type of payment plan so we could to discuss it | DA43: 4 | DB43: #NULL! | DC43: 1 | DD43: 0 | DE43: 1 | DF43: 0 | DG43: 0 | DH43: 0 | DI43: 0 | DJ43: 0 | DK43: 0 | DL43: 0 | DN43: 1 | DP43: #NULL! | DQ43: #NULL! | DR43: #NULL! | DT43: #NULL! | DU43: #NULL! | DV43: #NULL! | DW43: 1 | DX43: 2 | DZ43: #NULL! | EA43: #NULL! | EI43: #NULL! | EJ43: #NULL! | EK43: #NULL! | EL43: #NULL! | EM43: 6 | EN43: 6 | EO43: White & Mexican American | EP43: 1 | EQ43: 2 | ER43: 1 | ES43: 78753 | ET43: 2 | EU43: 3 | EV43: 5 | EW43: 5 | EX43: 2 | EY43: Christel | EZ43: Stautzenberger | FB43: christelstautzenberger1@gmail.com | FC43: 5122966481 | FD43: #NULL! | FE43: #NULL! | FF43: 1 | FH43: 10 Sep 2025 - 17:00:54 CDT | FI43: 10107
A44: 285 | B44: 1 | C44: 2 | D44: 1 | E44: #NULL! | F44: 2 | G44: 2 | H44: 2 | J44: 1 | K44: 1 | P44: #NULL! | Q44: #NULL! | R44: #NULL! | S44: 5 | T44: 5 | U44: 5 | V44: 5 | W44: 5 | Y44: #NULL! | Z44: #NULL! | AA44: #NULL! | AB44: #NULL! | AD44: #NULL! | AE44: #NULL! | AF44: #NULL! | AG44: #NULL! | AI44: #NULL! | AJ44: #NULL! | AK44: #NULL! | AL44: #NULL! | AN44: #NULL! | AO44: #NULL! | AP44: #NULL! | AQ44: #NULL! | AS44: #NULL! | AT44: #NULL! | AU44: #NULL! | AV44: #NULL! | AX44: #NULL! | AY44: #NULL! | AZ44: #NULL! | BA44: #NULL! | BC44: #NULL! | BD44: #NULL! | BE44: #NULL! | BF44: #NULL! | BH44: #NULL! | BI44: #NULL! | BJ44: #NULL! | BK44: #NULL! | BL44: 2 | BM44: 6 | BN44: Leave phone number for call back | BO44: 13 | BP44: #NULL! | BQ44: #NULL! | BR44: #NULL! | BS44: 6 | BT44: None | BU44: 97 | BV44: #NULL! | BW44: #NULL! | BX44: #NULL! | BZ44: #NULL! | CA44: #NULL! | CB44: #NULL! | CC44: 2 | CD44: #NULL! | CE44: 1 | CF44: 3 | CG44: #NULL! | CI44: #NULL! | CJ44: #NULL! | CK44: #NULL! | CL44: #NULL! | CN44: #NULL! | CO44: #NULL! | CP44: #NULL! | CQ44: 2 | CR44: #NULL! | CS44: 9 | CT44: 5 | CU44: 6 | CV44: 5 | CW44: 5 | CX44: 8 | CY44: 5 | CZ44: Mo | DA44: 97 | DB44: #NULL! | DC44: 5 | DD44: 0 | DE44: 0 | DF44: 0 | DG44: 0 | DH44: 0 | DI44: 0 | DJ44: 1 | DK44: 0 | DL44: 0 | DN44: 1 | DP44: #NULL! | DQ44: #NULL! | DR44: #NULL! | DT44: #NULL! | DU44: #NULL! | DV44: #NULL! | DW44: 2 | DX44: 2 | DZ44: #NULL! | EA44: #NULL! | EI44: #NULL! | EJ44: #NULL! | EK44: #NULL! | EL44: #NULL! | EM44: 10 | EN44: 1 | EP44: 5 | EQ44: 3 | ER44: 2 | ES44: 78660 | ET44: 6 | EU44: 4 | EV44: 3 | EW44: 5 | EX44: 2 | EY44: Mary | EZ44: McCauley | FB44: mccauley_kay@yahoo.com | FC44: 5129176047 | FD44: #NULL! | FE44: #NULL! | FF44: 1 | FH44: 10 Sep 2025 - 17:36:09 CDT | FI44: 1641
A45: 292 | B45: 1 | C45: 2 | D45: 1 | E45: #NULL! | F45: 2 | G45: 2 | H45: 4 | I45: Medical program | J45: 1 | K45: 99 | N45: Medical program | P45: #NULL! | Q45: #NULL! | R45: #NULL! | S45: #NULL! | T45: 10 | U45: 10 | V45: 5 | W45: 10 | Y45: #NULL! | Z45: #NULL! | AA45: #NULL! | AB45: #NULL! | AC45: Easy to connect to a human | AD45: 22 | AE45: #NULL! | AF45: #NULL! | AG45: #NULL! | AI45: #NULL! | AJ45: #NULL! | AK45: #NULL! | AL45: #NULL! | AM45: Handled my request immediately | AN45: 21 | AO45: #NULL! | AP45: #NULL! | AQ45: #NULL! | AS45: #NULL! | AT45: #NULL! | AU45: #NULL! | AV45: #NULL! | AX45: #NULL! | AY45: #NULL! | AZ45: #NULL! | BA45: #NULL! | BC45: #NULL! | BD45: #NULL! | BE45: #NULL! | BF45: #NULL! | BG45: What I expected. Not long or shorter | BH45: 21 | BI45: #NULL! | BJ45: #NULL! | BK45: #NULL! | BL45: 2 | BM45: 5 | BN45: I don’t remember | BO45: 98 | BP45: #NULL! | BQ45: #NULL! | BR45: #NULL! | BS45: 6 | BT45: What services can be done on line | BU45: 2 | BV45: #NULL! | BW45: #NULL! | BX45: #NULL! | BZ45: #NULL! | CA45: #NULL! | CB45: #NULL! | CC45: 2 | CD45: #NULL! | CE45: 2 | CF45: #NULL! | CG45: #NULL! | CI45: #NULL! | CJ45: #NULL! | CK45: #NULL! | CL45: #NULL! | CN45: #NULL! | CO45: #NULL! | CP45: #NULL! | CQ45: 2 | CR45: #NULL! | CS45: 10 | CT45: 10 | CU45: 10 | CV45: 10 | CW45: 10 | CX45: 10 | CY45: 11 | DA45: #NULL! | DB45: #NULL! | DC45: 10 | DD45: #NULL! | DE45: #NULL! | DF45: #NULL! | DG45: #NULL! | DH45: #NULL! | DI45: #NULL! | DJ45: #NULL! | DK45: #NULL! | DL45: #NULL! | DN45: 1 | DP45: #NULL! | DQ45: #NULL! | DR45: #NULL! | DT45: #NULL! | DU45: #NULL! | DV45: #NULL! | DW45: 3 | DX45: 2 | DZ45: #NULL! | EA45: #NULL! | EI45: #NULL! | EJ45: #NULL! | EK45: #NULL! | EL45: #NULL! | EM45: 7 | EN45: 1 | EP45: 1 | EQ45: 1 | ER45: 1 | ES45: 78752 | ET45: 2 | EU45: 4 | EV45: 5 | EW45: 5 | EX45: 2 | EY45: Diane | EZ45: Blastic | FB45: Dianeblastic@hotmail.com | FC45: 8087723082 | FD45: #NULL! | FE45: #NULL! | FF45: 3 | FH45: 10 Sep 2025 - 19:03:09 CDT | FI45: 25326
A46: 297 | B46: 1 | C46: 2 | D46: 1 | E46: #NULL! | F46: 2 | G46: 2 | H46: 2 | J46: 2 | K46: 1 | O46: That major storm on the east side that wiped out many trees and broke windows..... We called because our power was still not on after several days. | P46: 13 | Q46: #NULL! | R46: #NULL! | S46: 8 | T46: 7 | U46: 9 | V46: 8 | W46: 7 | Y46: #NULL! | Z46: #NULL! | AA46: #NULL! | AB46: #NULL! | AD46: #NULL! | AE46: #NULL! | AF46: #NULL! | AG46: #NULL! | AI46: #NULL! | AJ46: #NULL! | AK46: #NULL! | AL46: #NULL! | AM46: We got the information we needed | AN46: 26 | AO46: #NULL! | AP46: #NULL! | AQ46: #NULL! | AS46: #NULL! | AT46: #NULL! | AU46: #NULL! | AV46: #NULL! | AW46: I’d rather communicate by phone with a person | AX46: 3 | AY46: #NULL! | AZ46: #NULL! | BA46: #NULL! | BC46: #NULL! | BD46: #NULL! | BE46: #NULL! | BF46: #NULL! | BH46: #NULL! | BI46: #NULL! | BJ46: #NULL! | BK46: #NULL! | BL46: 2 | BM46: 10 | BN46: I don’t remember | BO46: 98 | BP46: #NULL! | BQ46: #NULL! | BR46: #NULL! | BS46: 10 | BT46: Information on other ways of contact or power outages | BU46: 7 | BV46: #NULL! | BW46: #NULL! | BX46: #NULL! | BZ46: #NULL! | CA46: #NULL! | CB46: #NULL! | CC46: 2 | CD46: #NULL! | CE46: 2 | CF46: #NULL! | CG46: #NULL! | CI46: #NULL! | CJ46: #NULL! | CK46: #NULL! | CL46: #NULL! | CN46: #NULL! | CO46: #NULL! | CP46: #NULL! | CQ46: 2 | CR46: #NULL! | CS46: 10 | CT46: 10 | CU46: 10 | CV46: 10 | CW46: 10 | CX46: 10 | CY46: 10 | DA46: #NULL! | DB46: #NULL! | DC46: 9 | DD46: #NULL! | DE46: #NULL! | DF46: #NULL! | DG46: #NULL! | DH46: #NULL! | DI46: #NULL! | DJ46: #NULL! | DK46: #NULL! | DL46: #NULL! | DN46: 1 | DP46: #NULL! | DQ46: #NULL! | DR46: #NULL! | DT46: #NULL! | DU46: #NULL! | DV46: #NULL! | DW46: 2 | DX46: 3 | DZ46: #NULL! | EA46: #NULL! | EI46: #NULL! | EJ46: #NULL! | EK46: #NULL! | EL46: #NULL! | EM46: 4 | EN46: 3 | EP46: 1 | EQ46: 1 | ER46: 2 | ES46: 78723 | ET46: 3 | EU46: 4 | EV46: 6 | EW46: 5 | EX46: 2 | EY46: Cat | EZ46: Drago | FB46: Catdrago@gmail.com | FC46: 214-686-3100 | FD46: #NULL! | FE46: #NULL! | FF46: 3 | FH46: 10 Sep 2025 - 20:01:40 CDT | FI46: 19522
A47: 300 | B47: 1 | C47: 2 | D47: 1 | E47: #NULL! | F47: 2 | G47: 2 | H47: 4 | I47: All of the above | J47: 1 | K47: 6 | P47: #NULL! | Q47: #NULL! | R47: #NULL! | S47: #NULL! | T47: 10 | U47: 10 | V47: 10 | W47: 10 | Y47: #NULL! | Z47: #NULL! | AA47: #NULL! | AB47: #NULL! | AC47: Straightforward | AD47: 20 | AE47: #NULL! | AF47: #NULL! | AG47: #NULL! | AI47: #NULL! | AJ47: #NULL! | AK47: #NULL! | AL47: #NULL! | AM47: Scheduled change of service easily | AN47: 22 | AO47: #NULL! | AP47: #NULL! | AQ47: #NULL! | AS47: #NULL! | AT47: #NULL! | AU47: #NULL! | AV47: #NULL! | AW47: Direct - one step | AX47: 21 | AY47: #NULL! | AZ47: #NULL! | BA47: #NULL! | BC47: #NULL! | BD47: #NULL! | BE47: #NULL! | BF47: #NULL! | BG47: Negligible | BH47: 97 | BI47: #NULL! | BJ47: #NULL! | BK47: #NULL! | BL47: 2 | BM47: 3 | BN47: Don’t recall. | BO47: 98 | BP47: #NULL! | BQ47: #NULL! | BR47: #NULL! | BS47: 5 | BT47: Estimated wait time | BU47: 6 | BV47: #NULL! | BW47: #NULL! | BX47: #NULL! | BZ47: #NULL! | CA47: #NULL! | CB47: #NULL! | CC47: 2 | CD47: #NULL! | CE47: 2 | CF47: #NULL! | CG47: #NULL! | CI47: #NULL! | CJ47: #NULL! | CK47: #NULL! | CL47: #NULL! | CN47: #NULL! | CO47: #NULL! | CP47: #NULL! | CQ47: 2 | CR47: #NULL! | CS47: 10 | CT47: 10 | CU47: 10 | CV47: 10 | CW47: 10 | CX47: 10 | CY47: 10 | DA47: #NULL! | DB47: #NULL! | DC47: 10 | DD47: #NULL! | DE47: #NULL! | DF47: #NULL! | DG47: #NULL! | DH47: #NULL! | DI47: #NULL! | DJ47: #NULL! | DK47: #NULL! | DL47: #NULL! | DN47: 1 | DP47: #NULL! | DQ47: #NULL! | DR47: #NULL! | DT47: #NULL! | DU47: #NULL! | DV47: #NULL! | DW47: 2 | DX47: 1 | DY47: Weekly updates by email | DZ47: 8 | EA47: #NULL! | EI47: #NULL! | EJ47: #NULL! | EK47: #NULL! | EL47: #NULL! | EM47: 10 | EN47: 1 | EP47: 5 | EQ47: 1 | ER47: 1 | ES47: 78759 | ET47: 2 | EU47: 5 | EV47: 6 | EW47: 5 | EX47: 1 | EY47: Mark | EZ47: Estes | FB47: estesmd@gmail.com | FC47: 5127312592 | FD47: #NULL! | FE47: #NULL! | FF47: 3 | FH47: 11 Sep 2025 - 07:00:54 CDT | FI47: 18633
A48: 301 | B48: 1 | C48: 2 | D48: 1 | E48: #NULL! | F48: 2 | G48: 2 | H48: 2 | J48: 1 | K48: 38 | N48: Understand the electric/ solar bill | P48: #NULL! | Q48: #NULL! | R48: #NULL! | S48: #NULL! | T48: 1 | U48: 1 | V48: 1 | W48: 3 | X48: The bill is not explanatory | Y48: 5 | Z48: #NULL! | AA48: #NULL! | AB48: #NULL! | AD48: #NULL! | AE48: #NULL! | AF48: #NULL! | AG48: #NULL! | AH48: Did not take my concerns seriously | AI48: 5 | AJ48: #NULL! | AK48: #NULL! | AL48: #NULL! | AN48: #NULL! | AO48: #NULL! | AP48: #NULL! | AQ48: #NULL! | AR48: See above | AS48: 5 | AT48: #NULL! | AU48: #NULL! | AV48: #NULL! | AX48: #NULL! | AY48: #NULL! | AZ48: #NULL! | BA48: #NULL! | BB48: Fair | BC48: 28 | BD48: #NULL! | BE48: #NULL! | BF48: #NULL! | BH48: #NULL! | BI48: #NULL! | BJ48: #NULL! | BK48: #NULL! | BL48: 4 | BM48: #NULL! | BO48: #NULL! | BP48: #NULL! | BQ48: #NULL! | BR48: #NULL! | BS48: #NULL! | BU48: #NULL! | BV48: #NULL! | BW48: #NULL! | BX48: 1 | BY48: The bill needs more explanation of what each charge or credit is. | BZ48: 4 | CA48: #NULL! | CB48: #NULL! | CC48: 2 | CD48: #NULL! | CE48: 2 | CF48: #NULL! | CG48: #NULL! | CI48: #NULL! | CJ48: #NULL! | CK48: #NULL! | CL48: #NULL! | CN48: #NULL! | CO48: #NULL! | CP48: #NULL! | CQ48: 2 | CR48: #NULL! | CS48: 2 | CT48: 1 | CU48: 2 | CV48: 1 | CW48: 1 | CX48: 2 | CY48: 1 | CZ48: Taken my issue to someone who could make changes to the bill | DA48: 3 | DB48: #NULL! | DC48: 1 | DD48: 0 | DE48: 1 | DF48: 0 | DG48: 0 | DH48: 0 | DI48: 1 | DJ48: 0 | DK48: 0 | DL48: 0 | DN48: 2 | DO48: I have already explained | DP48: 99 | DQ48: #NULL! | DR48: #NULL! | DT48: #NULL! | DU48: #NULL! | DV48: #NULL! | DW48: 1 | DX48: 1 | DY48: Gigg | DZ48: 99 | EA48: #NULL! | EI48: #NULL! | EJ48: #NULL! | EK48: #NULL! | EL48: #NULL! | EM48: 10 | EN48: 3 | EP48: 5 | EQ48: 3 | ER48: 2 | ES48: 78758 | ET48: 2 | EU48: 5 | EV48: 3 | EW48: 5 | EX48: 1 | EY48: James | EZ48: Soper | FB48: jimiekimo@gmail.com | FC48: 5126804952 | FD48: #NULL! | FE48: #NULL! | FF48: 1 | FH48: 11 Sep 2025 - 07:52:26 CDT | FI48: 285
A49: 307 | B49: 1 | C49: 2 | D49: 1 | E49: #NULL! | F49: 2 | G49: 2 | H49: 2 | J49: 1 | K49: 10 | P49: #NULL! | Q49: #NULL! | R49: #NULL! | S49: #NULL! | T49: 10 | U49: 10 | V49: 10 | W49: 9 | Y49: #NULL! | Z49: #NULL! | AA49: #NULL! | AB49: #NULL! | AC49: N/a | AD49: 97 | AE49: #NULL! | AF49: #NULL! | AG49: #NULL! | AI49: #NULL! | AJ49: #NULL! | AK49: #NULL! | AL49: #NULL! | AM49: N/a | AN49: 97 | AO49: #NULL! | AP49: #NULL! | AQ49: #NULL! | AS49: #NULL! | AT49: #NULL! | AU49: #NULL! | AV49: #NULL! | AW49: N/a | AX49: 97 | AY49: #NULL! | AZ49: #NULL! | BA49: #NULL! | BC49: #NULL! | BD49: #NULL! | BE49: #NULL! | BF49: #NULL! | BG49: N/a | BH49: 97 | BI49: #NULL! | BJ49: #NULL! | BK49: #NULL! | BL49: 2 | BM49: 8 | BN49: Don't remember | BO49: 98 | BP49: #NULL! | BQ49: #NULL! | BR49: #NULL! | BS49: 11 | BT49: N/a | BU49: 97 | BV49: #NULL! | BW49: #NULL! | BX49: #NULL! | BZ49: #NULL! | CA49: #NULL! | CB49: #NULL! | CC49: 2 | CD49: #NULL! | CE49: 2 | CF49: #NULL! | CG49: #NULL! | CI49: #NULL! | CJ49: #NULL! | CK49: #NULL! | CL49: #NULL! | CN49: #NULL! | CO49: #NULL! | CP49: #NULL! | CQ49: 2 | CR49: #NULL! | CS49: 10 | CT49: 10 | CU49: 10 | CV49: 10 | CW49: 10 | CX49: 10 | CY49: 10 | DA49: #NULL! | DB49: #NULL! | DC49: 10 | DD49: #NULL! | DE49: #NULL! | DF49: #NULL! | DG49: #NULL! | DH49: #NULL! | DI49: #NULL! | DJ49: #NULL! | DK49: #NULL! | DL49: #NULL! | DN49: 1 | DP49: #NULL! | DQ49: #NULL! | DR49: #NULL! | DT49: #NULL! | DU49: #NULL! | DV49: #NULL! | DW49: 3 | DX49: 1 | DY49: She was awesome. | DZ49: 99 | EA49: #NULL! | EI49: #NULL! | EJ49: #NULL! | EK49: #NULL! | EL49: #NULL! | EM49: 6 | EN49: 2 | EP49: 1 | EQ49: 2 | ER49: 1 | ES49: 78731 | ET49: 2 | EU49: 4 | EV49: 3 | EW49: 5 | EX49: 2 | EY49: Gisele | EZ49: Norris | FB49: gigiharvey79@gmail.com | FC49: 512-375-5826 | FD49: #NULL! | FE49: #NULL! | FF49: 3 | FH49: 11 Sep 2025 - 08:50:32 CDT | FI49: 16158
A50: 312 | B50: 1 | C50: 2 | D50: 1 | E50: #NULL! | F50: 2 | G50: 2 | H50: 3 | J50: 1 | K50: 21 | P50: #NULL! | Q50: #NULL! | R50: #NULL! | S50: #NULL! | T50: 8 | U50: 9 | V50: 8 | W50: 8 | Y50: #NULL! | Z50: #NULL! | AA50: #NULL! | AB50: #NULL! | AC50: Easy | AD50: 20 | AE50: #NULL! | AF50: #NULL! | AG50: #NULL! | AI50: #NULL! | AJ50: #NULL! | AK50: #NULL! | AL50: #NULL! | AM50: Easy | AN50: 27 | AO50: #NULL! | AP50: #NULL! | AQ50: #NULL! | AS50: #NULL! | AT50: #NULL! | AU50: #NULL! | AV50: #NULL! | AW50: Easy | AX50: 27 | AY50: #NULL! | AZ50: #NULL! | BA50: #NULL! | BC50: #NULL! | BD50: #NULL! | BE50: #NULL! | BF50: #NULL! | BG50: Easy | BH50: 28 | BI50: #NULL! | BJ50: #NULL! | BK50: #NULL! | BL50: 2 | BM50: 5 | BN50: None | BO50: 97 | BP50: #NULL! | BQ50: #NULL! | BR50: #NULL! | BS50: 10 | BT50: Nice music | BU50: 20 | BV50: #NULL! | BW50: #NULL! | BX50: #NULL! | BZ50: #NULL! | CA50: #NULL! | CB50: #NULL! | CC50: 2 | CD50: #NULL! | CE50: 2 | CF50: #NULL! | CG50: #NULL! | CI50: #NULL! | CJ50: #NULL! | CK50: #NULL! | CL50: #NULL! | CN50: #NULL! | CO50: #NULL! | CP50: #NULL! | CQ50: 2 | CR50: #NULL! | CS50: 10 | CT50: 8 | CU50: 11 | CV50: 8 | CW50: 8 | CX50: 10 | CY50: 10 | DA50: #NULL! | DB50: #NULL! | DC50: 9 | DD50: #NULL! | DE50: #NULL! | DF50: #NULL! | DG50: #NULL! | DH50: #NULL! | DI50: #NULL! | DJ50: #NULL! | DK50: #NULL! | DL50: #NULL! | DN50: 1 | DP50: #NULL! | DQ50: #NULL! | DR50: #NULL! | DT50: #NULL! | DU50: #NULL! | DV50: #NULL! | DW50: 2 | DX50: 2 | DZ50: #NULL! | EA50: #NULL! | EI50: #NULL! | EJ50: #NULL! | EK50: #NULL! | EL50: #NULL! | EM50: 8 | EN50: 1 | EP50: 1 | EQ50: 5 | ER50: 2 | ES50: 78758 | ET50: 2 | EU50: 5 | EV50: 6 | EW50: 5 | EX50: 1 | EY50: Thomas | EZ50: Costello | FB50: nation529@yahoo.com | FC50: 5126320606 | FD50: #NULL! | FE50: #NULL! | FF50: 1 | FH50: 11 Sep 2025 - 12:42:03 CDT | FI50: 11662
A51: 313 | B51: 1 | C51: 2 | D51: 1 | E51: #NULL! | F51: 2 | G51: 2 | H51: 2 | J51: 1 | K51: 17 | P51: #NULL! | Q51: #NULL! | R51: #NULL! | S51: #NULL! | T51: 11 | U51: 5 | V51: 11 | W51: 11 | Y51: #NULL! | Z51: #NULL! | AA51: #NULL! | AB51: #NULL! | AD51: #NULL! | AE51: #NULL! | AF51: #NULL! | AG51: #NULL! | AI51: #NULL! | AJ51: #NULL! | AK51: #NULL! | AL51: #NULL! | AN51: #NULL! | AO51: #NULL! | AP51: #NULL! | AQ51: #NULL! | AS51: #NULL! | AT51: #NULL! | AU51: #NULL! | AV51: #NULL! | AX51: #NULL! | AY51: #NULL! | AZ51: #NULL! | BA51: #NULL! | BC51: #NULL! | BD51: #NULL! | BE51: #NULL! | BF51: #NULL! | BH51: #NULL! | BI51: #NULL! | BJ51: #NULL! | BK51: #NULL! | BL51: 2 | BM51: 10 | BN51: I do not recall, this was months ago. | BO51: 98 | BP51: #NULL! | BQ51: #NULL! | BR51: #NULL! | BS51: 8 | BT51: Possibility to talk to an agent in a quick manner and not scroll through long menus. | BU51: 6 | BV51: #NULL! | BW51: #NULL! | BX51: #NULL! | BZ51: #NULL! | CA51: #NULL! | CB51: #NULL! | CC51: 2 | CD51: #NULL! | CE51: 3 | CF51: #NULL! | CG51: #NULL! | CI51: #NULL! | CJ51: #NULL! | CK51: #NULL! | CL51: #NULL! | CN51: #NULL! | CO51: #NULL! | CP51: #NULL! | CQ51: 2 | CR51: #NULL! | CS51: 7 | CT51: 1 | CU51: 2 | CV51: 1 | CW51: 8 | CX51: 8 | CY51: 1 | CZ51: The reason I contacted you is because after many years of being a client, I missed one.. Yes... One, payment. And this was because I have an automatic draft from one account to another to fund for my home's expenses (electricity included). One month this wire was not done by the bank (apparently the schedule "expired", so I had to extend it again). Long story short, the agent told me that because of this missed payment, I had to go personally from now on to pay at any of the authorized locations. This not only is a waste of my time, but it is not reasonable. This makes it more likely I might miss a due date if I am not home or traveling as opposed to having it be drafted from my account as it has been done for years. One month. One missed payment. And perfectly explained what happened. It almost seems like you punish your clients and have no regard to history or providing a courteous and polite service. | DA51: 5 | DB51: #NULL! | DC51: 1 | DD51: 1 | DE51: 1 | DF51: 0 | DG51: 0 | DH51: 0 | DI51: 1 | DJ51: 0 | DK51: 0 | DL51: 0 | DN51: 3 | DO51: Take the time to figure out I have been a client for many years and never missed a payment. And use criteria to decide how to treat this case, which seems pretty straight forward. 'No problem sir, we understand this happens. Please make sure automatic payments are reinstated so we don’t have issues in the future. Thanks for being a client". Does not seem like to much to ask. As opposed to: "since you missed a payment, you are now not eligible for automatic online payments and you have to go in person for a full year". Not only does this not make any sense and is quite frankly, rude. | DP51: 3 | DQ51: #NULL! | DR51: #NULL! | DT51: #NULL! | DU51: #NULL! | DV51: #NULL! | DW51: 3 | DX51: 3 | DZ51: #NULL! | EA51: #NULL! | EI51: #NULL! | EJ51: #NULL! | EK51: #NULL! | EL51: #NULL! | EM51: 6 | EN51: 7 | EP51: 7 | EQ51: 1 | ER51: 3 | ES51: 78746 | ET51: 7 | EU51: 6 | EV51: 8 | EW51: 5 | EX51: 4 | EY51: PATRICIO | EZ51: LEBRIJA | FB51: PATLEBRIJA@GMAIL.COM | FC51: 5127500087 | FD51: #NULL! | FE51: #NULL! | FF51: 2 | FH51: 11 Sep 2025 - 09:57:00 CDT | FI51: 2321
A52: 316 | B52: 1 | C52: 2 | D52: 1 | E52: #NULL! | F52: 2 | G52: 2 | H52: 2 | J52: 2 | K52: 15 | M52: Website for payment not letting me pay | O52: Last 2 months I have not been able to pay my bill on line. I tried for a couple of days, system kept telling me password was incorrect. First I call to report this a very nice lady got me to change password by giving me the standard COA password. I was able to pay. The following month same thing. I don't know what is wrong with your system but it needs to be looked into. | P52: 6 | Q52: #NULL! | R52: #NULL! | S52: #NULL! | T52: 5 | U52: 5 | V52: 5 | W52: 5 | Y52: #NULL! | Z52: #NULL! | AA52: #NULL! | AB52: #NULL! | AD52: #NULL! | AE52: #NULL! | AF52: #NULL! | AG52: #NULL! | AI52: #NULL! | AJ52: #NULL! | AK52: #NULL! | AL52: #NULL! | AN52: #NULL! | AO52: #NULL! | AP52: #NULL! | AQ52: #NULL! | AS52: #NULL! | AT52: #NULL! | AU52: #NULL! | AV52: #NULL! | AX52: #NULL! | AY52: #NULL! | AZ52: #NULL! | BA52: #NULL! | BC52: #NULL! | BD52: #NULL! | BE52: #NULL! | BF52: #NULL! | BH52: #NULL! | BI52: #NULL! | BJ52: #NULL! | BK52: #NULL! | BL52: 2 | BM52: 4 | BN52: Don't remember. | BO52: 98 | BP52: #NULL! | BQ52: #NULL! | BR52: #NULL! | BS52: 1 | BT52: Have no idea | BU52: 98 | BV52: #NULL! | BW52: #NULL! | BX52: #NULL! | BZ52: #NULL! | CA52: #NULL! | CB52: #NULL! | CC52: 2 | CD52: #NULL! | CE52: 2 | CF52: #NULL! | CG52: #NULL! | CI52: #NULL! | CJ52: #NULL! | CK52: #NULL! | CL52: #NULL! | CN52: #NULL! | CO52: #NULL! | CP52: #NULL! | CQ52: 2 | CR52: #NULL! | CS52: 10 | CT52: 10 | CU52: 10 | CV52: 11 | CW52: 10 | CX52: 8 | CY52: 10 | DA52: #NULL! | DB52: #NULL! | DC52: 10 | DD52: #NULL! | DE52: #NULL! | DF52: #NULL! | DG52: #NULL! | DH52: #NULL! | DI52: #NULL! | DJ52: #NULL! | DK52: #NULL! | DL52: #NULL! | DN52: 1 | DP52: #NULL! | DQ52: #NULL! | DR52: #NULL! | DT52: #NULL! | DU52: #NULL! | DV52: #NULL! | DW52: 3 | DX52: 2 | DZ52: #NULL! | EA52: #NULL! | EI52: #NULL! | EJ52: #NULL! | EK52: #NULL! | EL52: #NULL! | EM52: 10 | EN52: 3 | EP52: 5 | EQ52: 2 | ER52: 2 | ES52: 78747 | ET52: 4 | EU52: 3 | EV52: 2 | EW52: 5 | EX52: 2 | EY52: Mary | EZ52: Davilla | FB52: mary_davilla@yahoo.com | FC52: 5122289490 | FD52: #NULL! | FE52: #NULL! | FF52: 1 | FH52: 11 Sep 2025 - 10:25:27 CDT | FI52: 2872
A53: 318 | B53: 1 | C53: 2 | D53: 1 | E53: #NULL! | F53: 2 | G53: 2 | H53: 2 | J53: 1 | K53: 3 | P53: #NULL! | Q53: #NULL! | R53: #NULL! | S53: #NULL! | T53: 10 | U53: 10 | V53: 10 | W53: 10 | Y53: #NULL! | Z53: #NULL! | AA53: #NULL! | AB53: #NULL! | AC53: 10 | AD53: #NULL! | AE53: #NULL! | AF53: #NULL! | AG53: #NULL! | AI53: #NULL! | AJ53: #NULL! | AK53: #NULL! | AL53: #NULL! | AM53: 10 | AN53: #NULL! | AO53: #NULL! | AP53: #NULL! | AQ53: #NULL! | AS53: #NULL! | AT53: #NULL! | AU53: #NULL! | AV53: #NULL! | AW53: 10 | AX53: #NULL! | AY53: #NULL! | AZ53: #NULL! | BA53: #NULL! | BC53: #NULL! | BD53: #NULL! | BE53: #NULL! | BF53: #NULL! | BG53: 10 | BH53: #NULL! | BI53: #NULL! | BJ53: #NULL! | BK53: #NULL! | BL53: 1 | BM53: #NULL! | BO53: #NULL! | BP53: #NULL! | BQ53: #NULL! | BR53: #NULL! | BS53: #NULL! | BU53: #NULL! | BV53: #NULL! | BW53: #NULL! | BX53: #NULL! | BZ53: #NULL! | CA53: #NULL! | CB53: #NULL! | CC53: 2 | CD53: #NULL! | CE53: 2 | CF53: #NULL! | CG53: #NULL! | CI53: #NULL! | CJ53: #NULL! | CK53: #NULL! | CL53: #NULL! | CN53: #NULL! | CO53: #NULL! | CP53: #NULL! | CQ53: 2 | CR53: #NULL! | CS53: 10 | CT53: 10 | CU53: 10 | CV53: 10 | CW53: 10 | CX53: 10 | CY53: 10 | DA53: #NULL! | DB53: #NULL! | DC53: 10 | DD53: #NULL! | DE53: #NULL! | DF53: #NULL! | DG53: #NULL! | DH53: #NULL! | DI53: #NULL! | DJ53: #NULL! | DK53: #NULL! | DL53: #NULL! | DN53: 1 | DP53: #NULL! | DQ53: #NULL! | DR53: #NULL! | DT53: #NULL! | DU53: #NULL! | DV53: #NULL! | DW53: 2 | DX53: 2 | DZ53: #NULL! | EA53: #NULL! | EI53: #NULL! | EJ53: #NULL! | EK53: #NULL! | EL53: #NULL! | EM53: 10 | EN53: 1 | EP53: 2 | EQ53: 3 | ER53: 2 | ES53: 78704 | ET53: 1 | EU53: 4 | EV53: 4 | EW53: 5 | EX53: 2 | EY53: Paula | EZ53: Beaird | FB53: Paulitab1@gmail.com | FC53: 5122667995 | FD53: #NULL! | FE53: #NULL! | FF53: 1 | FH53: 11 Sep 2025 - 10:49:32 CDT | FI53: 4192
A54: 335 | B54: 1 | C54: 2 | D54: 1 | E54: #NULL! | F54: 2 | G54: 2 | H54: 2 | J54: 2 | K54: 15 | M54: Plus funds account other account information | O54: Good afternoon. I have had so many problems with city of Austin utilities employees at least seven possibly more in regards to my plus one funds and requests of the notes on my account all of this since May of 2025. I've not ever had problems before. Like this I’m really shocked can someone please ask Mr. Stuart Reily to contact me. Not Cassandra Ragland. Mr. Khan knew about these problems and did nothing to help. He retired days after. Thank you for your time. God bless you. Have a blessed Thursday. | P54: 6 | Q54: #NULL! | R54: #NULL! | S54: #NULL! | T54: 10 | U54: 10 | V54: 10 | W54: 10 | Y54: #NULL! | Z54: #NULL! | AA54: #NULL! | AB54: #NULL! | AC54: Accurate | AD54: 30 | AE54: #NULL! | AF54: #NULL! | AG54: #NULL! | AI54: #NULL! | AJ54: #NULL! | AK54: #NULL! | AL54: #NULL! | AM54: Accurate | AN54: 30 | AO54: #NULL! | AP54: #NULL! | AQ54: #NULL! | AS54: #NULL! | AT54: #NULL! | AU54: #NULL! | AV54: #NULL! | AW54: Accurate | AX54: 30 | AY54: #NULL! | AZ54: #NULL! | BA54: #NULL! | BC54: #NULL! | BD54: #NULL! | BE54: #NULL! | BF54: #NULL! | BG54: Accurate | BH54: 30 | BI54: #NULL! | BJ54: #NULL! | BK54: #NULL! | BL54: 1 | BM54: #NULL! | BO54: #NULL! | BP54: #NULL! | BQ54: #NULL! | BR54: #NULL! | BS54: #NULL! | BU54: #NULL! | BV54: #NULL! | BW54: #NULL! | BX54: #NULL! | BZ54: #NULL! | CA54: #NULL! | CB54: #NULL! | CC54: 2 | CD54: #NULL! | CE54: 1 | CF54: 2 | CG54: #NULL! | CI54: #NULL! | CJ54: #NULL! | CK54: #NULL! | CL54: #NULL! | CN54: #NULL! | CO54: #NULL! | CP54: #NULL! | CQ54: 2 | CR54: #NULL! | CS54: 10 | CT54: 1 | CU54: 10 | CV54: 1 | CW54: 1 | CX54: 10 | CY54: 3 | CZ54: They all need to be more honest! Don’t lie to people! | DA54: 5 | DB54: #NULL! | DC54: 1 | DD54: 0 | DE54: 1 | DF54: 0 | DG54: 0 | DH54: 0 | DI54: 0 | DJ54: 0 | DK54: 0 | DL54: 1 | DM54: I've been waiting since may of 2025 | DN54: 2 | DO54: They need to follow-up with people | DP54: 6 | DQ54: #NULL! | DR54: #NULL! | DT54: #NULL! | DU54: #NULL! | DV54: #NULL! | DW54: 3 | DX54: 2 | DZ54: #NULL! | EA54: #NULL! | EI54: #NULL! | EJ54: #NULL! | EK54: #NULL! | EL54: #NULL! | EM54: 8 | EN54: 6 | EO54: Black American Indian | EP54: 7 | EQ54: 2 | ER54: 3 | ES54: 78766 | ET54: 7 | EU54: 6 | EV54: 8 | EW54: 6 | EX54: 2 | EY54: Lavon | EZ54: Reed | FB54: Lavonreed69@gmail.com | FC54: 737-351-0233 | FD54: #NULL! | FE54: #NULL! | FF54: 2 | FH54: 11 Sep 2025 - 13:16:52 CDT | FI54: 8443
A55: 349 | B55: 1 | C55: 2 | D55: 1 | E55: #NULL! | F55: 2 | G55: 2 | H55: 3 | J55: 1 | K55: 21 | P55: #NULL! | Q55: #NULL! | R55: #NULL! | S55: #NULL! | T55: 10 | U55: 10 | V55: 10 | W55: 10 | Y55: #NULL! | Z55: #NULL! | AA55: #NULL! | AB55: #NULL! | AC55: 10 | AD55: #NULL! | AE55: #NULL! | AF55: #NULL! | AG55: #NULL! | AI55: #NULL! | AJ55: #NULL! | AK55: #NULL! | AL55: #NULL! | AM55: 10 | AN55: #NULL! | AO55: #NULL! | AP55: #NULL! | AQ55: #NULL! | AS55: #NULL! | AT55: #NULL! | AU55: #NULL! | AV55: #NULL! | AW55: 10 | AX55: #NULL! | AY55: #NULL! | AZ55: #NULL! | BA55: #NULL! | BC55: #NULL! | BD55: #NULL! | BE55: #NULL! | BF55: #NULL! | BG55: 10 | BH55: #NULL! | BI55: #NULL! | BJ55: #NULL! | BK55: #NULL! | BL55: 1 | BM55: #NULL! | BO55: #NULL! | BP55: #NULL! | BQ55: #NULL! | BR55: #NULL! | BS55: #NULL! | BU55: #NULL! | BV55: #NULL! | BW55: #NULL! | BX55: #NULL! | BZ55: #NULL! | CA55: #NULL! | CB55: #NULL! | CC55: 2 | CD55: #NULL! | CE55: 2 | CF55: #NULL! | CG55: #NULL! | CI55: #NULL! | CJ55: #NULL! | CK55: #NULL! | CL55: #NULL! | CN55: #NULL! | CO55: #NULL! | CP55: #NULL! | CQ55: 2 | CR55: #NULL! | CS55: 10 | CT55: 10 | CU55: 10 | CV55: 10 | CW55: 10 | CX55: 10 | CY55: 10 | DA55: #NULL! | DB55: #NULL! | DC55: 10 | DD55: #NULL! | DE55: #NULL! | DF55: #NULL! | DG55: #NULL! | DH55: #NULL! | DI55: #NULL! | DJ55: #NULL! | DK55: #NULL! | DL55: #NULL! | DN55: 1 | DP55: #NULL! | DQ55: #NULL! | DR55: #NULL! | DT55: #NULL! | DU55: #NULL! | DV55: #NULL! | DW55: 3 | DX55: 1 | DY55: Y’all give me updates on electricity and water usage | DZ55: 17 | EA55: #NULL! | EI55: #NULL! | EJ55: #NULL! | EK55: #NULL! | EL55: #NULL! | EM55: 10 | EN55: 1 | EP55: 5 | EQ55: 3 | ER55: 2 | ES55: 78727 | ET55: 1 | EU55: 3 | EV55: 2 | EW55: 5 | EX55: 1 | EY55: Riley | EZ55: Boudreaux | FB55: rboudreaux52@att.net | FC55: 5122893436 | FD55: #NULL! | FE55: #NULL! | FF55: 2 | FH55: 11 Sep 2025 - 14:50:50 CDT | FI55: 11100
A56: 355 | B56: 1 | C56: 2 | D56: 1 | E56: #NULL! | F56: 2 | G56: 2 | H56: 2 | J56: 1 | K56: 10 | P56: #NULL! | Q56: #NULL! | R56: #NULL! | S56: #NULL! | T56: 10 | U56: 10 | V56: 10 | W56: 10 | Y56: #NULL! | Z56: #NULL! | AA56: #NULL! | AB56: #NULL! | AC56: The system was understandable | AD56: 20 | AE56: #NULL! | AF56: #NULL! | AG56: #NULL! | AI56: #NULL! | AJ56: #NULL! | AK56: #NULL! | AL56: #NULL! | AM56: They help you with receiving help on your utility bills | AN56: 25 | AO56: #NULL! | AP56: #NULL! | AQ56: #NULL! | AS56: #NULL! | AT56: #NULL! | AU56: #NULL! | AV56: #NULL! | AW56: Spoke in plain English and revised it so I could understand | AX56: 27 | AY56: #NULL! | AZ56: #NULL! | BA56: #NULL! | BC56: #NULL! | BD56: #NULL! | BE56: #NULL! | BF56: #NULL! | BG56: Wait time was great | BH56: 21 | BI56: #NULL! | BJ56: #NULL! | BK56: #NULL! | BL56: 2 | BM56: 3 | BN56: Someone will be with you shortly | BO56: 6 | BP56: #NULL! | BQ56: #NULL! | BR56: #NULL! | BS56: 10 | BT56: None | BU56: 97 | BV56: #NULL! | BW56: #NULL! | BX56: #NULL! | BZ56: #NULL! | CA56: #NULL! | CB56: #NULL! | CC56: 2 | CD56: #NULL! | CE56: 2 | CF56: #NULL! | CG56: #NULL! | CI56: #NULL! | CJ56: #NULL! | CK56: #NULL! | CL56: #NULL! | CN56: #NULL! | CO56: #NULL! | CP56: #NULL! | CQ56: 2 | CR56: #NULL! | CS56: 10 | CT56: 10 | CU56: 10 | CV56: 10 | CW56: 10 | CX56: 10 | CY56: 10 | DA56: #NULL! | DB56: #NULL! | DC56: 10 | DD56: #NULL! | DE56: #NULL! | DF56: #NULL! | DG56: #NULL! | DH56: #NULL! | DI56: #NULL! | DJ56: #NULL! | DK56: #NULL! | DL56: #NULL! | DN56: 1 | DP56: #NULL! | DQ56: #NULL! | DR56: #NULL! | DT56: #NULL! | DU56: #NULL! | DV56: #NULL! | DW56: 3 | DX56: 2 | DZ56: #NULL! | EA56: #NULL! | EI56: #NULL! | EJ56: #NULL! | EK56: #NULL! | EL56: #NULL! | EM56: 8 | EN56: 2 | EP56: 5 | EQ56: 1 | ER56: 1 | ES56: 78752 | ET56: 2 | EU56: 3 | EV56: 1 | EW56: 5 | EX56: 2 | EY56: Mary | EZ56: Williams | FB56: mwswann313@yahoo.com | FC56: 5124296273 | FD56: #NULL! | FE56: #NULL! | FF56: 2 | FH56: 11 Sep 2025 - 16:30:36 CDT | FI56: 11048
A57: 358 | B57: 1 | C57: 2 | D57: 1 | E57: #NULL! | F57: 2 | G57: 2 | H57: 4 | I57: Billing | J57: 2 | K57: 3 | O57: After many calls to multiple service agents, I still cannot get COA to send me an invoice or billing statement. They do have my bank info, and they do draft the account monthly for an amount. No problems with the account being paid up and current. I just don't know what you're charging me, and when. I cannot get a statement sent to me my mail or email. The other account at this address does in fact get invoiced, billed, drafted and paid without problem. Why not both of them? And why do I have two accounts anyway? One for trash/water and services, and a separate one for power? | P57: 1 | Q57: #NULL! | R57: #NULL! | S57: #NULL! | T57: 11 | U57: 11 | V57: 11 | W57: 3 | Y57: #NULL! | Z57: #NULL! | AA57: #NULL! | AB57: #NULL! | AD57: #NULL! | AE57: #NULL! | AF57: #NULL! | AG57: #NULL! | AI57: #NULL! | AJ57: #NULL! | AK57: #NULL! | AL57: #NULL! | AN57: #NULL! | AO57: #NULL! | AP57: #NULL! | AQ57: #NULL! | AS57: #NULL! | AT57: #NULL! | AU57: #NULL! | AV57: #NULL! | AX57: #NULL! | AY57: #NULL! | AZ57: #NULL! | BA57: #NULL! | BB57: Wait time longer than 2 mins | BC57: 2 | BD57: #NULL! | BE57: #NULL! | BF57: #NULL! | BH57: #NULL! | BI57: #NULL! | BJ57: #NULL! | BK57: #NULL! | BL57: 2 | BM57: 8 | BN57: . | BO57: 99 | BP57: #NULL! | BQ57: #NULL! | BR57: #NULL! | BS57: 10 | BT57: . | BU57: 99 | BV57: #NULL! | BW57: #NULL! | BX57: #NULL! | BZ57: #NULL! | CA57: #NULL! | CB57: #NULL! | CC57: 1 | CD57: 7 | CE57: 2 | CF57: #NULL! | CG57: #NULL! | CI57: #NULL! | CJ57: #NULL! | CK57: #NULL! | CL57: #NULL! | CN57: #NULL! | CO57: #NULL! | CP57: #NULL! | CQ57: 2 | CR57: #NULL! | CS57: 7 | CT57: 4 | CU57: 6 | CV57: 1 | CW57: 11 | CX57: 6 | CY57: 11 | CZ57: She simply aid that she would take care of it, and that I should wait 6-8 weeks. To see if anything happened, I guess. In other words, there was no sense of ownership on her part to see the problem completely resolved. The attitude of Coa utilities seems to be that it's the customer's problem. | DA57: 2 | DB57: #NULL! | DC57: 1 | DD57: 0 | DE57: 1 | DF57: 0 | DG57: 0 | DH57: 0 | DI57: 1 | DJ57: 0 | DK57: 0 | DL57: 0 | DN57: 2 | DO57: Already told you | DP57: 99 | DQ57: #NULL! | DR57: #NULL! | DT57: #NULL! | DU57: #NULL! | DV57: #NULL! | DW57: 1 | DX57: 2 | DZ57: #NULL! | EA57: #NULL! | EI57: #NULL! | EJ57: #NULL! | EK57: #NULL! | EL57: #NULL! | EM57: 11 | EN57: 7 | EP57: 7 | EQ57: 5 | ER57: 3 | ES57: 78750 | ET57: 2 | EU57: 6 | EV57: 8 | EW57: 5 | EX57: 4 | EY57: Paul | EZ57: Griffiths | FB57: ccr@joseph-bolton.com | FC57: 5129179521 | FD57: #NULL! | FE57: #NULL! | FF57: 3 | FH57: 11 Sep 2025 - 17:17:17 CDT | FI57: 17442
A58: 359 | B58: 1 | C58: 2 | D58: 1 | E58: #NULL! | F58: 2 | G58: 2 | H58: 4 | I58: Discount program | J58: 1 | K58: 14 | P58: #NULL! | Q58: #NULL! | R58: #NULL! | S58: #NULL! | T58: 8 | U58: 7 | V58: 8 | W58: 6 | Y58: #NULL! | Z58: #NULL! | AA58: #NULL! | AB58: #NULL! | AC58: Questions answered well | AD58: 23 | AE58: #NULL! | AF58: #NULL! | AG58: #NULL! | AI58: #NULL! | AJ58: #NULL! | AK58: #NULL! | AL58: #NULL! | AN58: #NULL! | AO58: #NULL! | AP58: #NULL! | AQ58: #NULL! | AS58: #NULL! | AT58: #NULL! | AU58: #NULL! | AV58: #NULL! | AW58: Didn't have to press 1 for English | AX58: 21 | AY58: #NULL! | AZ58: #NULL! | BA58: #NULL! | BC58: #NULL! | BD58: #NULL! | BE58: #NULL! | BF58: #NULL! | BH58: #NULL! | BI58: #NULL! | BJ58: #NULL! | BK58: #NULL! | BL58: 2 | BM58: 2 | BN58: Can't remember | BO58: 98 | BP58: #NULL! | BQ58: #NULL! | BR58: #NULL! | BS58: 1 | BT58: No idea | BU58: 98 | BV58: #NULL! | BW58: #NULL! | BX58: #NULL! | BZ58: #NULL! | CA58: #NULL! | CB58: #NULL! | CC58: 1 | CD58: 6 | CE58: 2 | CF58: #NULL! | CG58: #NULL! | CI58: #NULL! | CJ58: #NULL! | CK58: #NULL! | CL58: #NULL! | CN58: #NULL! | CO58: #NULL! | CP58: #NULL! | CQ58: 2 | CR58: #NULL! | CS58: 7 | CT58: 7 | CU58: 7 | CV58: 7 | CW58: 7 | CX58: 7 | CY58: 7 | CZ58: Everything was fine | DA58: 97 | DB58: #NULL! | DC58: 7 | DD58: 0 | DE58: 0 | DF58: 0 | DG58: 0 | DH58: 0 | DI58: 0 | DJ58: 0 | DK58: 0 | DL58: 1 | DM58: was completely satisfied. | DN58: 1 | DP58: #NULL! | DQ58: #NULL! | DR58: #NULL! | DT58: #NULL! | DU58: #NULL! | DV58: #NULL! | DW58: 3 | DX58: 2 | DZ58: #NULL! | EA58: #NULL! | EI58: #NULL! | EJ58: #NULL! | EK58: #NULL! | EL58: #NULL! | EM58: 10 | EN58: 1 | EP58: 5 | EQ58: 1 | ER58: 2 | ES58: 78758 | ET58: 2 | EU58: 4 | EV58: 4 | EW58: 5 | EX58: 1 | EY58: Jack | EZ58: Wells | FB58: indianjack@juno.com | FC58: 5122913295 | FD58: #NULL! | FE58: #NULL! | FF58: 3 | FH58: 11 Sep 2025 - 17:44:35 CDT | FI58: 22941
A59: 360 | B59: 1 | C59: 2 | D59: 1 | E59: #NULL! | F59: 2 | G59: 2 | H59: 2 | J59: 1 | K59: 3 | P59: #NULL! | Q59: #NULL! | R59: #NULL! | S59: #NULL! | T59: 10 | U59: 10 | V59: 10 | W59: 10 | Y59: #NULL! | Z59: #NULL! | AA59: #NULL! | AB59: #NULL! | AC59: 10 | AD59: #NULL! | AE59: #NULL! | AF59: #NULL! | AG59: #NULL! | AI59: #NULL! | AJ59: #NULL! | AK59: #NULL! | AL59: #NULL! | AM59: 10 | AN59: #NULL! | AO59: #NULL! | AP59: #NULL! | AQ59: #NULL! | AS59: #NULL! | AT59: #NULL! | AU59: #NULL! | AV59: #NULL! | AW59: 10 | AX59: #NULL! | AY59: #NULL! | AZ59: #NULL! | BA59: #NULL! | BC59: #NULL! | BD59: #NULL! | BE59: #NULL! | BF59: #NULL! | BG59: 10 | BH59: #NULL! | BI59: #NULL! | BJ59: #NULL! | BK59: #NULL! | BL59: 1 | BM59: #NULL! | BO59: #NULL! | BP59: #NULL! | BQ59: #NULL! | BR59: #NULL! | BS59: #NULL! | BU59: #NULL! | BV59: #NULL! | BW59: #NULL! | BX59: #NULL! | BZ59: #NULL! | CA59: #NULL! | CB59: #NULL! | CC59: 2 | CD59: #NULL! | CE59: 2 | CF59: #NULL! | CG59: #NULL! | CI59: #NULL! | CJ59: #NULL! | CK59: #NULL! | CL59: #NULL! | CN59: #NULL! | CO59: #NULL! | CP59: #NULL! | CQ59: 2 | CR59: #NULL! | CS59: 10 | CT59: 10 | CU59: 10 | CV59: 10 | CW59: 10 | CX59: 10 | CY59: 10 | DA59: #NULL! | DB59: #NULL! | DC59: 10 | DD59: #NULL! | DE59: #NULL! | DF59: #NULL! | DG59: #NULL! | DH59: #NULL! | DI59: #NULL! | DJ59: #NULL! | DK59: #NULL! | DL59: #NULL! | DN59: 1 | DP59: #NULL! | DQ59: #NULL! | DR59: #NULL! | DT59: #NULL! | DU59: #NULL! | DV59: #NULL! | DW59: 2 | DX59: 1 | DY59: Usage email, payment email | DZ59: 17 | EA59: #NULL! | EI59: #NULL! | EJ59: #NULL! | EK59: #NULL! | EL59: #NULL! | EM59: 7 | EN59: 1 | EP59: 1 | EQ59: 2 | ER59: 2 | ES59: 78734 | ET59: 4 | EU59: 3 | EV59: 6 | EW59: 5 | EX59: 2 | EY59: Melanie | EZ59: Welch | FB59: melaniekwelch@gmail.com | FC59: 5122697176 | FD59: #NULL! | FE59: #NULL! | FF59: 2 | FH59: 11 Sep 2025 - 17:44:03 CDT | FI59: 3535
A60: 361 | B60: 1 | C60: 2 | D60: 1 | E60: #NULL! | F60: 2 | G60: 2 | H60: 2 | J60: 1 | K60: 11 | P60: #NULL! | Q60: #NULL! | R60: #NULL! | S60: #NULL! | T60: 5 | U60: 4 | V60: 4 | W60: 5 | Y60: #NULL! | Z60: #NULL! | AA60: #NULL! | AB60: #NULL! | AD60: #NULL! | AE60: #NULL! | AF60: #NULL! | AG60: #NULL! | AI60: #NULL! | AJ60: #NULL! | AK60: #NULL! | AL60: #NULL! | AN60: #NULL! | AO60: #NULL! | AP60: #NULL! | AQ60: #NULL! | AS60: #NULL! | AT60: #NULL! | AU60: #NULL! | AV60: #NULL! | AX60: #NULL! | AY60: #NULL! | AZ60: #NULL! | BA60: #NULL! | BC60: #NULL! | BD60: #NULL! | BE60: #NULL! | BF60: #NULL! | BH60: #NULL! | BI60: #NULL! | BJ60: #NULL! | BK60: #NULL! | BL60: 2 | BM60: 7 | BN60: Do not recall | BO60: 98 | BP60: #NULL! | BQ60: #NULL! | BR60: #NULL! | BS60: 4 | BT60: I try not to listen when I’m on hold, because most hold messages are telling me how important I am to a company unwilling to staff a call center--their primary means of *interaction* with me--properly. | BU60: 99 | BV60: #NULL! | BW60: #NULL! | BX60: #NULL! | BZ60: #NULL! | CA60: #NULL! | CB60: #NULL! | CC60: 2 | CD60: #NULL! | CE60: 2 | CF60: #NULL! | CG60: #NULL! | CI60: #NULL! | CJ60: #NULL! | CK60: #NULL! | CL60: #NULL! | CN60: #NULL! | CO60: #NULL! | CP60: #NULL! | CQ60: 2 | CR60: #NULL! | CS60: 10 | CT60: 7 | CU60: 10 | CV60: 10 | CW60: 10 | CX60: 10 | CY60: 11 | DA60: #NULL! | DB60: #NULL! | DC60: 7 | DD60: 0 | DE60: 0 | DF60: 0 | DG60: 0 | DH60: 0 | DI60: 0 | DJ60: 0 | DK60: 0 | DL60: 1 | DM60: 7 is not so bad | DN60: 1 | DP60: #NULL! | DQ60: #NULL! | DR60: #NULL! | DT60: #NULL! | DU60: #NULL! | DV60: #NULL! | DW60: 2 | DX60: 2 | DZ60: #NULL! | EA60: #NULL! | EI60: #NULL! | EJ60: #NULL! | EK60: #NULL! | EL60: #NULL! | EM60: 9 | EN60: 1 | EP60: 5 | EQ60: 1 | ER60: 2 | ES60: 78736 | ET60: 3 | EU60: 2 | EV60: 5 | EW60: 5 | EX60: 1 | EY60: Steven | EZ60: High | FB60: ranya@swbell.net | FC60: 512-968-4244 | FD60: #NULL! | FE60: #NULL! | FF60: 1 | FH60: 11 Sep 2025 - 17:57:26 CDT | FI60: 2969
A61: 367 | B61: 1 | C61: 2 | D61: 1 | E61: #NULL! | F61: 2 | G61: 2 | H61: 2 | J61: 2 | K61: 3 | O61: My bill was on auto-pay. During the Christmas holiday I didn’t have enough money in account to cover the payment. I needed to move money into the account. I didn’t receive any notification that I had not paid the bill and it happened again the next month. Austin energy solution was to punish the consumer. First by making them go to a location and pay cash, in addition they took me off bill averaging program. This makes it more expensive for consumers and is unnecessary except to be punitive. | P61: 1 | Q61: #NULL! | R61: #NULL! | S61: #NULL! | T61: 11 | U61: 11 | V61: 11 | W61: 11 | Y61: #NULL! | Z61: #NULL! | AA61: #NULL! | AB61: #NULL! | AD61: #NULL! | AE61: #NULL! | AF61: #NULL! | AG61: #NULL! | AI61: #NULL! | AJ61: #NULL! | AK61: #NULL! | AL61: #NULL! | AN61: #NULL! | AO61: #NULL! | AP61: #NULL! | AQ61: #NULL! | AS61: #NULL! | AT61: #NULL! | AU61: #NULL! | AV61: #NULL! | AX61: #NULL! | AY61: #NULL! | AZ61: #NULL! | BA61: #NULL! | BC61: #NULL! | BD61: #NULL! | BE61: #NULL! | BF61: #NULL! | BH61: #NULL! | BI61: #NULL! | BJ61: #NULL! | BK61: #NULL! | BL61: 2 | BM61: 5 | BN61: Nothing to comment on | BO61: 97 | BP61: #NULL! | BQ61: #NULL! | BR61: #NULL! | BS61: 10 | BT61: Number in queen and how long the wait will be. | BU61: 6 | BV61: #NULL! | BW61: #NULL! | BX61: #NULL! | BZ61: #NULL! | CA61: #NULL! | CB61: #NULL! | CC61: 2 | CD61: #NULL! | CE61: 2 | CF61: #NULL! | CG61: #NULL! | CI61: #NULL! | CJ61: #NULL! | CK61: #NULL! | CL61: #NULL! | CN61: #NULL! | CO61: #NULL! | CP61: #NULL! | CQ61: 2 | CR61: #NULL! | CS61: 5 | CT61: 8 | CU61: 2 | CV61: 1 | CW61: 8 | CX61: 8 | CY61: 7 | CZ61: Nothing but had no authority to address my request. | DA61: 2 | DB61: #NULL! | DC61: 3 | DD61: 0 | DE61: 0 | DF61: 0 | DG61: 0 | DH61: 0 | DI61: 1 | DJ61: 0 | DK61: 0 | DL61: 0 | DN61: 2 | DO61: Allow averaging to continue after bill was brought current | DP61: 99 | DQ61: #NULL! | DR61: #NULL! | DT61: #NULL! | DU61: #NULL! | DV61: #NULL! | DW61: 1 | DX61: 2 | DZ61: #NULL! | EA61: #NULL! | EI61: #NULL! | EJ61: #NULL! | EK61: #NULL! | EL61: #NULL! | EM61: 10 | EN61: 1 | EP61: 1 | EQ61: 3 | ER61: 2 | ES61: 78727 | ET61: 2 | EU61: 5 | EV61: 6 | EW61: 3 | EX61: 1 | EY61: Chuck | EZ61: Rice | FB61: crice@chuckricegroup.com | FC61: 5128040100 | FD61: #NULL! | FE61: #NULL! | FF61: 3 | FH61: 11 Sep 2025 - 20:02:11 CDT | FI61: 26758
A62: 374 | B62: 1 | C62: 2 | D62: 1 | E62: #NULL! | F62: 2 | G62: 2 | H62: 4 | I62: All 3 | J62: 1 | K62: 4 | P62: #NULL! | Q62: #NULL! | R62: #NULL! | S62: #NULL! | T62: 10 | U62: 10 | V62: 5 | W62: 10 | Y62: #NULL! | Z62: #NULL! | AA62: #NULL! | AB62: #NULL! | AC62: It was | AD62: 20 | AE62: #NULL! | AF62: #NULL! | AG62: #NULL! | AI62: #NULL! | AJ62: #NULL! | AK62: #NULL! | AL62: #NULL! | AM62: It did | AN62: 28 | AO62: #NULL! | AP62: #NULL! | AQ62: #NULL! | AS62: #NULL! | AT62: #NULL! | AU62: #NULL! | AV62: #NULL! | AX62: #NULL! | AY62: #NULL! | AZ62: #NULL! | BA62: #NULL! | BC62: #NULL! | BD62: #NULL! | BE62: #NULL! | BF62: #NULL! | BG62: Not too long | BH62: 21 | BI62: #NULL! | BJ62: #NULL! | BK62: #NULL! | BL62: 5 | BM62: 10 | BN62: No memory, so it wasn’t too bad | BO62: 98 | BP62: #NULL! | BQ62: #NULL! | BR62: #NULL! | BS62: 10 | BT62: Where I am in the queue and how long it would take an opportunity to be called back instead of holding | BU62: 6 | BV62: #NULL! | BW62: #NULL! | BX62: #NULL! | BZ62: #NULL! | CA62: #NULL! | CB62: #NULL! | CC62: 3 | CD62: #NULL! | CE62: 2 | CF62: #NULL! | CG62: #NULL! | CI62: #NULL! | CJ62: #NULL! | CK62: #NULL! | CL62: #NULL! | CN62: #NULL! | CO62: #NULL! | CP62: #NULL! | CQ62: 2 | CR62: #NULL! | CS62: 10 | CT62: 10 | CU62: 10 | CV62: 10 | CW62: 10 | CX62: 10 | CY62: 10 | DA62: #NULL! | DB62: #NULL! | DC62: 10 | DD62: #NULL! | DE62: #NULL! | DF62: #NULL! | DG62: #NULL! | DH62: #NULL! | DI62: #NULL! | DJ62: #NULL! | DK62: #NULL! | DL62: #NULL! | DN62: 1 | DP62: #NULL! | DQ62: #NULL! | DR62: #NULL! | DT62: #NULL! | DU62: #NULL! | DV62: #NULL! | DW62: 3 | DX62: 3 | DZ62: #NULL! | EA62: #NULL! | EI62: #NULL! | EJ62: #NULL! | EK62: #NULL! | EL62: #NULL! | EM62: 8 | EN62: 1 | EP62: 1 | EQ62: 1 | ER62: 2 | ES62: 78759 | ET62: 2 | EU62: 5 | EV62: 6 | EW62: 4 | EX62: 2 | EY62: Elizabeth | EZ62: McLean | FB62: rebmclean@gmail.com | FC62: 2149959942 | FD62: #NULL! | FE62: #NULL! | FF62: 1 | FH62: 11 Sep 2025 - 21:51:59 CDT | FI62: 486
A63: 377 | B63: 1 | C63: 2 | D63: 1 | E63: #NULL! | F63: 2 | G63: 2 | H63: 2 | J63: 1 | K63: 13 | P63: #NULL! | Q63: #NULL! | R63: #NULL! | S63: #NULL! | T63: 10 | U63: 10 | V63: 10 | W63: 10 | Y63: #NULL! | Z63: #NULL! | AA63: #NULL! | AB63: #NULL! | AC63: Easy | AD63: 20 | AE63: #NULL! | AF63: #NULL! | AG63: #NULL! | AI63: #NULL! | AJ63: #NULL! | AK63: #NULL! | AL63: #NULL! | AM63: It was pretty clear | AN63: 28 | AO63: #NULL! | AP63: #NULL! | AQ63: #NULL! | AS63: #NULL! | AT63: #NULL! | AU63: #NULL! | AV63: #NULL! | AW63: I prefer a human, but call trees are a necessary evil | AX63: 3 | AY63: #NULL! | AZ63: #NULL! | BA63: #NULL! | BC63: #NULL! | BD63: #NULL! | BE63: #NULL! | BF63: #NULL! | BG63: Short wait | BH63: 21 | BI63: #NULL! | BJ63: #NULL! | BK63: #NULL! | BL63: 1 | BM63: #NULL! | BO63: #NULL! | BP63: #NULL! | BQ63: #NULL! | BR63: #NULL! | BS63: #NULL! | BU63: #NULL! | BV63: #NULL! | BW63: #NULL! | BX63: #NULL! | BZ63: #NULL! | CA63: #NULL! | CB63: #NULL! | CC63: 3 | CD63: #NULL! | CE63: 2 | CF63: #NULL! | CG63: #NULL! | CI63: #NULL! | CJ63: #NULL! | CK63: #NULL! | CL63: #NULL! | CN63: #NULL! | CO63: #NULL! | CP63: #NULL! | CQ63: 2 | CR63: #NULL! | CS63: 10 | CT63: 10 | CU63: 10 | CV63: 10 | CW63: 10 | CX63: 10 | CY63: 10 | DA63: #NULL! | DB63: #NULL! | DC63: 10 | DD63: #NULL! | DE63: #NULL! | DF63: #NULL! | DG63: #NULL! | DH63: #NULL! | DI63: #NULL! | DJ63: #NULL! | DK63: #NULL! | DL63: #NULL! | DN63: 1 | DP63: #NULL! | DQ63: #NULL! | DR63: #NULL! | DT63: #NULL! | DU63: #NULL! | DV63: #NULL! | DW63: 4 | DX63: 3 | DZ63: #NULL! | EA63: #NULL! | EI63: #NULL! | EJ63: #NULL! | EK63: #NULL! | EL63: #NULL! | EM63: 8 | EN63: 1 | EP63: 1 | EQ63: 3 | ER63: 1 | ES63: 78748 | ET63: 1 | EU63: 4 | EV63: 6 | EW63: 5 | EX63: 1 | EY63: Patrick | EZ63: Norsch | FB63: Pnorsch@gmail.com | FC63: 512820 8740 | FD63: #NULL! | FE63: #NULL! | FF63: 2 | FH63: 11 Sep 2025 - 22:32:51 CDT | FI63: 12347
A64: 378 | B64: 1 | C64: 2 | D64: 1 | E64: #NULL! | F64: 2 | G64: 2 | H64: 2 | J64: 1 | K64: 3 | P64: #NULL! | Q64: #NULL! | R64: #NULL! | S64: #NULL! | T64: 10 | U64: 11 | V64: 7 | W64: 11 | Y64: #NULL! | Z64: #NULL! | AA64: #NULL! | AB64: #NULL! | AC64: Seemed easy enough | AD64: 20 | AE64: #NULL! | AF64: #NULL! | AG64: #NULL! | AI64: #NULL! | AJ64: #NULL! | AK64: #NULL! | AL64: #NULL! | AN64: #NULL! | AO64: #NULL! | AP64: #NULL! | AQ64: #NULL! | AS64: #NULL! | AT64: #NULL! | AU64: #NULL! | AV64: #NULL! | AX64: #NULL! | AY64: #NULL! | AZ64: #NULL! | BA64: #NULL! | BC64: #NULL! | BD64: #NULL! | BE64: #NULL! | BF64: #NULL! | BH64: #NULL! | BI64: #NULL! | BJ64: #NULL! | BK64: #NULL! | BL64: 5 | BM64: 1 | BO64: #NULL! | BP64: #NULL! | BQ64: #NULL! | BR64: #NULL! | BS64: #NULL! | BU64: #NULL! | BV64: #NULL! | BW64: #NULL! | BX64: #NULL! | BZ64: #NULL! | CA64: #NULL! | CB64: #NULL! | CC64: 2 | CD64: #NULL! | CE64: 2 | CF64: #NULL! | CG64: #NULL! | CI64: #NULL! | CJ64: #NULL! | CK64: #NULL! | CL64: #NULL! | CN64: #NULL! | CO64: #NULL! | CP64: #NULL! | CQ64: 2 | CR64: #NULL! | CS64: 10 | CT64: 10 | CU64: 10 | CV64: 10 | CW64: 10 | CX64: 10 | CY64: 10 | DA64: #NULL! | DB64: #NULL! | DC64: 10 | DD64: #NULL! | DE64: #NULL! | DF64: #NULL! | DG64: #NULL! | DH64: #NULL! | DI64: #NULL! | DJ64: #NULL! | DK64: #NULL! | DL64: #NULL! | DN64: 1 | DP64: #NULL! | DQ64: #NULL! | DR64: #NULL! | DT64: #NULL! | DU64: #NULL! | DV64: #NULL! | DW64: 3 | DX64: 3 | DZ64: #NULL! | EA64: #NULL! | EI64: #NULL! | EJ64: #NULL! | EK64: #NULL! | EL64: #NULL! | EM64: 10 | EN64: 1 | EP64: 5 | EQ64: 3 | ER64: 2 | ES64: 78753 | ET64: 4 | EU64: 3 | EV64: 8 | EW64: 5 | EX64: 2 | EY64: C | EZ64: Crocker | FB64: cpricecrocker@gmail.com | FC64: 5128368759 | FD64: #NULL! | FE64: #NULL! | FF64: 3 | FH64: 11 Sep 2025 - 23:39:55 CDT | FI64: 19693
A65: 398 | B65: 1 | C65: 2 | D65: 1 | E65: #NULL! | F65: 2 | G65: 2 | H65: 2 | J65: 1 | K65: 38 | N65: Autopay inquiry | P65: #NULL! | Q65: #NULL! | R65: #NULL! | S65: #NULL! | T65: 10 | U65: 10 | V65: 10 | W65: 10 | Y65: #NULL! | Z65: #NULL! | AA65: #NULL! | AB65: #NULL! | AC65: 10 | AD65: #NULL! | AE65: #NULL! | AF65: #NULL! | AG65: #NULL! | AI65: #NULL! | AJ65: #NULL! | AK65: #NULL! | AL65: #NULL! | AM65: 10 | AN65: #NULL! | AO65: #NULL! | AP65: #NULL! | AQ65: #NULL! | AS65: #NULL! | AT65: #NULL! | AU65: #NULL! | AV65: #NULL! | AW65: 10 | AX65: #NULL! | AY65: #NULL! | AZ65: #NULL! | BA65: #NULL! | BC65: #NULL! | BD65: #NULL! | BE65: #NULL! | BF65: #NULL! | BG65: 10 | BH65: #NULL! | BI65: #NULL! | BJ65: #NULL! | BK65: #NULL! | BL65: 1 | BM65: #NULL! | BO65: #NULL! | BP65: #NULL! | BQ65: #NULL! | BR65: #NULL! | BS65: #NULL! | BU65: #NULL! | BV65: #NULL! | BW65: #NULL! | BX65: #NULL! | BZ65: #NULL! | CA65: #NULL! | CB65: #NULL! | CC65: 2 | CD65: #NULL! | CE65: 2 | CF65: #NULL! | CG65: #NULL! | CI65: #NULL! | CJ65: #NULL! | CK65: #NULL! | CL65: #NULL! | CN65: #NULL! | CO65: #NULL! | CP65: #NULL! | CQ65: 2 | CR65: #NULL! | CS65: 10 | CT65: 10 | CU65: 10 | CV65: 10 | CW65: 10 | CX65: 10 | CY65: 10 | DA65: #NULL! | DB65: #NULL! | DC65: 10 | DD65: #NULL! | DE65: #NULL! | DF65: #NULL! | DG65: #NULL! | DH65: #NULL! | DI65: #NULL! | DJ65: #NULL! | DK65: #NULL! | DL65: #NULL! | DN65: 1 | DP65: #NULL! | DQ65: #NULL! | DR65: #NULL! | DT65: #NULL! | DU65: #NULL! | DV65: #NULL! | DW65: 3 | DX65: 2 | DZ65: #NULL! | EA65: #NULL! | EI65: #NULL! | EJ65: #NULL! | EK65: #NULL! | EL65: #NULL! | EM65: 10 | EN65: 1 | EP65: 5 | EQ65: 2 | ER65: 1 | ES65: 78753 | ET65: 1 | EU65: 5 | EV65: 2 | EW65: 4 | EX65: 2 | EY65: K | EZ65: Mac | FB65: kmacl444@yahoo.com | FC65: 5124369425 | FD65: #NULL! | FE65: #NULL! | FF65: 3 | FH65: 12 Sep 2025 - 10:24:06 CDT | FI65: 22897
A66: 405 | B66: 1 | C66: 2 | D66: 1 | E66: #NULL! | F66: 2 | G66: 2 | H66: 5 | J66: 1 | K66: 19 | P66: #NULL! | Q66: #NULL! | R66: #NULL! | S66: #NULL! | T66: 6 | U66: 3 | V66: 1 | W66: 5 | Y66: #NULL! | Z66: #NULL! | AA66: #NULL! | AB66: #NULL! | AD66: #NULL! | AE66: #NULL! | AF66: #NULL! | AG66: #NULL! | AH66: The man was very mean when I need help | AI66: 5 | AJ66: #NULL! | AK66: #NULL! | AL66: #NULL! | AN66: #NULL! | AO66: #NULL! | AP66: #NULL! | AQ66: #NULL! | AR66: The man was very mean | AS66: 5 | AT66: #NULL! | AU66: #NULL! | AV66: #NULL! | AX66: #NULL! | AY66: #NULL! | AZ66: #NULL! | BA66: #NULL! | BC66: #NULL! | BD66: #NULL! | BE66: #NULL! | BF66: #NULL! | BH66: #NULL! | BI66: #NULL! | BJ66: #NULL! | BK66: #NULL! | BL66: 2 | BM66: 5 | BN66: Someone be with you when it’s your turn | BO66: 6 | BP66: #NULL! | BQ66: #NULL! | BR66: #NULL! | BS66: 10 | BT66: None | BU66: 97 | BV66: #NULL! | BW66: #NULL! | BX66: #NULL! | BZ66: #NULL! | CA66: #NULL! | CB66: #NULL! | CC66: 2 | CD66: #NULL! | CE66: 2 | CF66: #NULL! | CG66: #NULL! | CI66: #NULL! | CJ66: #NULL! | CK66: #NULL! | CL66: #NULL! | CN66: #NULL! | CO66: #NULL! | CP66: #NULL! | CQ66: 2 | CR66: #NULL! | CS66: 1 | CT66: 1 | CU66: 2 | CV66: 1 | CW66: 1 | CX66: 7 | CY66: 1 | CZ66: Well he just said that I needed to pay my bill, I told him I was in the hospital and I just need to pay my bill he couldn’t help me | DA66: 5 | DB66: #NULL! | DC66: 1 | DD66: 1 | DE66: 0 | DF66: 0 | DG66: 0 | DH66: 1 | DI66: 1 | DJ66: 0 | DK66: 0 | DL66: 0 | DN66: 2 | DO66: To understand my situation but that didn't happen | DP66: 3 | DQ66: #NULL! | DR66: #NULL! | DT66: #NULL! | DU66: #NULL! | DV66: #NULL! | DW66: 5 | DX66: 1 | DY66: I had a young man that came to my house and put me on a program to help me with my situation | DZ66: 3 | EA66: #NULL! | EI66: #NULL! | EJ66: #NULL! | EK66: #NULL! | EL66: #NULL! | EM66: 10 | EN66: 3 | EP66: 5 | EQ66: 4 | ER66: 2 | ES66: 78702 | ET66: 1 | EU66: 1 | EV66: 1 | EW66: 5 | EX66: 2 | EY66: Linda | EZ66: Martinez | FB66: Linda.mtz02@gmail.com | FC66: 737 235 2503 | FD66: #NULL! | FE66: #NULL! | FF66: 3 | FH66: 12 Sep 2025 - 11:36:38 CDT | FI66: 19570
A67: 407 | B67: 1 | C67: 2 | D67: 1 | E67: #NULL! | F67: 2 | G67: 2 | H67: 2 | J67: 2 | K67: 15 | M67: Transferred service, one agent says I don’t need to put another deposit because I’m a customer, | O67: The next agent says I do, I sent emails with no response and the deposit is incurring late fees so I am at your mercy and nothing I say matters. | P67: 1 | Q67: #NULL! | R67: #NULL! | S67: #NULL! | T67: 2 | U67: 1 | V67: 1 | W67: 1 | X67: 2 | Y67: #NULL! | Z67: #NULL! | AA67: #NULL! | AB67: #NULL! | AD67: #NULL! | AE67: #NULL! | AF67: #NULL! | AG67: #NULL! | AH67: 2 | AI67: #NULL! | AJ67: #NULL! | AK67: #NULL! | AL67: #NULL! | AN67: #NULL! | AO67: #NULL! | AP67: #NULL! | AQ67: #NULL! | AR67: 1 | AS67: #NULL! | AT67: #NULL! | AU67: #NULL! | AV67: #NULL! | AX67: #NULL! | AY67: #NULL! | AZ67: #NULL! | BA67: #NULL! | BB67: 2 | BC67: #NULL! | BD67: #NULL! | BE67: #NULL! | BF67: #NULL! | BH67: #NULL! | BI67: #NULL! | BJ67: #NULL! | BK67: #NULL! | BL67: 2 | BM67: 10 | BN67: Do not recall | BO67: 98 | BP67: #NULL! | BQ67: #NULL! | BR67: #NULL! | BS67: 6 | BT67: Don’t put it so loud. | BU67: 21 | BV67: #NULL! | BW67: #NULL! | BX67: #NULL! | BZ67: #NULL! | CA67: #NULL! | CB67: #NULL! | CC67: 1 | CD67: 6 | CE67: 2 | CF67: #NULL! | CG67: #NULL! | CI67: #NULL! | CJ67: #NULL! | CK67: #NULL! | CL67: #NULL! | CN67: #NULL! | CO67: #NULL! | CP67: #NULL! | CQ67: 2 | CR67: #NULL! | CS67: 1 | CT67: 1 | CU67: 1 | CV67: 1 | CW67: 1 | CX67: 1 | CY67: 1 | CZ67: Read prior notes | DA67: 2 | DB67: #NULL! | DC67: 1 | DD67: 1 | DE67: 1 | DF67: 0 | DG67: 0 | DH67: 0 | DI67: 1 | DJ67: 0 | DK67: 0 | DL67: 1 | DM67: Nothing I said mattered | DN67: 2 | DO67: Call agents need to be on the same page, one says something and another one says something else, whatever is in the city’s favor “wins” | DP67: 5 | DQ67: 9 | DR67: #NULL! | DT67: #NULL! | DU67: #NULL! | DV67: #NULL! | DW67: 1 | DX67: 3 | DZ67: #NULL! | EA67: #NULL! | EI67: #NULL! | EJ67: #NULL! | EK67: #NULL! | EL67: #NULL! | EM67: 7 | EN67: 7 | EP67: 1 | EQ67: 2 | ER67: 3 | ES67: 78745 | ET67: 7 | EU67: 6 | EV67: 8 | EW67: 5 | EX67: 2 | EY67: Linda | EZ67: Sweeney | FB67: Mswurdygurl@yahoo.com | FC67: 5125895413 | FD67: #NULL! | FE67: #NULL! | FF67: 3 | FH67: 12 Sep 2025 - 11:18:51 CDT | FI67: 17774
A68: 408 | B68: 1 | C68: 2 | D68: 1 | E68: #NULL! | F68: 2 | G68: 2 | H68: 2 | J68: 1 | K68: 38 | N68: Setting up autopay | P68: #NULL! | Q68: #NULL! | R68: #NULL! | S68: #NULL! | T68: 7 | U68: 8 | V68: 7 | W68: 8 | Y68: #NULL! | Z68: #NULL! | AA68: #NULL! | AB68: #NULL! | AD68: #NULL! | AE68: #NULL! | AF68: #NULL! | AG68: #NULL! | AI68: #NULL! | AJ68: #NULL! | AK68: #NULL! | AL68: #NULL! | AM68: I had to talk with someone as I remember | AN68: 99 | AO68: #NULL! | AP68: #NULL! | AQ68: #NULL! | AS68: #NULL! | AT68: #NULL! | AU68: #NULL! | AV68: #NULL! | AX68: #NULL! | AY68: #NULL! | AZ68: #NULL! | BA68: #NULL! | BC68: #NULL! | BD68: #NULL! | BE68: #NULL! | BF68: #NULL! | BG68: I remember the hold time over 5 minutes | BH68: 2 | BI68: #NULL! | BJ68: #NULL! | BK68: #NULL! | BL68: 2 | BM68: 8 | BN68: I don’t recall | BO68: 98 | BP68: #NULL! | BQ68: #NULL! | BR68: #NULL! | BS68: 11 | BT68: Something specific to my account. | BU68: 17 | BV68: #NULL! | BW68: #NULL! | BX68: #NULL! | BZ68: #NULL! | CA68: #NULL! | CB68: #NULL! | CC68: 3 | CD68: #NULL! | CE68: 2 | CF68: #NULL! | CG68: #NULL! | CI68: #NULL! | CJ68: #NULL! | CK68: #NULL! | CL68: #NULL! | CN68: #NULL! | CO68: #NULL! | CP68: #NULL! | CQ68: 2 | CR68: #NULL! | CS68: 9 | CT68: 8 | CU68: 8 | CV68: 8 | CW68: 8 | CX68: 8 | CY68: 8 | DA68: #NULL! | DB68: #NULL! | DC68: 8 | DD68: #NULL! | DE68: #NULL! | DF68: #NULL! | DG68: #NULL! | DH68: #NULL! | DI68: #NULL! | DJ68: #NULL! | DK68: #NULL! | DL68: #NULL! | DN68: 1 | DP68: #NULL! | DQ68: #NULL! | DR68: #NULL! | DT68: #NULL! | DU68: #NULL! | DV68: #NULL! | DW68: 2 | DX68: 3 | DZ68: #NULL! | EA68: #NULL! | EI68: #NULL! | EJ68: #NULL! | EK68: #NULL! | EL68: #NULL! | EM68: 10 | EN68: 1 | EP68: 5 | EQ68: 4 | ER68: 2 | ES68: 78704 | ET68: 1 | EU68: 5 | EV68: 6 | EW68: 4 | EX68: 1 | EY68: Robert | EZ68: Cahn | FB68: robertcahn@hotmail.com | FC68: 9173123409 | FD68: #NULL! | FE68: #NULL! | FF68: 1 | FH68: 12 Sep 2025 - 11:23:04 CDT | FI68: 1735
A69: 411 | B69: 1 | C69: 2 | D69: 1 | E69: #NULL! | F69: 2 | G69: 2 | H69: 1 | J69: 1 | K69: 20 | P69: #NULL! | Q69: #NULL! | R69: #NULL! | S69: #NULL! | T69: 4 | U69: 11 | V69: 3 | W69: 6 | Y69: #NULL! | Z69: #NULL! | AA69: #NULL! | AB69: #NULL! | AD69: #NULL! | AE69: #NULL! | AF69: #NULL! | AG69: #NULL! | AI69: #NULL! | AJ69: #NULL! | AK69: #NULL! | AL69: #NULL! | AN69: #NULL! | AO69: #NULL! | AP69: #NULL! | AQ69: #NULL! | AR69: They never understand me | AS69: 4 | AT69: #NULL! | AU69: #NULL! | AV69: #NULL! | AX69: #NULL! | AY69: #NULL! | AZ69: #NULL! | BA69: #NULL! | BC69: #NULL! | BD69: #NULL! | BE69: #NULL! | BF69: #NULL! | BH69: #NULL! | BI69: #NULL! | BJ69: #NULL! | BK69: #NULL! | BL69: 2 | BM69: 4 | BN69: No idea lol | BO69: 98 | BP69: #NULL! | BQ69: #NULL! | BR69: #NULL! | BS69: 7 | BT69: Nothing | BU69: 97 | BV69: #NULL! | BW69: #NULL! | BX69: #NULL! | BZ69: #NULL! | CA69: #NULL! | CB69: #NULL! | CC69: 2 | CD69: #NULL! | CE69: 2 | CF69: #NULL! | CG69: #NULL! | CI69: #NULL! | CJ69: #NULL! | CK69: #NULL! | CL69: #NULL! | CN69: #NULL! | CO69: #NULL! | CP69: #NULL! | CQ69: 2 | CR69: #NULL! | CS69: 10 | CT69: 10 | CU69: 10 | CV69: 10 | CW69: 10 | CX69: 10 | CY69: 10 | DA69: #NULL! | DB69: #NULL! | DC69: 10 | DD69: #NULL! | DE69: #NULL! | DF69: #NULL! | DG69: #NULL! | DH69: #NULL! | DI69: #NULL! | DJ69: #NULL! | DK69: #NULL! | DL69: #NULL! | DN69: 1 | DP69: #NULL! | DQ69: #NULL! | DR69: #NULL! | DT69: #NULL! | DU69: #NULL! | DV69: #NULL! | DW69: 2 | DX69: 2 | DZ69: #NULL! | EA69: #NULL! | EI69: #NULL! | EJ69: #NULL! | EK69: #NULL! | EL69: #NULL! | EM69: 4 | EN69: 1 | EP69: 1 | EQ69: 1 | ER69: 2 | ES69: 78724 | ET69: 2 | EU69: 3 | EV69: 6 | EW69: 4 | EX69: 2 | EY69: Lisa | EZ69: Thompson | FB69: lisalacythompson@gmail.com | FC69: 4352149295 | FD69: #NULL! | FE69: #NULL! | FF69: 3 | FH69: 12 Sep 2025 - 11:22:47 CDT | FI69: 14419
A70: 427 | B70: 1 | C70: 2 | D70: 1 | E70: #NULL! | F70: 2 | G70: 2 | H70: 3 | J70: 1 | K70: 21 | P70: #NULL! | Q70: #NULL! | R70: #NULL! | S70: #NULL! | T70: 10 | U70: 10 | V70: 11 | W70: 10 | Y70: #NULL! | Z70: #NULL! | AA70: #NULL! | AB70: #NULL! | AC70: It was easy to use | AD70: 20 | AE70: #NULL! | AF70: #NULL! | AG70: #NULL! | AI70: #NULL! | AJ70: #NULL! | AK70: #NULL! | AL70: #NULL! | AM70: Simple | AN70: 27 | AO70: #NULL! | AP70: #NULL! | AQ70: #NULL! | AS70: #NULL! | AT70: #NULL! | AU70: #NULL! | AV70: #NULL! | AX70: #NULL! | AY70: #NULL! | AZ70: #NULL! | BA70: #NULL! | BC70: #NULL! | BD70: #NULL! | BE70: #NULL! | BF70: #NULL! | BG70: No wait | BH70: 21 | BI70: #NULL! | BJ70: #NULL! | BK70: #NULL! | BL70: 1 | BM70: #NULL! | BO70: #NULL! | BP70: #NULL! | BQ70: #NULL! | BR70: #NULL! | BS70: #NULL! | BU70: #NULL! | BV70: #NULL! | BW70: #NULL! | BX70: #NULL! | BZ70: #NULL! | CA70: #NULL! | CB70: #NULL! | CC70: 2 | CD70: #NULL! | CE70: 2 | CF70: #NULL! | CG70: #NULL! | CI70: #NULL! | CJ70: #NULL! | CK70: #NULL! | CL70: #NULL! | CN70: #NULL! | CO70: #NULL! | CP70: #NULL! | CQ70: 2 | CR70: #NULL! | CS70: 10 | CT70: 10 | CU70: 10 | CV70: 11 | CW70: 10 | CX70: 10 | CY70: 11 | DA70: #NULL! | DB70: #NULL! | DC70: 10 | DD70: #NULL! | DE70: #NULL! | DF70: #NULL! | DG70: #NULL! | DH70: #NULL! | DI70: #NULL! | DJ70: #NULL! | DK70: #NULL! | DL70: #NULL! | DN70: 1 | DP70: #NULL! | DQ70: #NULL! | DR70: #NULL! | DT70: #NULL! | DU70: #NULL! | DV70: #NULL! | DW70: 3 | DX70: 1 | DY70: Email on the new system | DZ70: 3 | EA70: #NULL! | EI70: #NULL! | EJ70: #NULL! | EK70: #NULL! | EL70: #NULL! | EM70: 10 | EN70: 1 | EP70: 1 | EQ70: 1 | ER70: 2 | ES70: 78741 | ET70: 2 | EU70: 2 | EV70: 8 | EW70: 5 | EX70: 1 | EY70: Martin | EZ70: Wennerstrom | FB70: km5ct@arrl.net | FC70: 5129703774 | FD70: #NULL! | FE70: #NULL! | FF70: 3 | FH70: 12 Sep 2025 - 13:20:56 CDT | FI70: 13765
A71: 434 | B71: 1 | C71: 2 | D71: 1 | E71: #NULL! | F71: 2 | G71: 2 | H71: 2 | J71: 1 | K71: 2 | P71: #NULL! | Q71: #NULL! | R71: #NULL! | S71: #NULL! | T71: 10 | U71: 10 | V71: 10 | W71: 10 | Y71: #NULL! | Z71: #NULL! | AA71: #NULL! | AB71: #NULL! | AC71: There isn't a lot of it so you still get to the agent quickly | AD71: 22 | AE71: #NULL! | AF71: #NULL! | AG71: #NULL! | AI71: #NULL! | AJ71: #NULL! | AK71: #NULL! | AL71: #NULL! | AM71: It gets to the point | AN71: 28 | AO71: #NULL! | AP71: #NULL! | AQ71: #NULL! | AS71: #NULL! | AT71: #NULL! | AU71: #NULL! | AV71: #NULL! | AW71: It seems human-ish | AX71: 22 | AY71: #NULL! | AZ71: #NULL! | BA71: #NULL! | BC71: #NULL! | BD71: #NULL! | BE71: #NULL! | BF71: #NULL! | BG71: There is no wait time typically | BH71: 21 | BI71: #NULL! | BJ71: #NULL! | BK71: #NULL! | BL71: 1 | BM71: #NULL! | BO71: #NULL! | BP71: #NULL! | BQ71: #NULL! | BR71: #NULL! | BS71: #NULL! | BU71: #NULL! | BV71: #NULL! | BW71: #NULL! | BX71: #NULL! | BZ71: #NULL! | CA71: #NULL! | CB71: #NULL! | CC71: 2 | CD71: #NULL! | CE71: 2 | CF71: #NULL! | CG71: #NULL! | CI71: #NULL! | CJ71: #NULL! | CK71: #NULL! | CL71: #NULL! | CN71: #NULL! | CO71: #NULL! | CP71: #NULL! | CQ71: 2 | CR71: #NULL! | CS71: 10 | CT71: 10 | CU71: 10 | CV71: 10 | CW71: 10 | CX71: 10 | CY71: 10 | DA71: #NULL! | DB71: #NULL! | DC71: 10 | DD71: #NULL! | DE71: #NULL! | DF71: #NULL! | DG71: #NULL! | DH71: #NULL! | DI71: #NULL! | DJ71: #NULL! | DK71: #NULL! | DL71: #NULL! | DN71: 1 | DP71: #NULL! | DQ71: #NULL! | DR71: #NULL! | DT71: #NULL! | DU71: #NULL! | DV71: #NULL! | DW71: 4 | DX71: 2 | DZ71: #NULL! | EA71: #NULL! | EI71: #NULL! | EJ71: #NULL! | EK71: #NULL! | EL71: #NULL! | EM71: 4 | EN71: 1 | EP71: 1 | EQ71: 3 | ER71: 1 | ES71: 78741 | ET71: 1 | EU71: 5 | EV71: 6 | EW71: 4 | EX71: 2 | EY71: Alyona | EZ71: DelaCoeur | FB71: alyd4889@gmail.com | FC71: 2064539569 | FD71: #NULL! | FE71: #NULL! | FF71: 3 | FH71: 12 Sep 2025 - 16:41:47 CDT | FI71: 19679
A72: 439 | B72: 1 | C72: 2 | D72: 1 | E72: #NULL! | F72: 2 | G72: 2 | H72: 2 | J72: 1 | K72: 1 | P72: #NULL! | Q72: #NULL! | R72: #NULL! | S72: 1 | T72: 4 | U72: 1 | V72: 2 | W72: 4 | Y72: #NULL! | Z72: #NULL! | AA72: #NULL! | AB72: #NULL! | AD72: #NULL! | AE72: #NULL! | AF72: #NULL! | AG72: #NULL! | AH72: They simply kept changing info they gave us | AI72: 6 | AJ72: #NULL! | AK72: #NULL! | AL72: #NULL! | AN72: #NULL! | AO72: #NULL! | AP72: #NULL! | AQ72: #NULL! | AR72: Uninformed employees | AS72: 6 | AT72: #NULL! | AU72: #NULL! | AV72: #NULL! | AX72: #NULL! | AY72: #NULL! | AZ72: #NULL! | BA72: #NULL! | BC72: #NULL! | BD72: #NULL! | BE72: #NULL! | BF72: #NULL! | BH72: #NULL! | BI72: #NULL! | BJ72: #NULL! | BK72: #NULL! | BL72: 2 | BM72: 5 | BN72: Do not | BO72: 98 | BP72: #NULL! | BQ72: #NULL! | BR72: #NULL! | BS72: 1 | BT72: Info on the city wide outages | BU72: 7 | BV72: #NULL! | BW72: #NULL! | BX72: #NULL! | BZ72: #NULL! | CA72: #NULL! | CB72: #NULL! | CC72: 2 | CD72: #NULL! | CE72: 2 | CF72: #NULL! | CG72: #NULL! | CI72: #NULL! | CJ72: #NULL! | CK72: #NULL! | CL72: #NULL! | CN72: #NULL! | CO72: #NULL! | CP72: #NULL! | CQ72: 2 | CR72: #NULL! | CS72: 8 | CT72: 6 | CU72: 4 | CV72: 5 | CW72: 7 | CX72: 5 | CY72: 4 | CZ72: Citywide outage had no info | DA72: 4 | DB72: #NULL! | DC72: 4 | DD72: 0 | DE72: 1 | DF72: 0 | DG72: 0 | DH72: 0 | DI72: 1 | DJ72: 0 | DK72: 0 | DL72: 0 | DN72: 2 | DO72: Have an actual message to those of us experiencing an outage, even a " sorry , we are not sure" | DP72: 3 | DQ72: #NULL! | DR72: #NULL! | DT72: #NULL! | DU72: #NULL! | DV72: #NULL! | DW72: 1 | DX72: 2 | DZ72: #NULL! | EA72: #NULL! | EI72: #NULL! | EJ72: #NULL! | EK72: #NULL! | EL72: #NULL! | EM72: 10 | EN72: 1 | EP72: 1 | EQ72: 1 | ER72: 2 | ES72: 78757 | ET72: 2 | EU72: 5 | EV72: 6 | EW72: 5 | EX72: 2 | EY72: Chloe | EZ72: Midia | FB72: Chloe.midia@gmail.com | FC72: 5129053815 | FD72: #NULL! | FE72: #NULL! | FF72: 3 | FH72: 12 Sep 2025 - 19:45:54 CDT | FI72: 22103
A73: 446 | B73: 1 | C73: 2 | D73: 1 | E73: #NULL! | F73: 2 | G73: 2 | H73: 2 | J73: 2 | K73: 1 | O73: Power outage; text messages saying it was on, it was not; told to call, offices closed, no power forv5cdays in May/June is not ok or is bad information and no way to get true information or updates. | P73: 13 | Q73: #NULL! | R73: #NULL! | S73: 1 | T73: 1 | U73: 1 | V73: 1 | W73: 1 | X73: No live person option; no option for immediate crisis | Y73: 3 | Z73: #NULL! | AA73: #NULL! | AB73: #NULL! | AD73: #NULL! | AE73: #NULL! | AF73: #NULL! | AG73: #NULL! | AH73: Miscommunication and false information | AI73: 8 | AJ73: #NULL! | AK73: #NULL! | AL73: #NULL! | AN73: #NULL! | AO73: #NULL! | AP73: #NULL! | AQ73: #NULL! | AR73: Inefficient | AS73: 2 | AT73: #NULL! | AU73: #NULL! | AV73: #NULL! | AX73: #NULL! | AY73: #NULL! | AZ73: #NULL! | BA73: #NULL! | BB73: Need call back feature to queue calls | BC73: 4 | BD73: #NULL! | BE73: #NULL! | BF73: #NULL! | BH73: #NULL! | BI73: #NULL! | BJ73: #NULL! | BK73: #NULL! | BL73: 4 | BM73: #NULL! | BO73: #NULL! | BP73: #NULL! | BQ73: #NULL! | BR73: #NULL! | BS73: #NULL! | BU73: #NULL! | BV73: #NULL! | BW73: #NULL! | BX73: 1 | BY73: They never called! | BZ73: 1 | CA73: #NULL! | CB73: #NULL! | CC73: 2 | CD73: #NULL! | CE73: 3 | CF73: #NULL! | CG73: #NULL! | CI73: #NULL! | CJ73: #NULL! | CK73: #NULL! | CL73: #NULL! | CN73: #NULL! | CO73: #NULL! | CP73: #NULL! | CQ73: 2 | CR73: #NULL! | CS73: 5 | CT73: 5 | CU73: 5 | CV73: 1 | CW73: 1 | CX73: 10 | CY73: 5 | CZ73: They did not return call. They did not know anything. The whole situation was not ok | DA73: 1 | DB73: #NULL! | DC73: 1 | DD73: 0 | DE73: 1 | DF73: 0 | DG73: 0 | DH73: 0 | DI73: 0 | DJ73: 0 | DK73: 0 | DL73: 0 | DN73: 2 | DO73: Send texts that are correct. Have live cars when crisis is happening on phones. Time to respond and support a city the size of Austin efficiently or allow other providers in market | DP73: 1 | DQ73: #NULL! | DR73: #NULL! | DT73: #NULL! | DU73: #NULL! | DV73: #NULL! | DW73: 2 | DX73: 2 | DZ73: #NULL! | EA73: #NULL! | EI73: #NULL! | EJ73: #NULL! | EK73: #NULL! | EL73: #NULL! | EM73: 8 | EN73: 1 | EP73: 1 | EQ73: 1 | ER73: 2 | ES73: 78731 | ET73: 2 | EU73: 5 | EV73: 6 | EW73: 5 | EX73: 2 | EY73: Jill | EZ73: Klucher | FB73: Jillklucher@gmail.com | FC73: 5125874878 | FD73: #NULL! | FE73: #NULL! | FF73: 3 | FH73: 13 Sep 2025 - 09:43:59 CDT | FI73: 18651
A74: 460 | B74: 1 | C74: 2 | D74: 1 | E74: #NULL! | F74: 2 | G74: 2 | H74: 2 | J74: 2 | K74: 3 | O74: Just bills | P74: 1 | Q74: #NULL! | R74: #NULL! | S74: #NULL! | T74: 9 | U74: 10 | V74: 10 | W74: 8 | Y74: #NULL! | Z74: #NULL! | AA74: #NULL! | AB74: #NULL! | AC74: N/a | AD74: 97 | AE74: #NULL! | AF74: #NULL! | AG74: #NULL! | AI74: #NULL! | AJ74: #NULL! | AK74: #NULL! | AL74: #NULL! | AM74: N/a | AN74: 97 | AO74: #NULL! | AP74: #NULL! | AQ74: #NULL! | AS74: #NULL! | AT74: #NULL! | AU74: #NULL! | AV74: #NULL! | AW74: N/a | AX74: 97 | AY74: #NULL! | AZ74: #NULL! | BA74: #NULL! | BC74: #NULL! | BD74: #NULL! | BE74: #NULL! | BF74: #NULL! | BG74: N/a | BH74: 97 | BI74: #NULL! | BJ74: #NULL! | BK74: #NULL! | BL74: 2 | BM74: 7 | BN74: Yes | BO74: 99 | BP74: #NULL! | BQ74: #NULL! | BR74: #NULL! | BS74: 10 | BT74: N/a | BU74: 97 | BV74: #NULL! | BW74: #NULL! | BX74: #NULL! | BZ74: #NULL! | CA74: #NULL! | CB74: #NULL! | CC74: 2 | CD74: #NULL! | CE74: 2 | CF74: #NULL! | CG74: #NULL! | CI74: #NULL! | CJ74: #NULL! | CK74: #NULL! | CL74: #NULL! | CN74: #NULL! | CO74: #NULL! | CP74: #NULL! | CQ74: 2 | CR74: #NULL! | CS74: 10 | CT74: 10 | CU74: 10 | CV74: 10 | CW74: 10 | CX74: 10 | CY74: 10 | DA74: #NULL! | DB74: #NULL! | DC74: 10 | DD74: #NULL! | DE74: #NULL! | DF74: #NULL! | DG74: #NULL! | DH74: #NULL! | DI74: #NULL! | DJ74: #NULL! | DK74: #NULL! | DL74: #NULL! | DN74: 1 | DP74: #NULL! | DQ74: #NULL! | DR74: #NULL! | DT74: #NULL! | DU74: #NULL! | DV74: #NULL! | DW74: 3 | DX74: 1 | DY74: Just adjustable bill | DZ74: 3 | EA74: #NULL! | EI74: #NULL! | EJ74: #NULL! | EK74: #NULL! | EL74: #NULL! | EM74: 7 | EN74: 2 | EP74: 6 | EQ74: 3 | ER74: 1 | ES74: 78752 | ET74: 1 | EU74: 2 | EV74: 7 | EW74: 5 | EX74: 1 | EY74: Korley | EZ74: Blaboe | FB74: korley_1@yahoo.com | FC74: '+1 512-775-5464 | FD74: #NULL! | FE74: #NULL! | FF74: 3 | FH74: 14 Sep 2025 - 16:26:39 CDT | FI74: 13507
A75: 461 | B75: 1 | C75: 2 | D75: 1 | E75: #NULL! | F75: 2 | G75: 2 | H75: 4 | I75: Reported me to credit bureau. I had to stop mail service because of mail theft. | J75: 2 | K75: 12 | L75: Wasn’t able to get a loan because reporting to credit bureau. Mail theft caused us to stop mail. | O75: We had an office in an area consumed by mail theft and had stopped mail as a result. The account was supposed to be on auto pay and ae reported me to the credit bureaus. I paid and was told it could be removed but required supervisor approval. Was told no supervisors were available and would receive a call back. I never received one. Called again and was told the same thing. No call back. Out of frustration I finally forced a call and got connected to an equally angry supervisor. It was not resolved and never removed. It’s the only blemish on my credit. | P75: 6 | Q75: #NULL! | R75: #NULL! | S75: #NULL! | T75: 1 | U75: 1 | V75: 1 | W75: 1 | X75: 1 | Y75: #NULL! | Z75: #NULL! | AA75: #NULL! | AB75: #NULL! | AD75: #NULL! | AE75: #NULL! | AF75: #NULL! | AG75: #NULL! | AH75: 1 | AI75: #NULL! | AJ75: #NULL! | AK75: #NULL! | AL75: #NULL! | AN75: #NULL! | AO75: #NULL! | AP75: #NULL! | AQ75: #NULL! | AR75: 1 | AS75: #NULL! | AT75: #NULL! | AU75: #NULL! | AV75: #NULL! | AX75: #NULL! | AY75: #NULL! | AZ75: #NULL! | BA75: #NULL! | BB75: 1 | BC75: #NULL! | BD75: #NULL! | BE75: #NULL! | BF75: #NULL! | BH75: #NULL! | BI75: #NULL! | BJ75: #NULL! | BK75: #NULL! | BL75: 2 | BM75: 8 | BN75: I don't know | BO75: 98 | BP75: #NULL! | BQ75: #NULL! | BR75: #NULL! | BS75: 10 | BT75: ? | BU75: 99 | BV75: #NULL! | BW75: #NULL! | BX75: #NULL! | BZ75: #NULL! | CA75: #NULL! | CB75: #NULL! | CC75: 1 | CD75: 1 | CE75: 1 | CF75: 2 | CG75: #NULL! | CI75: #NULL! | CJ75: #NULL! | CK75: #NULL! | CL75: #NULL! | CN75: #NULL! | CO75: #NULL! | CP75: #NULL! | CQ75: 1 | CR75: 1 | CS75: 7 | CT75: 1 | CU75: 1 | CV75: 1 | CW75: 7 | CX75: 1 | CY75: 1 | CZ75: It’s a small amount of money that was owed and I had never had this level of problems with any other utility companies, like pec. Your attitudes at ae are destructive to people’s credit over such a small amount of money. | DA75: 5 | DB75: #NULL! | DC75: 1 | DD75: 0 | DE75: 1 | DF75: 0 | DG75: 0 | DH75: 0 | DI75: 0 | DJ75: 0 | DK75: 0 | DL75: 0 | DN75: 2 | DO75: Had supervisors available that understand when a customer calls in and has to be passed around, placed on a call back list to only not be called back, and could be frustrated about the experience, could be professional and know that the customer is upset at the situation and not the individual. | DP75: 5 | DQ75: #NULL! | DR75: #NULL! | DT75: #NULL! | DU75: #NULL! | DV75: #NULL! | DW75: 1 | DX75: 2 | DZ75: #NULL! | EA75: #NULL! | EI75: #NULL! | EJ75: #NULL! | EK75: #NULL! | EL75: #NULL! | EM75: 8 | EN75: 7 | EP75: 6 | EQ75: 2 | ER75: 3 | ES75: 78734 | ET75: 7 | EU75: 6 | EV75: 8 | EW75: 5 | EX75: 4 | EY75: James | EZ75: Irwin | FB75: Jamesirwin@austin.rr.com | FC75: 5128489445 | FD75: #NULL! | FE75: #NULL! | FF75: 3 | FH75: 14 Sep 2025 - 18:56:34 CDT | FI75: 15745
A76: 470 | B76: 1 | C76: 2 | D76: 1 | E76: #NULL! | F76: 2 | G76: 2 | H76: 4 | I76: Unknown fee on electricity bill | J76: 1 | K76: 38 | N76: Unknown fee on bill | P76: #NULL! | Q76: #NULL! | R76: #NULL! | S76: #NULL! | T76: 5 | U76: 5 | V76: 2 | W76: 5 | Y76: #NULL! | Z76: #NULL! | AA76: #NULL! | AB76: #NULL! | AD76: #NULL! | AE76: #NULL! | AF76: #NULL! | AG76: #NULL! | AI76: #NULL! | AJ76: #NULL! | AK76: #NULL! | AL76: #NULL! | AN76: #NULL! | AO76: #NULL! | AP76: #NULL! | AQ76: #NULL! | AR76: When I call, I want to talk to a live person. I do everything else online | AS76: 3 | AT76: #NULL! | AU76: #NULL! | AV76: #NULL! | AX76: #NULL! | AY76: #NULL! | AZ76: #NULL! | BA76: #NULL! | BC76: #NULL! | BD76: #NULL! | BE76: #NULL! | BF76: #NULL! | BH76: #NULL! | BI76: #NULL! | BJ76: #NULL! | BK76: #NULL! | BL76: 5 | BM76: 10 | BN76: I do not remember. I called forwarded several times | BO76: 98 | BP76: #NULL! | BQ76: #NULL! | BR76: #NULL! | BS76: 9 | BT76: City of Austin news, events, etc. | BU76: 7 | BV76: #NULL! | BW76: #NULL! | BX76: #NULL! | BZ76: #NULL! | CA76: #NULL! | CB76: #NULL! | CC76: 1 | CD76: 5 | CE76: 1 | CF76: 1 | CG76: 2 | CH76: No one could explain what/why the $15 transportation fee is for on my electricity bill | CI76: 4 | CJ76: #NULL! | CK76: #NULL! | CL76: 5 | CM76: Knowledge about all the unnecessary fees charged to the customer | CN76: 7 | CO76: #NULL! | CP76: #NULL! | CQ76: 1 | CR76: 7 | CS76: 8 | CT76: 8 | CU76: 8 | CV76: 2 | CW76: 11 | CX76: 8 | CY76: 11 | CZ76: Knowledge about all the extra fees and taxes charged to the customers | DA76: 4 | DB76: #NULL! | DC76: 7 | DD76: 0 | DE76: 0 | DF76: 0 | DG76: 0 | DH76: 0 | DI76: 1 | DJ76: 0 | DK76: 0 | DL76: 0 | DN76: 1 | DP76: #NULL! | DQ76: #NULL! | DR76: #NULL! | DT76: #NULL! | DU76: #NULL! | DV76: #NULL! | DW76: 1 | DX76: 2 | DZ76: #NULL! | EA76: #NULL! | EI76: #NULL! | EJ76: #NULL! | EK76: #NULL! | EL76: #NULL! | EM76: 8 | EN76: 1 | EP76: 1 | EQ76: 3 | ER76: 1 | ES76: 99999 | ET76: 1 | EU76: 4 | EV76: 8 | EW76: 5 | EX76: 2 | EY76: Deb | EZ76: Will | FB76: debandsons@gmail.com | FC76: 5125551212 | FD76: #NULL! | FE76: #NULL! | FF76: 3 | FH76: 15 Sep 2025 - 18:33:55 CDT | FI76: 15925
A77: 471 | B77: 1 | C77: 2 | D77: 1 | E77: #NULL! | F77: 3 | G77: 2 | H77: 4 | I77: Conservation info | J77: 1 | K77: 14 | N77: I wanted to get info about energy and water conservation audits | P77: #NULL! | Q77: #NULL! | R77: #NULL! | S77: #NULL! | T77: 1 | U77: 1 | V77: 1 | W77: 1 | X77: I got put on hold and never got to speak to a person | Y77: 2 | Z77: #NULL! | AA77: #NULL! | AB77: #NULL! | AD77: #NULL! | AE77: #NULL! | AF77: #NULL! | AG77: #NULL! | AH77: I got put on hold and never got to speak to a person | AI77: 3 | AJ77: #NULL! | AK77: #NULL! | AL77: #NULL! | AN77: #NULL! | AO77: #NULL! | AP77: #NULL! | AQ77: #NULL! | AR77: I got put on hold and never got to speak to a person | AS77: 2 | AT77: 3 | AU77: #NULL! | AV77: #NULL! | AX77: #NULL! | AY77: #NULL! | AZ77: #NULL! | BA77: #NULL! | BB77: I got put on hold and never got to speak to a person | BC77: 2 | BD77: #NULL! | BE77: #NULL! | BF77: #NULL! | BH77: #NULL! | BI77: #NULL! | BJ77: #NULL! | BK77: #NULL! | BL77: 3 | BM77: 11 | BO77: #NULL! | BP77: #NULL! | BQ77: #NULL! | BR77: #NULL! | BS77: #NULL! | BU77: #NULL! | BV77: #NULL! | BW77: #NULL! | BX77: #NULL! | BZ77: #NULL! | CA77: #NULL! | CB77: #NULL! | CC77: #NULL! | CD77: #NULL! | CE77: #NULL! | CF77: #NULL! | CG77: #NULL! | CI77: #NULL! | CJ77: #NULL! | CK77: #NULL! | CL77: #NULL! | CN77: #NULL! | CO77: #NULL! | CP77: #NULL! | CQ77: #NULL! | CR77: #NULL! | CS77: #NULL! | CT77: #NULL! | CU77: #NULL! | CV77: #NULL! | CW77: #NULL! | CX77: #NULL! | CY77: #NULL! | DA77: #NULL! | DB77: #NULL! | DC77: 1 | DD77: 0 | DE77: 0 | DF77: 0 | DG77: 0 | DH77: 0 | DI77: 0 | DJ77: 0 | DK77: 0 | DL77: 1 | DM77: I got put on hold and NEVER got to speak to a person | DN77: 2 | DO77: Have someone available to talk to about conservation audits during business hours. | DP77: 9 | DQ77: #NULL! | DR77: #NULL! | DT77: #NULL! | DU77: #NULL! | DV77: #NULL! | DW77: 1 | DX77: 3 | DZ77: #NULL! | EA77: #NULL! | EI77: #NULL! | EJ77: #NULL! | EK77: #NULL! | EL77: #NULL! | EM77: 10 | EN77: 1 | EP77: 5 | EQ77: 4 | ER77: 2 | ES77: 78759 | ET77: 1 | EU77: 5 | EV77: 8 | EW77: 5 | EX77: 2 | EY77: Becky | EZ77: Brenner | FB77: jbbwanders@gmail.com | FC77: 5126320137 | FD77: #NULL! | FE77: #NULL! | FF77: 2 | FH77: 15 Sep 2025 - 22:40:08 CDT | FI77: 10870
A78: 482 | B78: 1 | C78: 2 | D78: 1 | E78: #NULL! | F78: 2 | G78: 2 | H78: 2 | J78: 1 | K78: 3 | P78: #NULL! | Q78: #NULL! | R78: #NULL! | S78: #NULL! | T78: 3 | U78: 3 | V78: 3 | W78: 3 | X78: Communication issues | Y78: 5 | Z78: #NULL! | AA78: #NULL! | AB78: #NULL! | AD78: #NULL! | AE78: #NULL! | AF78: #NULL! | AG78: #NULL! | AH78: Communication issues | AI78: 9 | AJ78: #NULL! | AK78: #NULL! | AL78: #NULL! | AN78: #NULL! | AO78: #NULL! | AP78: #NULL! | AQ78: #NULL! | AR78: Communication issues | AS78: 5 | AT78: #NULL! | AU78: #NULL! | AV78: #NULL! | AX78: #NULL! | AY78: #NULL! | AZ78: #NULL! | BA78: #NULL! | BB78: Communication issues | BC78: 5 | BD78: #NULL! | BE78: #NULL! | BF78: #NULL! | BH78: #NULL! | BI78: #NULL! | BJ78: #NULL! | BK78: #NULL! | BL78: 2 | BM78: 9 | BN78: N/a, don't recall, guessing there were announcements and/or giving COA website info | BO78: 3 | BP78: #NULL! | BQ78: #NULL! | BR78: #NULL! | BS78: 10 | BT78: Spa announcements related to utilities. | BU78: 1 | BV78: #NULL! | BW78: #NULL! | BX78: #NULL! | BZ78: #NULL! | CA78: #NULL! | CB78: #NULL! | CC78: 2 | CD78: #NULL! | CE78: 2 | CF78: #NULL! | CG78: #NULL! | CI78: #NULL! | CJ78: #NULL! | CK78: #NULL! | CL78: #NULL! | CN78: #NULL! | CO78: #NULL! | CP78: #NULL! | CQ78: 2 | CR78: #NULL! | CS78: 10 | CT78: 11 | CU78: 10 | CV78: 11 | CW78: 11 | CX78: 10 | CY78: 11 | DA78: #NULL! | DB78: #NULL! | DC78: 9 | DD78: #NULL! | DE78: #NULL! | DF78: #NULL! | DG78: #NULL! | DH78: #NULL! | DI78: #NULL! | DJ78: #NULL! | DK78: #NULL! | DL78: #NULL! | DN78: 1 | DP78: #NULL! | DQ78: #NULL! | DR78: #NULL! | DT78: #NULL! | DU78: #NULL! | DV78: #NULL! | DW78: 5 | DX78: 2 | DZ78: #NULL! | EA78: #NULL! | EI78: #NULL! | EJ78: #NULL! | EK78: #NULL! | EL78: #NULL! | EM78: 11 | EN78: 7 | EP78: 7 | EQ78: 5 | ER78: 3 | ES78: 99999 | ET78: 7 | EU78: 6 | EV78: 8 | EW78: 6 | EX78: 4 | EY78: laur | EZ78: along | FB78: lauralong@duck.com | FC78: 5125125125 | FD78: #NULL! | FE78: #NULL! | FF78: 2 | FH78: 16 Sep 2025 - 10:38:02 CDT | FI78: 12404
A79: 486 | B79: 1 | C79: 2 | D79: 1 | E79: #NULL! | F79: 2 | G79: 2 | H79: 2 | J79: 1 | K79: 4 | P79: #NULL! | Q79: #NULL! | R79: #NULL! | S79: #NULL! | T79: 10 | U79: 10 | V79: 10 | W79: 10 | Y79: #NULL! | Z79: #NULL! | AA79: #NULL! | AB79: #NULL! | AC79: Easy to call and connect to agent | AD79: 22 | AE79: #NULL! | AF79: #NULL! | AG79: #NULL! | AI79: #NULL! | AJ79: #NULL! | AK79: #NULL! | AL79: #NULL! | AM79: My questions were all answered | AN79: 23 | AO79: #NULL! | AP79: #NULL! | AQ79: #NULL! | AS79: #NULL! | AT79: #NULL! | AU79: #NULL! | AV79: #NULL! | AW79: Easy to talk to a knowledgeable person who understood immediately what I was asking for | AX79: 25 | AY79: #NULL! | AZ79: #NULL! | BA79: #NULL! | BC79: #NULL! | BD79: #NULL! | BE79: #NULL! | BF79: #NULL! | BG79: Call was answered within a minute | BH79: 21 | BI79: #NULL! | BJ79: #NULL! | BK79: #NULL! | BL79: 1 | BM79: #NULL! | BO79: #NULL! | BP79: #NULL! | BQ79: #NULL! | BR79: #NULL! | BS79: #NULL! | BU79: #NULL! | BV79: #NULL! | BW79: #NULL! | BX79: #NULL! | BZ79: #NULL! | CA79: #NULL! | CB79: #NULL! | CC79: 2 | CD79: #NULL! | CE79: 2 | CF79: #NULL! | CG79: #NULL! | CI79: #NULL! | CJ79: #NULL! | CK79: #NULL! | CL79: #NULL! | CN79: #NULL! | CO79: #NULL! | CP79: #NULL! | CQ79: 2 | CR79: #NULL! | CS79: 10 | CT79: 10 | CU79: 10 | CV79: 10 | CW79: 10 | CX79: 10 | CY79: 10 | DA79: #NULL! | DB79: #NULL! | DC79: 10 | DD79: #NULL! | DE79: #NULL! | DF79: #NULL! | DG79: #NULL! | DH79: #NULL! | DI79: #NULL! | DJ79: #NULL! | DK79: #NULL! | DL79: #NULL! | DN79: 1 | DP79: #NULL! | DQ79: #NULL! | DR79: #NULL! | DT79: #NULL! | DU79: #NULL! | DV79: #NULL! | DW79: 4 | DX79: 2 | DZ79: #NULL! | EA79: #NULL! | EI79: #NULL! | EJ79: #NULL! | EK79: #NULL! | EL79: #NULL! | EM79: 6 | EN79: 1 | EP79: 1 | EQ79: 1 | ER79: 2 | ES79: 78731 | ET79: 4 | EU79: 5 | EV79: 6 | EW79: 5 | EX79: 1 | EY79: Sean | EZ79: Owen | FB79: srowen@gmail.com | FC79: 7372170020 | FD79: #NULL! | FE79: #NULL! | FF79: 2 | FH79: 16 Sep 2025 - 10:50:05 CDT | FI79: 8662
A80: 491 | B80: 1 | C80: 2 | D80: 1 | E80: #NULL! | F80: 2 | G80: 2 | H80: 4 | I80: Help for low income family | J80: 1 | K80: 38 | N80: Assistance with bills | P80: #NULL! | Q80: #NULL! | R80: #NULL! | S80: #NULL! | T80: 10 | U80: 2 | V80: 10 | W80: 10 | Y80: #NULL! | Z80: #NULL! | AA80: #NULL! | AB80: #NULL! | AC80: It is. | AD80: 20 | AE80: #NULL! | AF80: #NULL! | AG80: #NULL! | AH80: I have applied for assistance with our bill. I sent copy of gross income ($29,782. Sent copy of social security payments. Refused because I did not get financial aid from other agencies. I filed 4 times and every time it was another reason e.g. I sure sign my name on back of papers I sent. I am very frustrated. | AI80: 7 | AJ80: #NULL! | AK80: #NULL! | AL80: #NULL! | AN80: #NULL! | AO80: #NULL! | AP80: #NULL! | AQ80: #NULL! | AS80: #NULL! | AT80: #NULL! | AU80: #NULL! | AV80: #NULL! | AW80: Answered in timely manner. Person was polite. | AX80: 21 | AY80: 25 | AZ80: #NULL! | BA80: #NULL! | BC80: #NULL! | BD80: #NULL! | BE80: #NULL! | BF80: #NULL! | BG80: As above | BH80: 21 | BI80: #NULL! | BJ80: #NULL! | BK80: #NULL! | BL80: 1 | BM80: #NULL! | BO80: #NULL! | BP80: #NULL! | BQ80: #NULL! | BR80: #NULL! | BS80: #NULL! | BU80: #NULL! | BV80: #NULL! | BW80: #NULL! | BX80: #NULL! | BZ80: #NULL! | CA80: #NULL! | CB80: #NULL! | CC80: 1 | CD80: 8 | CE80: 3 | CF80: #NULL! | CG80: #NULL! | CI80: #NULL! | CJ80: #NULL! | CK80: #NULL! | CL80: #NULL! | CN80: #NULL! | CO80: #NULL! | CP80: #NULL! | CQ80: 2 | CR80: #NULL! | CS80: 9 | CT80: 9 | CU80: 10 | CV80: 6 | CW80: 6 | CX80: 10 | CY80: 10 | CZ80: Be more informed about assistance process. Every time I called it was a different answer. | DA80: 4 | DB80: #NULL! | DC80: 6 | DD80: 0 | DE80: 1 | DF80: 0 | DG80: 0 | DH80: 0 | DI80: 1 | DJ80: 0 | DK80: 0 | DL80: 1 | DM80: I am still waiting for assistance with my bill. | DN80: 2 | DO80: .1. Know more about requirements for applying for help. 2. I read the application thoroughly and filled it out to the best of my ability. | DP80: 1 | DQ80: #NULL! | DR80: #NULL! | DT80: #NULL! | DU80: #NULL! | DV80: #NULL! | DW80: 3 | DX80: 2 | DZ80: #NULL! | EA80: #NULL! | EI80: #NULL! | EJ80: #NULL! | EK80: #NULL! | EL80: #NULL! | EM80: 10 | EN80: 1 | EP80: 5 | EQ80: 1 | ER80: 2 | ES80: 78733 | ET80: 2 | EU80: 4 | EV80: 3 | EW80: 5 | EX80: 2 | EY80: Patricia | EZ80: Turner | FB80: Pturner037@gmail.com | FC80: 678-642-3715 | FD80: #NULL! | FE80: #NULL! | FF80: 3 | FH80: 16 Sep 2025 - 11:59:19 CDT | FI80: 12833
A81: 494 | B81: 1 | C81: 2 | D81: 1 | E81: #NULL! | F81: 2 | G81: 2 | H81: 2 | J81: 1 | K81: 11 | P81: #NULL! | Q81: #NULL! | R81: #NULL! | S81: #NULL! | T81: 9 | U81: 9 | V81: 9 | W81: 9 | Y81: #NULL! | Z81: #NULL! | AA81: #NULL! | AB81: #NULL! | AC81: No brainer | AD81: 20 | AE81: #NULL! | AF81: #NULL! | AG81: #NULL! | AI81: #NULL! | AJ81: #NULL! | AK81: #NULL! | AL81: #NULL! | AM81: Same | AN81: 20 | AO81: #NULL! | AP81: #NULL! | AQ81: #NULL! | AS81: #NULL! | AT81: #NULL! | AU81: #NULL! | AV81: #NULL! | AW81: Necessary evil | AX81: 99 | AY81: #NULL! | AZ81: #NULL! | BA81: #NULL! | BC81: #NULL! | BD81: #NULL! | BE81: #NULL! | BF81: #NULL! | BG81: Ok - not a busy day | BH81: 21 | BI81: #NULL! | BJ81: #NULL! | BK81: #NULL! | BL81: 2 | BM81: 5 | BN81: Don't remember - generally ignore anyway | BO81: 98 | BP81: #NULL! | BQ81: #NULL! | BR81: #NULL! | BS81: 10 | BT81: I like callback info and off-ramp process - did not use this time but would if long wait time announced. | BU81: 13 | BV81: #NULL! | BW81: #NULL! | BX81: #NULL! | BZ81: #NULL! | CA81: #NULL! | CB81: #NULL! | CC81: 2 | CD81: #NULL! | CE81: 2 | CF81: #NULL! | CG81: #NULL! | CI81: #NULL! | CJ81: #NULL! | CK81: #NULL! | CL81: #NULL! | CN81: #NULL! | CO81: #NULL! | CP81: #NULL! | CQ81: 2 | CR81: #NULL! | CS81: 10 | CT81: 10 | CU81: 10 | CV81: 10 | CW81: 10 | CX81: 10 | CY81: 10 | DA81: #NULL! | DB81: #NULL! | DC81: 10 | DD81: #NULL! | DE81: #NULL! | DF81: #NULL! | DG81: #NULL! | DH81: #NULL! | DI81: #NULL! | DJ81: #NULL! | DK81: #NULL! | DL81: #NULL! | DN81: 1 | DP81: #NULL! | DQ81: #NULL! | DR81: #NULL! | DT81: #NULL! | DU81: #NULL! | DV81: #NULL! | DW81: 2 | DX81: 2 | DZ81: #NULL! | EA81: #NULL! | EI81: #NULL! | EJ81: #NULL! | EK81: #NULL! | EL81: #NULL! | EM81: 10 | EN81: 6 | EO81: These categories are stupid - from former census worker ! | EP81: 5 | EQ81: 2 | ER81: 2 | ES81: 78741 | ET81: 2 | EU81: 4 | EV81: 3 | EW81: 5 | EX81: 1 | EY81: Ronald | EZ81: Vasey | FB81: rvasey44@gmail.com | FC81: 5122173797 | FD81: #NULL! | FE81: #NULL! | FF81: 3 | FH81: 16 Sep 2025 - 12:16:44 CDT | FI81: 21331
A82: 495 | B82: 1 | C82: 2 | D82: 1 | E82: #NULL! | F82: 2 | G82: 2 | H82: 1 | J82: 2 | K82: 20 | O82: Recycling container not picked up for my address as well as my entire street. | P82: 12 | Q82: #NULL! | R82: #NULL! | S82: #NULL! | T82: 10 | U82: 10 | V82: 10 | W82: 10 | Y82: #NULL! | Z82: #NULL! | AA82: #NULL! | AB82: #NULL! | AC82: I am very familiar with these types of systems. I found it easy to use. | AD82: 27 | AE82: #NULL! | AF82: #NULL! | AG82: #NULL! | AI82: #NULL! | AJ82: #NULL! | AK82: #NULL! | AL82: #NULL! | AM82: Effective | AN82: 21 | AO82: #NULL! | AP82: #NULL! | AQ82: #NULL! | AS82: #NULL! | AT82: #NULL! | AU82: #NULL! | AV82: #NULL! | AW82: Effective | AX82: 21 | AY82: #NULL! | AZ82: #NULL! | BA82: #NULL! | BC82: #NULL! | BD82: #NULL! | BE82: #NULL! | BF82: #NULL! | BG82: Call answered quickly | BH82: 21 | BI82: #NULL! | BJ82: #NULL! | BK82: #NULL! | BL82: 1 | BM82: #NULL! | BO82: #NULL! | BP82: #NULL! | BQ82: #NULL! | BR82: #NULL! | BS82: #NULL! | BU82: #NULL! | BV82: #NULL! | BW82: #NULL! | BX82: #NULL! | BZ82: #NULL! | CA82: #NULL! | CB82: #NULL! | CC82: 2 | CD82: #NULL! | CE82: 2 | CF82: #NULL! | CG82: #NULL! | CI82: #NULL! | CJ82: #NULL! | CK82: #NULL! | CL82: #NULL! | CN82: #NULL! | CO82: #NULL! | CP82: #NULL! | CQ82: 2 | CR82: #NULL! | CS82: 10 | CT82: 10 | CU82: 10 | CV82: 10 | CW82: 10 | CX82: 10 | CY82: 10 | DA82: #NULL! | DB82: #NULL! | DC82: 10 | DD82: #NULL! | DE82: #NULL! | DF82: #NULL! | DG82: #NULL! | DH82: #NULL! | DI82: #NULL! | DJ82: #NULL! | DK82: #NULL! | DL82: #NULL! | DN82: 1 | DP82: #NULL! | DQ82: #NULL! | DR82: #NULL! | DT82: #NULL! | DU82: #NULL! | DV82: #NULL! | DW82: 2 | DX82: 2 | DZ82: #NULL! | EA82: #NULL! | EI82: #NULL! | EJ82: #NULL! | EK82: #NULL! | EL82: #NULL! | EM82: 6 | EN82: 3 | EP82: 5 | EQ82: 1 | ER82: 2 | ES82: 78746 | ET82: 7 | EU82: 4 | EV82: 8 | EW82: 5 | EX82: 1 | EY82: D | EZ82: Saenz | FB82: rhumstone@att.net | FC82: 5125608949 | FD82: #NULL! | FE82: #NULL! | FF82: 1 | FH82: 16 Sep 2025 - 12:24:57 CDT | FI82: 2985
A83: 500 | B83: 1 | C83: 2 | D83: 1 | E83: #NULL! | F83: 2 | G83: 2 | H83: 4 | I83: Garbage bin | J83: 2 | K83: 15 | M83: Garbage bin | O83: My garbage bin was taken away, when they did the normal weekly pick up. I called to let them know and that I needed a replacement garbage bin. | P83: 12 | Q83: #NULL! | R83: #NULL! | S83: #NULL! | T83: 7 | U83: 7 | V83: 7 | W83: 7 | Y83: #NULL! | Z83: #NULL! | AA83: #NULL! | AB83: #NULL! | AD83: #NULL! | AE83: #NULL! | AF83: #NULL! | AG83: #NULL! | AI83: #NULL! | AJ83: #NULL! | AK83: #NULL! | AL83: #NULL! | AN83: #NULL! | AO83: #NULL! | AP83: #NULL! | AQ83: #NULL! | AS83: #NULL! | AT83: #NULL! | AU83: #NULL! | AV83: #NULL! | AX83: #NULL! | AY83: #NULL! | AZ83: #NULL! | BA83: #NULL! | BC83: #NULL! | BD83: #NULL! | BE83: #NULL! | BF83: #NULL! | BH83: #NULL! | BI83: #NULL! | BJ83: #NULL! | BK83: #NULL! | BL83: 2 | BM83: 10 | BN83: Don't remember | BO83: 98 | BP83: #NULL! | BQ83: #NULL! | BR83: #NULL! | BS83: 7 | BT83: Department name and their extension in case we get disconnected. | BU83: 13 | BV83: #NULL! | BW83: #NULL! | BX83: #NULL! | BZ83: #NULL! | CA83: #NULL! | CB83: #NULL! | CC83: 1 | CD83: 3 | CE83: 1 | CF83: 1 | CG83: 1 | CH83: I had been transferred to wrong department | CI83: 1 | CJ83: #NULL! | CK83: #NULL! | CL83: 7 | CM83: Checking backing to make sure the call was not disconnected on their end. | CN83: 5 | CO83: #NULL! | CP83: #NULL! | CQ83: 2 | CR83: #NULL! | CS83: 9 | CT83: 10 | CU83: 7 | CV83: 5 | CW83: 7 | CX83: 9 | CY83: 10 | CZ83: They need to be more specific on delivery of bin; I had to call 3 times because the delivery day of the bin was not delivered on the 3 days I was told it was going to be delivered. | DA83: 4 | DB83: #NULL! | DC83: 7 | DD83: 0 | DE83: 1 | DF83: 1 | DG83: 0 | DH83: 0 | DI83: 0 | DJ83: 0 | DK83: 0 | DL83: 1 | DM83: i had to call 3x to finally get my bin replaced | DN83: 3 | DO83: Nothing more at this time, thank you for your concern on my customer service satisfaction. | DP83: 97 | DQ83: #NULL! | DR83: #NULL! | DT83: #NULL! | DU83: #NULL! | DV83: #NULL! | DW83: 3 | DX83: 2 | DZ83: #NULL! | EA83: #NULL! | EI83: #NULL! | EJ83: #NULL! | EK83: #NULL! | EL83: #NULL! | EM83: 11 | EN83: 7 | EP83: 7 | EQ83: 5 | ER83: 3 | ES83: 99999 | ET83: 7 | EU83: 6 | EV83: 8 | EW83: 6 | EX83: 4 | EY83: Linda | EZ83: Solis | FB83: lindasolis2000@gmail.com | FC83: 3107200685 | FD83: #NULL! | FE83: #NULL! | FF83: 2 | FH83: 16 Sep 2025 - 12:53:44 CDT | FI83: 7410
A84: 502 | B84: 1 | C84: 2 | D84: 1 | E84: #NULL! | F84: 2 | G84: 2 | H84: 1 | J84: 2 | K84: 20 | O84: We have contacted 311 multiple times to resolve getting our garbage picked up! We have lived at this corner lot residence since 1984. This has been an ongoing problem for as long as I can remember. We have tried putting the cans in front of the house, on the side entry garage side of our house & even placing the recycle in the front and garbage on the side. Last week I flagged down a trash truck that works the opposite side of the street and explained our saga. He stated that the trash should be picked up regardless of which side it is on. He was nice enough to pick up our trash which was out of his route. I even had one driver tell me years back that I was trying to get 2 pickups by having trash picked up on one side and filling the can again and moving it to the other side. That is ridiculous! | P84: 12 | Q84: #NULL! | R84: #NULL! | S84: #NULL! | T84: 9 | U84: 9 | V84: 9 | W84: 9 | Y84: #NULL! | Z84: #NULL! | AA84: #NULL! | AB84: #NULL! | AC84: 9 | AD84: #NULL! | AE84: #NULL! | AF84: #NULL! | AG84: #NULL! | AI84: #NULL! | AJ84: #NULL! | AK84: #NULL! | AL84: #NULL! | AM84: 9 | AN84: #NULL! | AO84: #NULL! | AP84: #NULL! | AQ84: #NULL! | AS84: #NULL! | AT84: #NULL! | AU84: #NULL! | AV84: #NULL! | AW84: 9 | AX84: #NULL! | AY84: #NULL! | AZ84: #NULL! | BA84: #NULL! | BC84: #NULL! | BD84: #NULL! | BE84: #NULL! | BF84: #NULL! | BG84: 9 | BH84: #NULL! | BI84: #NULL! | BJ84: #NULL! | BK84: #NULL! | BL84: 2 | BM84: 6 | BN84: Irrelevant | BO84: 99 | BP84: #NULL! | BQ84: #NULL! | BR84: #NULL! | BS84: 9 | BT84: Irrelevant | BU84: 99 | BV84: #NULL! | BW84: #NULL! | BX84: #NULL! | BZ84: #NULL! | CA84: #NULL! | CB84: #NULL! | CC84: 2 | CD84: #NULL! | CE84: 2 | CF84: #NULL! | CG84: #NULL! | CI84: #NULL! | CJ84: #NULL! | CK84: #NULL! | CL84: #NULL! | CN84: #NULL! | CO84: #NULL! | CP84: #NULL! | CQ84: 2 | CR84: #NULL! | CS84: 10 | CT84: 10 | CU84: 10 | CV84: 10 | CW84: 10 | CX84: 10 | CY84: 10 | DA84: #NULL! | DB84: #NULL! | DC84: 1 | DD84: 0 | DE84: 1 | DF84: 0 | DG84: 0 | DH84: 0 | DI84: 0 | DJ84: 0 | DK84: 0 | DL84: 0 | DN84: 2 | DO84: Do as promised and pick up the trash within 48 hours! Never happed in recent calls twice. One elevated to the supervise stating, “we have a picture and there was no garbage can there”. Really?? | DP84: 4 | DQ84: #NULL! | DR84: #NULL! | DT84: #NULL! | DU84: #NULL! | DV84: #NULL! | DW84: 1 | DX84: 1 | DY84: Irrelevant | DZ84: 99 | EA84: #NULL! | EI84: #NULL! | EJ84: #NULL! | EK84: #NULL! | EL84: #NULL! | EM84: 10 | EN84: 1 | EP84: 5 | EQ84: 1 | ER84: 2 | ES84: 78759 | ET84: 2 | EU84: 4 | EV84: 6 | EW84: 5 | EX84: 1 | EY84: Johnnie F | EZ84: Hajek Jr | FB84: stirringro@hotmail.com | FC84: 5126361258 | FD84: #NULL! | FE84: #NULL! | FF84: 2 | FH84: 16 Sep 2025 - 13:05:38 CDT | FI84: 7418
A85: 516 | B85: 1 | C85: 2 | D85: 1 | E85: #NULL! | F85: 3 | G85: 2 | H85: 2 | J85: 1 | K85: 20 | N85: When will they remove the od utility pole on my property that they replaced with a new pole last yea | P85: #NULL! | Q85: #NULL! | R85: #NULL! | S85: #NULL! | T85: 2 | U85: 1 | V85: 1 | W85: 2 | X85: Voice response systems are a pain | Y85: 9 | Z85: #NULL! | AA85: #NULL! | AB85: #NULL! | AD85: #NULL! | AE85: #NULL! | AF85: #NULL! | AG85: #NULL! | AH85: They don't ever provide the information I need | AI85: 6 | AJ85: #NULL! | AK85: #NULL! | AL85: #NULL! | AN85: #NULL! | AO85: #NULL! | AP85: #NULL! | AQ85: #NULL! | AR85: The worst. I want a live person who can actually answer my specific questions | AS85: 4 | AT85: #NULL! | AU85: #NULL! | AV85: #NULL! | AX85: #NULL! | AY85: #NULL! | AZ85: #NULL! | BA85: #NULL! | BB85: Irrelevant since waiting for poor service is a waste | BC85: 2 | BD85: #NULL! | BE85: #NULL! | BF85: #NULL! | BH85: #NULL! | BI85: #NULL! | BJ85: #NULL! | BK85: #NULL! | BL85: 5 | BM85: 10 | BN85: I don't listen to the hold messages. I put the phone down until I hear a real person. | BO85: 97 | BP85: #NULL! | BQ85: #NULL! | BR85: #NULL! | BS85: 10 | BT85: Nothing. Just get me to a person. | BU85: 21 | BV85: #NULL! | BW85: #NULL! | BX85: #NULL! | BZ85: #NULL! | CA85: #NULL! | CB85: #NULL! | CC85: 2 | CD85: #NULL! | CE85: 2 | CF85: #NULL! | CG85: #NULL! | CI85: #NULL! | CJ85: #NULL! | CK85: #NULL! | CL85: #NULL! | CN85: #NULL! | CO85: #NULL! | CP85: #NULL! | CQ85: 2 | CR85: #NULL! | CS85: 9 | CT85: 3 | CU85: 7 | CV85: 1 | CW85: 8 | CX85: 9 | CY85: 5 | CZ85: Not their fault. I was told it was basically up to me to contact other utilities about getting their wires moved off the old pole and they rep had no information on when the old pole might be removed except that the other wires had to be gone first. So basically Austin energy would do nothing, not even contact the other utilities, it was up to me. Very not satisfactory, especially since I don't even know whose sites are up there. | DA85: 97 | DB85: #NULL! | DC85: 1 | DD85: 0 | DE85: 1 | DF85: 0 | DG85: 0 | DH85: 0 | DI85: 1 | DJ85: 0 | DK85: 0 | DL85: 1 | DM85: I was basically told I had to do the footwork myself, which is absurd, | DN85: 2 | DO85: Austin energy could actually complete a job they started. The guys who put up the new poke and moved the electric stuff over told me ae would be contacting the other utilities using the old pole to get them to move their wires and the old pole would be removed. That was more than a year ago and nothing has been done and I have a bunch of unsightly wires hanging so low that I can run my hands over them. | DP85: 4 | DQ85: #NULL! | DR85: #NULL! | DT85: #NULL! | DU85: #NULL! | DV85: #NULL! | DW85: 1 | DX85: 2 | DZ85: #NULL! | EA85: #NULL! | EI85: #NULL! | EJ85: #NULL! | EK85: #NULL! | EL85: #NULL! | EM85: 10 | EN85: 1 | EP85: 2 | EQ85: 2 | ER85: 2 | ES85: 78704 | ET85: 1 | EU85: 5 | EV85: 8 | EW85: 5 | EX85: 2 | EY85: RONA | EZ85: DISTENFELD | FB85: rona@sbcglobal.net | FC85: 7372395258 | FD85: #NULL! | FE85: #NULL! | FF85: 3 | FH85: 16 Sep 2025 - 14:34:39 CDT | FI85: 18903
A86: 522 | B86: 1 | C86: 2 | D86: 1 | E86: #NULL! | F86: 2 | G86: 2 | H86: 2 | J86: 1 | K86: 4 | P86: #NULL! | Q86: #NULL! | R86: #NULL! | S86: #NULL! | T86: 5 | U86: 5 | V86: 5 | W86: 1 | Y86: #NULL! | Z86: #NULL! | AA86: #NULL! | AB86: #NULL! | AD86: #NULL! | AE86: #NULL! | AF86: #NULL! | AG86: #NULL! | AI86: #NULL! | AJ86: #NULL! | AK86: #NULL! | AL86: #NULL! | AN86: #NULL! | AO86: #NULL! | AP86: #NULL! | AQ86: #NULL! | AS86: #NULL! | AT86: #NULL! | AU86: #NULL! | AV86: #NULL! | AX86: #NULL! | AY86: #NULL! | AZ86: #NULL! | BA86: #NULL! | BB86: Hold time is always so long! | BC86: 2 | BD86: #NULL! | BE86: #NULL! | BF86: #NULL! | BH86: #NULL! | BI86: #NULL! | BJ86: #NULL! | BK86: #NULL! | BL86: 2 | BM86: 9 | BN86: I think it was tinny music | BO86: 20 | BP86: #NULL! | BQ86: #NULL! | BR86: #NULL! | BS86: 1 | BT86: Would prefer to have quiet on hold times so I can get a little work done while I wait | BU86: 21 | BV86: #NULL! | BW86: #NULL! | BX86: #NULL! | BZ86: #NULL! | CA86: #NULL! | CB86: #NULL! | CC86: 1 | CD86: 5 | CE86: 1 | CF86: 1 | CG86: 2 | CH86: I am a property manager. Often when I call in to request to start service, the attendant transfers me immediately to "commercial" and then I wait on hold again, then get transferred back to residential. It is maddening! | CI86: 1 | CJ86: #NULL! | CK86: #NULL! | CL86: 3 | CM86: Let me explain why I am calling before transferring me!!!!!! | CN86: 1 | CO86: #NULL! | CP86: #NULL! | CQ86: 2 | CR86: #NULL! | CS86: 7 | CT86: 5 | CU86: 5 | CV86: 3 | CW86: 3 | CX86: 8 | CY86: 2 | CZ86: Sometimes it feels like the reps just don't care or are brand new and don't know the answers. | DA86: 4 | DB86: #NULL! | DC86: 3 | DD86: 0 | DE86: 0 | DF86: 0 | DG86: 0 | DH86: 0 | DI86: 0 | DJ86: 1 | DK86: 0 | DL86: 0 | DN86: 1 | DP86: #NULL! | DQ86: #NULL! | DR86: #NULL! | DT86: #NULL! | DU86: #NULL! | DV86: #NULL! | DW86: 1 | DX86: 2 | DZ86: #NULL! | EA86: #NULL! | EI86: #NULL! | EJ86: #NULL! | EK86: #NULL! | EL86: #NULL! | EM86: 7 | EN86: 1 | EP86: 1 | EQ86: 1 | ER86: 2 | ES86: 78749 | ET86: 2 | EU86: 5 | EV86: 6 | EW86: 5 | EX86: 2 | EY86: Theresa | EZ86: Bastian | FB86: theresa@letsmoveaustin.com | FC86: 5122973442 | FD86: #NULL! | FE86: #NULL! | FF86: 2 | FH86: 16 Sep 2025 - 14:49:49 CDT | FI86: 9943
A87: 526 | B87: 1 | C87: 2 | D87: 1 | E87: #NULL! | F87: 2 | G87: 2 | H87: 2 | J87: 1 | K87: 2 | P87: #NULL! | Q87: #NULL! | R87: #NULL! | S87: #NULL! | T87: 10 | U87: 10 | V87: 10 | W87: 10 | Y87: #NULL! | Z87: #NULL! | AA87: #NULL! | AB87: #NULL! | AC87: 10 | AD87: #NULL! | AE87: #NULL! | AF87: #NULL! | AG87: #NULL! | AI87: #NULL! | AJ87: #NULL! | AK87: #NULL! | AL87: #NULL! | AM87: 10 | AN87: #NULL! | AO87: #NULL! | AP87: #NULL! | AQ87: #NULL! | AS87: #NULL! | AT87: #NULL! | AU87: #NULL! | AV87: #NULL! | AW87: 10 | AX87: #NULL! | AY87: #NULL! | AZ87: #NULL! | BA87: #NULL! | BC87: #NULL! | BD87: #NULL! | BE87: #NULL! | BF87: #NULL! | BG87: 10 | BH87: #NULL! | BI87: #NULL! | BJ87: #NULL! | BK87: #NULL! | BL87: 2 | BM87: 4 | BN87: Don't remember | BO87: 98 | BP87: #NULL! | BQ87: #NULL! | BR87: #NULL! | BS87: 7 | BT87: Not sure. I rarely call Austin energy. | BU87: 98 | BV87: #NULL! | BW87: #NULL! | BX87: #NULL! | BZ87: #NULL! | CA87: #NULL! | CB87: #NULL! | CC87: 2 | CD87: #NULL! | CE87: 2 | CF87: #NULL! | CG87: #NULL! | CI87: #NULL! | CJ87: #NULL! | CK87: #NULL! | CL87: #NULL! | CN87: #NULL! | CO87: #NULL! | CP87: #NULL! | CQ87: 2 | CR87: #NULL! | CS87: 10 | CT87: 10 | CU87: 10 | CV87: 10 | CW87: 10 | CX87: 10 | CY87: 10 | DA87: #NULL! | DB87: #NULL! | DC87: 10 | DD87: #NULL! | DE87: #NULL! | DF87: #NULL! | DG87: #NULL! | DH87: #NULL! | DI87: #NULL! | DJ87: #NULL! | DK87: #NULL! | DL87: #NULL! | DN87: 1 | DP87: #NULL! | DQ87: #NULL! | DR87: #NULL! | DT87: #NULL! | DU87: #NULL! | DV87: #NULL! | DW87: 2 | DX87: 3 | DZ87: #NULL! | EA87: #NULL! | EI87: #NULL! | EJ87: #NULL! | EK87: #NULL! | EL87: #NULL! | EM87: 10 | EN87: 1 | EP87: 5 | EQ87: 3 | ER87: 2 | ES87: 78758 | ET87: 1 | EU87: 3 | EV87: 4 | EW87: 5 | EX87: 2 | EY87: Sharon | EZ87: Zakes | FB87: Sharon2816@hotmail.com | FC87: 5127516959 | FD87: #NULL! | FE87: #NULL! | FF87: 3 | FH87: 16 Sep 2025 - 15:24:11 CDT | FI87: 24515
A88: 532 | B88: 1 | C88: 2 | D88: 1 | E88: #NULL! | F88: 2 | G88: 2 | H88: 1 | J88: 2 | K88: 20 | O88: My recycle (green can) was not picked up. Resident at same address for 32 years and this has been a reoccurring issue. | P88: 12 | Q88: #NULL! | R88: #NULL! | S88: #NULL! | T88: 9 | U88: 9 | V88: 9 | W88: 8 | Y88: #NULL! | Z88: #NULL! | AA88: #NULL! | AB88: #NULL! | AC88: Only had a couple of buttons to push | AD88: 27 | AE88: #NULL! | AF88: #NULL! | AG88: #NULL! | AI88: #NULL! | AJ88: #NULL! | AK88: #NULL! | AL88: #NULL! | AM88: Information available, but no corrective action | AN88: 7 | AO88: 6 | AP88: #NULL! | AQ88: #NULL! | AS88: #NULL! | AT88: #NULL! | AU88: #NULL! | AV88: #NULL! | AW88: Prefer the phone. Hate apps | AX88: 3 | AY88: #NULL! | AZ88: #NULL! | BA88: #NULL! | BC88: #NULL! | BD88: #NULL! | BE88: #NULL! | BF88: #NULL! | BG88: Wait did not seem very long at all | BH88: 21 | BI88: #NULL! | BJ88: #NULL! | BK88: #NULL! | BL88: 2 | BM88: 3 | BN88: I don't recall, as I was thinking about why I have to push "1 for English" when I live in the use | BO88: 99 | BP88: #NULL! | BQ88: #NULL! | BR88: #NULL! | BS88: 10 | BT88: None | BU88: 97 | BV88: #NULL! | BW88: #NULL! | BX88: #NULL! | BZ88: #NULL! | CA88: #NULL! | CB88: #NULL! | CC88: 1 | CD88: 8 | CE88: 2 | CF88: #NULL! | CG88: #NULL! | CI88: #NULL! | CJ88: #NULL! | CK88: #NULL! | CL88: #NULL! | CN88: #NULL! | CO88: #NULL! | CP88: #NULL! | CQ88: 2 | CR88: #NULL! | CS88: 10 | CT88: 10 | CU88: 10 | CV88: 8 | CW88: 10 | CX88: 10 | CY88: 10 | DA88: #NULL! | DB88: #NULL! | DC88: 1 | DD88: 0 | DE88: 1 | DF88: 0 | DG88: 0 | DH88: 0 | DI88: 0 | DJ88: 0 | DK88: 0 | DL88: 0 | DN88: 1 | DP88: #NULL! | DQ88: #NULL! | DR88: #NULL! | DT88: #NULL! | DU88: #NULL! | DV88: #NULL! | DW88: 1 | DX88: 3 | DZ88: #NULL! | EA88: #NULL! | EI88: #NULL! | EJ88: #NULL! | EK88: #NULL! | EL88: #NULL! | EM88: 10 | EN88: 1 | EP88: 5 | EQ88: 1 | ER88: 2 | ES88: 78759 | ET88: 2 | EU88: 3 | EV88: 8 | EW88: 5 | EX88: 1 | EY88: Ron | EZ88: Engel | FB88: norlegne@yahoo.com | FC88: 5123318756 | FD88: #NULL! | FE88: #NULL! | FF88: 1 | FH88: 16 Sep 2025 - 16:31:22 CDT | FI88: 6660
A89: 537 | B89: 1 | C89: 2 | D89: 1 | E89: #NULL! | F89: 2 | G89: 2 | H89: 3 | J89: 1 | K89: 21 | N89: Water cycle | P89: #NULL! | Q89: #NULL! | R89: #NULL! | S89: #NULL! | T89: 10 | U89: 10 | V89: 10 | W89: 8 | Y89: #NULL! | Z89: #NULL! | AA89: #NULL! | AB89: #NULL! | AC89: Good | AD89: 20 | AE89: #NULL! | AF89: #NULL! | AG89: #NULL! | AI89: #NULL! | AJ89: #NULL! | AK89: #NULL! | AL89: #NULL! | AM89: Good | AN89: 28 | AO89: #NULL! | AP89: #NULL! | AQ89: #NULL! | AS89: #NULL! | AT89: #NULL! | AU89: #NULL! | AV89: #NULL! | AW89: Good | AX89: 28 | AY89: #NULL! | AZ89: #NULL! | BA89: #NULL! | BC89: #NULL! | BD89: #NULL! | BE89: #NULL! | BF89: #NULL! | BG89: Good | BH89: 28 | BI89: #NULL! | BJ89: #NULL! | BK89: #NULL! | BL89: 2 | BM89: 7 | BN89: Don’t recall | BO89: 98 | BP89: #NULL! | BQ89: #NULL! | BR89: #NULL! | BS89: 10 | BT89: Time and reason for wait | BU89: 6 | BV89: #NULL! | BW89: #NULL! | BX89: #NULL! | BZ89: #NULL! | CA89: #NULL! | CB89: #NULL! | CC89: 2 | CD89: #NULL! | CE89: 2 | CF89: #NULL! | CG89: #NULL! | CI89: #NULL! | CJ89: #NULL! | CK89: #NULL! | CL89: #NULL! | CN89: #NULL! | CO89: #NULL! | CP89: #NULL! | CQ89: 2 | CR89: #NULL! | CS89: 8 | CT89: 8 | CU89: 8 | CV89: 8 | CW89: 8 | CX89: 10 | CY89: 8 | DA89: #NULL! | DB89: #NULL! | DC89: 9 | DD89: #NULL! | DE89: #NULL! | DF89: #NULL! | DG89: #NULL! | DH89: #NULL! | DI89: #NULL! | DJ89: #NULL! | DK89: #NULL! | DL89: #NULL! | DN89: 1 | DP89: #NULL! | DQ89: #NULL! | DR89: #NULL! | DT89: #NULL! | DU89: #NULL! | DV89: #NULL! | DW89: 2 | DX89: 2 | DZ89: #NULL! | EA89: #NULL! | EI89: #NULL! | EJ89: #NULL! | EK89: #NULL! | EL89: #NULL! | EM89: 10 | EN89: 3 | EP89: 5 | EQ89: 1 | ER89: 2 | ES89: 78758 | ET89: 3 | EU89: 3 | EV89: 6 | EW89: 5 | EX89: 1 | EY89: Joel | EZ89: Navarro | FB89: Joel.Navarro913@gmail.com | FC89: 512-913-6485 | FD89: #NULL! | FE89: #NULL! | FF89: 3 | FH89: 16 Sep 2025 - 17:15:40 CDT | FI89: 25245
A90: 539 | B90: 1 | C90: 2 | D90: 1 | E90: #NULL! | F90: 2 | G90: 2 | H90: 4 | I90: All of the above | J90: 1 | K90: 31 | N90: My mother's city of Austin account | P90: #NULL! | Q90: #NULL! | R90: #NULL! | S90: #NULL! | T90: 8 | U90: 8 | V90: 8 | W90: 8 | Y90: #NULL! | Z90: #NULL! | AA90: #NULL! | AB90: #NULL! | AC90: Pretty much | AD90: 20 | AE90: #NULL! | AF90: #NULL! | AG90: #NULL! | AI90: #NULL! | AJ90: #NULL! | AK90: #NULL! | AL90: #NULL! | AM90: Still needed to talk to a person | AN90: 99 | AO90: #NULL! | AP90: #NULL! | AQ90: #NULL! | AS90: #NULL! | AT90: #NULL! | AU90: #NULL! | AV90: #NULL! | AW90: Took me awhile but I eventually got someone to help me with my issue | AX90: 22 | AY90: #NULL! | AZ90: #NULL! | BA90: #NULL! | BC90: #NULL! | BD90: #NULL! | BE90: #NULL! | BF90: #NULL! | BG90: Took a couple days but was not time sensitive within reason | BH90: 21 | BI90: #NULL! | BJ90: #NULL! | BK90: #NULL! | BL90: 4 | BM90: #NULL! | BO90: #NULL! | BP90: #NULL! | BQ90: #NULL! | BR90: #NULL! | BS90: #NULL! | BU90: #NULL! | BV90: #NULL! | BW90: #NULL! | BX90: 8 | BZ90: #NULL! | CA90: #NULL! | CB90: #NULL! | CC90: 2 | CD90: #NULL! | CE90: 1 | CF90: 1 | CG90: 2 | CH90: Changing responsibility for my mother's city of Austin account | CI90: 99 | CJ90: #NULL! | CK90: #NULL! | CL90: 5 | CM90: Actually had to be handled by email | CN90: 99 | CO90: #NULL! | CP90: #NULL! | CQ90: 1 | CR90: 8 | CS90: 8 | CT90: 8 | CU90: 5 | CV90: 11 | CW90: 8 | CX90: 8 | CY90: 8 | DA90: #NULL! | DB90: #NULL! | DC90: 8 | DD90: #NULL! | DE90: #NULL! | DF90: #NULL! | DG90: #NULL! | DH90: #NULL! | DI90: #NULL! | DJ90: #NULL! | DK90: #NULL! | DL90: #NULL! | DN90: 2 | DO90: Not sure, my request was probably not very common. | DP90: 98 | DQ90: #NULL! | DR90: #NULL! | DT90: #NULL! | DU90: #NULL! | DV90: #NULL! | DW90: 2 | DX90: 2 | DZ90: #NULL! | EA90: #NULL! | EI90: #NULL! | EJ90: #NULL! | EK90: #NULL! | EL90: #NULL! | EM90: 10 | EN90: 1 | EP90: 5 | EQ90: 2 | ER90: 2 | ES90: 78758 | ET90: 1 | EU90: 5 | EV90: 8 | EW90: 5 | EX90: 1 | EY90: Tom | EZ90: Flynn | FB90: trflynn@jtan.com | FC90: (512) 837-0949 | FD90: #NULL! | FE90: #NULL! | FF90: 1 | FH90: 16 Sep 2025 - 17:29:11 CDT | FI90: 4314
